Workbook

Sheet PLANTILLAS 
B3: PASTA CARBONARA | H3: PASTA CARBONARA | N3: PASTA CARBONARA
B4: INGREDIENTES | C4: CANTIDAD | D4: UND MEDIDA | E4: COS/GR | F4: VALOR | H4: INGREDIENTES | I4: CANTIDAD | J4: UND MEDIDA | K4: COS/GR | L4: VALOR | N4: INGREDIENTES | O4: CANTIDAD | P4: UND MEDIDA | Q4: COS/GR | R4: VALOR
D5: gr | F5: =C5*E5 -> 0 | J5: gr | L5: =I5*K5 -> 0 | P5: gr | R5: =O5*Q5 -> 0
D6: gr | F6: =C6*E6 -> 0 | J6: gr | L6: =I6*K6 -> 0 | P6: gr | R6: =O6*Q6 -> 0
D7: gr | F7: =C7*E7 -> 0 | J7: gr | L7: =I7*K7 -> 0 | P7: gr | R7: =O7*Q7 -> 0
D8: gr | F8: =C8*E8 -> 0 | J8: gr | L8: =I8*K8 -> 0 | P8: gr | R8: =O8*Q8 -> 0
D9: gr | F9: =C9*E9 -> 0 | J9: gr | L9: =I9*K9 -> 0 | P9: gr | R9: =O9*Q9 -> 0
D10: gr | F10: =C10*E10 -> 0 | J10: gr | L10: =I10*K10 -> 0 | P10: gr | R10: =O10*Q10 -> 0
D11: gr | F11: =C11*E11 -> 0 | J11: gr | L11: =I11*K11 -> 0 | P11: gr | R11: =O11*Q11 -> 0
F12: =C12*E12 -> 0 | L12: =I12*K12 -> 0 | R12: =O12*Q12 -> 0
F13: =C13*E13 -> 0 | L13: =I13*K13 -> 0 | R13: =O13*Q13 -> 0
B14: MATERIAL DE EMPAQUE | H14: MATERIAL DE EMPAQUE | N14: MATERIAL DE EMPAQUE
F15: =C15*140 -> 0 | L15: =I15*140 -> 0 | R15: =O15*140 -> 0
F16: =C16*140 -> 0 | L16: =I16*140 -> 0 | R16: =O16*140 -> 0
F17: =C17*140 -> 0 | L17: =I17*140 -> 0 | R17: =O17*140 -> 0
B18: COSTO + PRECIO DE VENTA | H18: COSTO + PRECIO DE VENTA | N18: COSTO + PRECIO DE VENTA
B19: COSTO DE INGREDIENTES | F19: =(F5+F6+F7+F8+F9+F10+F11+F12+F13+F17) -> 0 | H19: COSTO DE INGREDIENTES | L19: =(L5+L6+L7+L8+L9+L10+L11+L12+L13+L17) -> 0 | N19: COSTO DE INGREDIENTES | R19: =(R5+R6+R7+R8+R9+R10+R11+R12+R13+R17) -> 0
B20: MARGEN DE ERROR O VARIACION 10% | F20: =F19*0.1 -> 0 | H20: MARGEN DE ERROR O VARIACION 10% | L20: =L19*0.1 -> 0 | N20: MARGEN DE ERROR O VARIACION 10% | R20: =R19*0.1 -> 0
B21: COSTO TOTAL DE LA PREPARACION | F21: =SUM(F19:F20) -> 0 | H21: COSTO TOTAL DE LA PREPARACION | L21: =SUM(L19:L20) -> 0 | N21: COSTO TOTAL DE LA PREPARACION | R21: =SUM(R19:R20) -> 0
B22: PRECIO DE VENTA | F22: 30000 | H22: PRECIO DE VENTA | L22: 30000 | N22: PRECIO DE VENTA | R22: 30000
B25: PASTA CARBONARA | H25: PASTA CARBONARA | N25: PASTA CARBONARA
B26: INGREDIENTES | C26: CANTIDAD | D26: UND MEDIDA | E26: COS/GR | F26: VALOR | H26: INGREDIENTES | I26: CANTIDAD | J26: UND MEDIDA | K26: COS/GR | L26: VALOR | N26: INGREDIENTES | O26: CANTIDAD | P26: UND MEDIDA | Q26: COS/GR | R26: VALOR
D27: gr | F27: =C27*E27 -> 0 | J27: gr | L27: =I27*K27 -> 0 | P27: gr | R27: =O27*Q27 -> 0
D28: gr | F28: =C28*E28 -> 0 | J28: gr | L28: =I28*K28 -> 0 | P28: gr | R28: =O28*Q28 -> 0
D29: gr | F29: =C29*E29 -> 0 | J29: gr | L29: =I29*K29 -> 0 | P29: gr | R29: =O29*Q29 -> 0
D30: gr | F30: =C30*E30 -> 0 | J30: gr | L30: =I30*K30 -> 0 | P30: gr | R30: =O30*Q30 -> 0
D31: gr | F31: =C31*E31 -> 0 | J31: gr | L31: =I31*K31 -> 0 | P31: gr | R31: =O31*Q31 -> 0
D32: gr | F32: =C32*E32 -> 0 | J32: gr | L32: =I32*K32 -> 0 | P32: gr | R32: =O32*Q32 -> 0
D33: gr | F33: =C33*E33 -> 0 | J33: gr | L33: =I33*K33 -> 0 | P33: gr | R33: =O33*Q33 -> 0
F34: =C34*E34 -> 0 | L34: =I34*K34 -> 0 | R34: =O34*Q34 -> 0
F35: =C35*E35 -> 0 | L35: =I35*K35 -> 0 | R35: =O35*Q35 -> 0
B36: MATERIAL DE EMPAQUE | H36: MATERIAL DE EMPAQUE | N36: MATERIAL DE EMPAQUE
F37: =C37*140 -> 0 | L37: =I37*140 -> 0 | R37: =O37*140 -> 0
F38: =C38*140 -> 0 | L38: =I38*140 -> 0 | R38: =O38*140 -> 0
F39: =C39*140 -> 0 | L39: =I39*140 -> 0 | R39: =O39*140 -> 0
B40: COSTO + PRECIO DE VENTA | H40: COSTO + PRECIO DE VENTA | N40: COSTO + PRECIO DE VENTA
B41: COSTO DE INGREDIENTES | F41: =(F27+F28+F29+F30+F31+F32+F33+F34+F35+F39) -> 0 | H41: COSTO DE INGREDIENTES | L41: =(L27+L28+L29+L30+L31+L32+L33+L34+L35+L39) -> 0 | N41: COSTO DE INGREDIENTES | R41: =(R27+R28+R29+R30+R31+R32+R33+R34+R35+R39) -> 0
B42: MARGEN DE ERROR O VARIACION 10% | F42: =F41*0.1 -> 0 | H42: MARGEN DE ERROR O VARIACION 10% | L42: =L41*0.1 -> 0 | N42: MARGEN DE ERROR O VARIACION 10% | R42: =R41*0.1 -> 0
B43: COSTO TOTAL DE LA PREPARACION | F43: =SUM(F41:F42) -> 0 | H43: COSTO TOTAL DE LA PREPARACION | L43: =SUM(L41:L42) -> 0 | N43: COSTO TOTAL DE LA PREPARACION | R43: =SUM(R41:R42) -> 0
B44: PRECIO DE VENTA | F44: 30000 | H44: PRECIO DE VENTA | L44: 30000 | N44: PRECIO DE VENTA | R44: 30000
B47: PASTA CARBONARA | H47: PASTA CARBONARA | N47: PASTA CARBONARA
B48: INGREDIENTES | C48: CANTIDAD | D48: UND MEDIDA | E48: COS/GR | F48: VALOR | H48: INGREDIENTES | I48: CANTIDAD | J48: UND MEDIDA | K48: COS/GR | L48: VALOR | N48: INGREDIENTES | O48: CANTIDAD | P48: UND MEDIDA | Q48: COS/GR | R48: VALOR
D49: gr | F49: =C49*E49 -> 0 | J49: gr | L49: =I49*K49 -> 0 | P49: gr | R49: =O49*Q49 -> 0
D50: gr | F50: =C50*E50 -> 0 | J50: gr | L50: =I50*K50 -> 0 | P50: gr | R50: =O50*Q50 -> 0
D51: gr | F51: =C51*E51 -> 0 | J51: gr | L51: =I51*K51 -> 0 | P51: gr | R51: =O51*Q51 -> 0
D52: gr | F52: =C52*E52 -> 0 | J52: gr | L52: =I52*K52 -> 0 | P52: gr | R52: =O52*Q52 -> 0
D53: gr | F53: =C53*E53 -> 0 | J53: gr | L53: =I53*K53 -> 0 | P53: gr | R53: =O53*Q53 -> 0
D54: gr | F54: =C54*E54 -> 0 | J54: gr | L54: =I54*K54 -> 0 | P54: gr | R54: =O54*Q54 -> 0
D55: gr | F55: =C55*E55 -> 0 | J55: gr | L55: =I55*K55 -> 0 | P55: gr | R55: =O55*Q55 -> 0
F56: =C56*E56 -> 0 | L56: =I56*K56 -> 0 | R56: =O56*Q56 -> 0
F57: =C57*E57 -> 0 | L57: =I57*K57 -> 0 | R57: =O57*Q57 -> 0
B58: MATERIAL DE EMPAQUE | H58: MATERIAL DE EMPAQUE | N58: MATERIAL DE EMPAQUE
F59: =C59*140 -> 0 | L59: =I59*140 -> 0 | R59: =O59*140 -> 0
F60: =C60*140 -> 0 | L60: =I60*140 -> 0 | R60: =O60*140 -> 0
F61: =C61*140 -> 0 | L61: =I61*140 -> 0 | R61: =O61*140 -> 0
B62: COSTO + PRECIO DE VENTA | H62: COSTO + PRECIO DE VENTA | N62: COSTO + PRECIO DE VENTA
B63: COSTO DE INGREDIENTES | F63: =(F49+F50+F51+F52+F53+F54+F55+F56+F57+F61) -> 0 | H63: COSTO DE INGREDIENTES | L63: =(L49+L50+L51+L52+L53+L54+L55+L56+L57+L61) -> 0 | N63: COSTO DE INGREDIENTES | R63: =(R49+R50+R51+R52+R53+R54+R55+R56+R57+R61) -> 0
B64: MARGEN DE ERROR O VARIACION 10% | F64: =F63*0.1 -> 0 | H64: MARGEN DE ERROR O VARIACION 10% | L64: =L63*0.1 -> 0 | N64: MARGEN DE ERROR O VARIACION 10% | R64: =R63*0.1 -> 0
B65: COSTO TOTAL DE LA PREPARACION | F65: =SUM(F63:F64) -> 0 | H65: COSTO TOTAL DE LA PREPARACION | L65: =SUM(L63:L64) -> 0 | N65: COSTO TOTAL DE LA PREPARACION | R65: =SUM(R63:R64) -> 0
B66: PRECIO DE VENTA | F66: 30000 | H66: PRECIO DE VENTA | L66: 30000 | N66: PRECIO DE VENTA | R66: 30000

Sheet ENTREGABLES
B2: La biblia de los productos
B3: Costos de la receta
B4: Lista de Proveedores
B5: Capacitar al equipo

Sheet PRECIOS
A1: PRECIOS COMPRA DE PLANTA
A2: PROVEEDOR | B2: I/S | C2: PRODUCTO/INSUMO | D2: PROVEEDOR / PRECIO COMPRA | E2: PROVEEDOR / PRECIO COMPRA | F2: PROVEEDOR / PRECIO COMPRA | G2: PROVEEDOR / PRECIO COMPRA | H2: PROVEEDOR / PRECIO COMPRA | I2: PROVEEDOR / PRECIO COMPRA | J2: PROVEEDOR / PRECIO COMPRA | K2: PESO | L2: UNIDAD MEDIDA | M2: VALOR DEL GRAMO
C3: CARNES | D3: El Gran Langostino | E3: Choridanni | F3: LA 27 | G3: Supertiendas Cañaveral | H3: Cervalle | I3: Distribuidora Monos | J3: Comercializadora Malta
A4: Distribuidora Monos | C4: LOMO VICHE ESPECIAL | I4: 47900 | J4: 56000 | K4: 1000 | L4: GR | M4: =I4/K4 -> 47.9
A5: Distribuidora Monos | C5: MOLIDA CORTES FINOS X 3970 SN | I5: 21900 | K5: 1000 | L5: GR | M5: =I5/K5 -> 21.9
A6: Distribuidora Monos | C6: MOLIDA DE RES NACIONAL X 4180 SR | I6: 20500 | K6: 1000 | L6: GR | M6: =I6/K6 -> 20.5
A7: Distribuidora Monos | C7: COSTILLA DE CERDO LLANERA X 4955 | I7: 19900 | K7: 1000 | L7: GR | M7: =I7/K7 -> 19.9
A8: Distribuidora Monos | C8: TOCINETA AHUMADA COCIDA | I8: 26900 | K8: 1000 | L8: GR | M8: =I8/K8 -> 26.9
A9: Distribuidora Monos | C9: PUNTA DE ANCA URUGUAYA X 1000 GR | I9: 57900
A10: Distribuidora Monos | C10: LOMO CARACHA ANGUS URUGUAYA 1000 GR | I10: 45900.11
A11: Supertiendas Cañaveral | C11: PERNIL MCPOLLO CAMPO | G11: 9400 | J11: 8500 | K11: 1000 | L11: GR | M11: =G11/K11 -> 9.4
A12: Supertiendas Cañaveral | C12: PUNTA DE ANCA MADURADA X 1000 GR DIA | G12: 64000 | J12: 47800 | K12: 1000 | L12: GR | M12: =I12/K12 -> 0
A13: Supertiendas Cañaveral | C13: LOMO CARACHA 1000 chatA DIA | G13: 54000 | J13: 44200 | K13: 1000 | L13: GR | M13: =G13/K13 -> 54
A14: Cervalle | C14: BONDIOLA X 1000 GR | H14: 23550 | K14: 1001 | L14: GR | M14: =I14/K14 -> 0
A15: El Gran Langostino | C15: PULPO GRD X1000 | D15: 63500 | K15: 1000 | L15: GR | M15: =D15/K15 -> 63.5
A16: Choridanni | C16: CHORIZO PARRILLERO X 5 | E16: 13450 | K16: 5 | L16: GR | M16: =I16/K16 -> 0
A17: Porcicarnes | C17: CHICHARON BARRIGUERO X 1000 | I17: 33270 | J17: 25400 | K17: 1000 | L17: GR | M17: =J17/K17 -> 25.4
A18: La 27 | C18: TOCINETA ARTESANAL X 1000 GR | F18: 23000 | K18: 1000 | L18: GR | M18: =I18/K18 -> 0
A19: La 27 | C19: JAMON CALIMA 500 GR | F19: 5238.1 | K19: 500 | L19: GR | M19: =I19/K19 -> 0
C22: LACTEOS | D22: LA 27 | E22: Quesos Don Luis | F22: Mercar
C23: QUESO COSTEÑO | E23: 11000
C24: QUESO MOZARELLA X 2500 | D24: 48800 | E24: 54000 | K24: 2500 | L24: GR | M24: =I24/K24 -> 0
C25: QUESO TAJADO SANT ELENA X 2500 GR | D25: 48800 | E25: 53000
C26: CREMA DE LECHE X 850 ML | F26: 17950 | K26: 850 | L26: GR | M26: =F26/K26 -> 21.117647
C27: LECHERA X 2000 ML | E27: 27000 | K27: 2000 | L27: ML | M27: =E27/K27 -> 13.5
C28: PAPAS | D28: Supertiendas Cañaveral | E28: Distribuidora Monos
A29: Supertiendas Cañaveral | C29: PAPA AMARILLA | D29: 4200 | K29: 1000 | L29: GR | M29: =I29/K29 -> 0
A30: Distribuidora Monos | C30: PAPAS A LA FRANCESA X 3000 | E30: 20500 | K30: 3000 | L30: GR | M30: =J30/K30 -> 0
C31: PAN | D31: LA 27 | E31: Distribuidora Monos | F31: D1 | G31: Pan Wich
C32: PAN HAMBURGUESA GOURMET AJONJ X 8 | E32: 8400 | K32: 8 | L32: UND | M32: =I32/K32 -> 0
A33: Distribuidora Monos | C33: PAN HAMBURGUESA LISO BRIOCHE X 8 | E33: 8400 | K33: 8 | L33: UND | M33: =I33/K33 -> 0
C34: PAN HAMBURGUESA X 10 | G34: 7800
A35: La 27 | C35: PAN TAJADO BIMBO | D35: 6500 | F35: 3250 | K35: 1 | L35: PAQ | M35: =I35/K35 -> 0
C36: BEBIDAS Y LICORES | D36: Licores Palmira | E36: Empresarial Giraldo | M36: =I36/K36 -> #DIV/0!
A37: Licores palmira | C37: VINO CATA TINTO X 1000 | D37: 20500 | E37: 19399 | K37: 1000 | L37: ML | M37: =I37/K37 -> 0
A38: Licores palmira | C38: TEQUILA JOSE CUERVO X 700 | D38: 69900 | E38: 79900 | K38: 700 | L38: ML | M38: =I38/K38 -> 0
A39: Licores palmira | C39: TEQUILA OLMECA X 700 | D39: 73400 | K39: 700 | L39: ML | M39: =I39/K39 -> 0
C40: VODKA ADSOLUT BLUE X 700 ML | E40: 77000
A41: Licores palmira | C41: MARTINI ROSSO X 750 | D41: 63800 | K41: 750 | L41: ML | M41: =I41/K41 -> 0
A42: Licores palmira | C42: AGUARDIENTE BLANCO TR X 750 | D42: 39500 | E42: 39100 | K42: 750 | L42: ML | M42: =I42/K42 -> 0
C43: AGUARDIENTE BLANCO FIESTA X 375 ML | E43: 21050
A44: Licores palmira | C44: BRANDY 5 ESTRELLAS X 700 | D44: 44500 | E44: 42000 | K44: 700 | L44: ML | M44: =I44/K44 -> 0
A45: Licores palmira | C45: RON BACARDI X 750 | D45: 49600 | K45: 750 | L45: ML | M45: =I45/K45 -> 0
C46: RON VC X 375 ML | E46: 19799
A47: Licores palmira | C47: CERVEZA CORONA 330 ML | D47: 3787.5 | E47: 3333.29 | K47: 1 | L47: UND | M47: =I47/K47 -> 0
A48: Licores palmira | C48: GAS COCA COLA 400 ML X12 | D48: 2500 | K48: 1 | L48: UND | M48: =I48/K48 -> 0
A49: Licores palmira | C49: GAS SODA 1.5 X 12 | D49: 3750 | K49: 1 | L49: UND | M49: =I49/K49 -> 0
A50: Licores palmira | C50: GAS GINGER 1.5 X 12 | D50: 4300 | K50: 1 | L50: UND | M50: =I50/K50 -> 0
A51: Licores palmira | C51: GAS SODA 300 ML X 24 | D51: 2120.83 | E51: 2300 | K51: 1 | L51: UND | M51: =I51/K51 -> 0
A52: Licores palmira | C52: GAS GINGER 300 ML X 24 | D52: 2120 | K52: 1 | L52: UND | M52: =I52/K52 -> 0
C53: AGUA MIA X 600 CC | E53: 800
A54: Licores palmira | C54: AGUA BRISA 600 ML X 24 | D54: 1333.33 | K54: 1 | L54: UND | M54: =I54/K54 -> 0
C55: WHISKY JACK DANIELS | D55: 118000 | E55: 105000
A56: Valhalla | C56: ZUMO DE LIMON X 1000 ML | D56: 10000 | K56: 1000 | L56: ML | M56: =I56/K56 -> 0
C57: HOTBORT LYCHE X 1100 ML | E57: 22100 | K57: 1100 | M57: =I57/K57 -> 0
C58: HOTBORT GRANADINE X 1100 ML | E58: 22100 | K58: 1100 | L58: ML | M58: =I58/K58 -> 0
C59: LICOR BRISAR BLUE T/SEC X 750 ML | E59: 31750 | K59: 750 | L59: ML | M59: =I59/K59 -> 0
C60: LYCHE EL FORTIN LATA X 567 | E60: 13400 | K60: 567 | L60: ML | M60: =I60/K60 -> 0
C61: VINO CATA BLANCO X 1000 ML | E61: 19500 | K61: 1000 | L61: ML | M61: =I61/K61 -> 0
C62: BEBIDA GATORADE X 500 ML | E62: 3300 | K62: 500 | L62: ML | M62: =I62/K62 -> 0
C63: GAS COCA COLA ZERO 400 ML X12 | E63: 2350 | K63: 1 | L63: UND | M63: =I63/K63 -> 0
C64: TEQUILA JIMADOR REPOSADO X700 ML | E64: 94900 | K64: 700 | L64: ML | M64: =I64/K64 -> 0
C65: GINEGRA GORDONS X 700 ML | E65: 66600 | K65: 700 | L65: ML | M65: =I65/K65 -> 0
C66: CERVEZA CLUB COL DOR X 330 ML | E66: 3250 | K66: 330 | L66: ML | M66: =I66/K66 -> 0
L67: ML | M67: =I67/K67 -> #DIV/0!
L68: ML | M68: =I68/K68 -> #DIV/0!
L69: ML | M69: =I69/K69 -> #DIV/0!
A72: POSTRES | M72: =I72/K72 -> #DIV/0!
A73: Deleite pastelerias | C73: CHEESECAKE X 500 GR | I73: 60000 | K73: 8 | L73: GR | M73: =I73/K73 -> 7500
A74: Deleite pastelerias | C74: TARTA DE QUESO | I74: 72000 | K74: 8 | L74: GR | M74: =I74/K74 -> 9000
A75: Deleite pastelerias | C75: SALSA DE FRUTOS ROJOS | I75: 20000 | K75: 50 | L75: GR | M75: =I75/K75 -> 400
A76: Deleite pastelerias | C76: SALSA DE AGRAS | I76: 20000 | K76: 50 | L76: GR | M76: =I76/K76 -> 400
A77: Deleite pastelerias | C77: SALSA DE FRUTOS AMARILLOS | I77: 20000 | K77: 50 | L77: GR | M77: =I77/K77 -> 400
C79: FRUTAS Y VERDURAS | D79: Supertiendas Cañaveral | E79: Solo Frutas
A80: Supertiendas Cañaveral | C80: MANZANA VERDE X 1000 GR | D80: 10400 | K80: 1000 | L80: GR | M80: =I80/K80 -> 0
A81: Supertiendas Cañaveral | C81: HIERBAS SURTIDAS | D81: 950 | K81: 1 | L81: UND | M81: =I81/K81 -> 0
A82: Supertiendas Cañaveral | C82: LIMON TAHITI | D82: 3900 | E82: 1980 | K82: 1000 | L82: GR | M82: =E82/K82 -> 1.98
A83: Supertiendas Cañaveral | C83: FRESA BANDEJA X 500 GR | D83: 7750 | K83: 500 | L83: GR | M83: =I83/K83 -> 0
A84: Supertiendas Cañaveral | C84: UVA ISABEL X 400 GR | D84: 3550 | K84: 400 | L84: GR | M84: =I84/K84 -> 0
A85: Supertiendas Cañaveral | C85: NARANJA X 3000 | D85: 7850 | K85: 3000 | L85: PAQ | M85: =I85/K85 -> 0
A86: Supertiendas Cañaveral | C86: LECHUGA BIOFRESCOS | D86: 2750 | K86: 160 | L86: GR | M86: =I86/K86 -> 0
A87: Supertiendas Cañaveral | C87: TOMATE CHERRY X 250GR | D87: 13600 | E87: 4890 | K87: 250 | L87: GR | M87: =E87/K87 -> 19.56
A88: Supertiendas Cañaveral | C88: RUGULA ORTIFRESCO X 150 GR | D88: 4850 | E88: 4980 | K88: 150 | L88: GR | M88: =E88/K88 -> 33.2
A89: Supertiendas Cañaveral | C89: HIERBAS SURTIDAS X 50 GR | D89: 1600 | K89: 50 | L89: GR | M89: =I89/K89 -> 0
A90: Supertiendas Cañaveral | C90: PIÑA ORO MIEL | D90: 3600 | K90: 1000 | L90: GR | M90: =I90/K90 -> 0
A91: Supertiendas Cañaveral | C91: MARACUYA | D91: 5600 | K91: 1000 | L91: GR | M91: =I91/K91 -> 0
A92: Supertiendas Cañaveral | C92: AJO | D92: 11600 | K92: 1000 | L92: GR | M92: =I92/K92 -> 0
A93: Supertiendas Cañaveral | C93: PIMENTON | D93: 4800 | K93: 1000 | L93: GR | M93: =I93/K93 -> 0
A94: Supertiendas Cañaveral | C94: CEBOLLA CABEZONA | D94: 4000 | K94: 1000 | L94: GR | M94: =I94/K94 -> 0
A95: Supertiendas Cañaveral | C95: PLATANO GUAYABO | D95: 4700 | E95: 3580.41 | K95: 1000 | L95: GR | M95: =E95/K95 -> 3.58041
A96: Supertiendas Cañaveral | C96: TOMATE CHONTO | D96: 7800 | K96: 1000 | L96: GR | M96: =I96/K96 -> 0
A97: Supertiendas Cañaveral | C97: LULO | D97: 4900 | K97: 1000 | L97: GR | M97: =I97/K97 -> 0
C98: TOMATE CHERRY X 250 GR | D98: 4400
M101: =I101/K101 -> #DIV/0!
M102: =I102/K102 -> #DIV/0!
M103: =I103/K103 -> #DIV/0!
M111: =I111/K111 -> #DIV/0!
C112: INSUMOS DE ASEO | M112: =I112/K112 -> #DIV/0!
A113: Supertiendas Cañaveral | C113: FIBRA ABRASIVA BONBRIL | D113: 6150 | K113: 1 | L113: UND | M113: =I113/K113 -> 0
A114: Supertiendas Cañaveral | C114: LAVALOZA LAVAMIL 1400 ML | D114: 10800 | K114: 1400 | L114: ML | M114: =I114/K114 -> 0
...

Sheet LISTADO  PRODUCTO
A1: Item | B1: GRUPO | C1: PRODUCTO | D1: Costo ing + Variacion | E1: % Ingredientes + Variacion | F1: Costo EMPAQ | G1: Costo Ing+emp | H1: % Costo Ing + emp | I1: Costo todo con Combo | J1: Precio de venta | K1: precio sin impuesto al consumo | L1: PRECIO DE VENTAS | M1: MARGEN CONTRIBUCION SIN EMP | N1: % CONTRIBUCION SIN EMP | O1: MARGEN CONTRIBUCION + EMP | P1: % CONTRIBUCION + EMP | Q1: PRECIO ACTUAL COMBO | R1: PRECIO PROVIASIONAL COMBO | S1: DIFERENCIA | T1: NUEVO NOMBRE
A2: 1 | B2: CORTES | C2: CHURRASCO | D2: ='CORTES '!F15 -> 23010.9 | E2: =D2/K2 -> 0.4518504 | F2: 0 | G2: =+D2+F2 -> 23010.9 | H2: =G2/K2 -> 0.4518504 | I2: =+D2+F2+H2 -> 23011.352 | J2: ='CORTES '!F16 -> 55000 | K2: =+J2/1.08 -> 50925.926 | L2: =J2 -> 55000 | M2: 0 | N2: =M2/K2 -> 0 | O2: 0 | P2: =O2/K2 -> 0 | Q2: =#REF! -> #REF! | R2: 0
A3: 2 | B3: CORTES | C3: PUNTA DE ANCA | D3: ='CORTES '!L15 -> 33005.5 | E3: =D3/K3 -> 0.7129188 | F3: 0 | G3: =+D3+F3 -> 33005.5 | H3: =G3/K3 -> 0.7129188 | I3: =+D3+F3+H3 -> 33006.213 | J3: ='CORTES '!L16 -> 50000 | K3: =+J3/1.08 -> 46296.296 | L3: =J3 -> 50000 | M3: 0 | N3: =M3/K3 -> 0 | O3: 0 | P3: =O3/K3 -> 0 | Q3: =#REF! -> #REF! | R3: 0
A4: 3 | B4: CORTES | C4: BEBY BEEF | D4: ='CORTES '!R15 -> 20300.5 | E4: =D4/K4 -> 0.34257094 | F4: 0 | G4: =+D4+F4 -> 20300.5 | H4: =G4/K4 -> 0.34257094 | I4: =+D4+F4+H4 -> 20300.843 | J4: ='CORTES '!R16 -> 64000 | K4: =+J4/1.08 -> 59259.259 | L4: =J4 -> 64000 | M4: 0 | N4: =M4/K4 -> 0 | O4: 0 | P4: =O4/K4 -> 0 | Q4: =#REF! -> #REF! | R4: 0
A5: 4 | B5: PICADAS | C5: PICADA MALAGANA X 4 | D5: ='PICADA MALAGANA'!G27 -> 31377.115 | E5: =D5/K5 -> 0.24205203 | F5: 0 | G5: =+D5+F5 -> 31377.115 | H5: =G5/K5 -> 0.24205203 | I5: =+D5+F5+H5 -> 31377.357 | J5: ='PICADA MALAGANA'!G34 -> 140000 | K5: =+J5/1.08 -> 129629.63 | L5: =J5 -> 140000 | M5: 0 | N5: =M5/K5 -> 0 | O5: 0 | P5: =O5/K5 -> 0 | Q5: =#REF! -> #REF! | R5: 0
A6: 5 | B6: PICADAS | C6: PICADA MALAGANA X 2 | D6: ='PICADA MALAGANA'!G60 -> 18306.365 | E6: =D6/K6 -> 0.23259852 | F6: 0 | G6: =+D6+F6 -> 18306.365 | H6: =G6/K6 -> 0.23259852 | I6: =+D6+F6+H6 -> 18306.598 | J6: ='PICADA MALAGANA'!G66 -> 85000 | K6: =+J6/1.08 -> 78703.704 | L6: =J6 -> 85000 | M6: 0 | N6: =M6/K6 -> 0 | O6: 0 | P6: =O6/K6 -> 0 | Q6: =#REF! -> #REF! | R6: 0
A7: 6 | B7: ENTRADAS | C7: CHORIZO PARRILLERO | D7: ='ENTRADAS (2)'!L20 -> 8443.93 | E7: =D7/K7 -> 0.36477778 | F7: 0 | G7: =+D7+F7 -> 8443.93 | H7: =G7/K7 -> 0.36477778 | I7: =+D7+F7+H7 -> 8444.2948 | J7: ='ENTRADAS (2)'!L21 -> 25000 | K7: =+J7/1.08 -> 23148.148 | L7: =J7 -> 25000 | M7: 0 | N7: =M7/K7 -> 0 | O7: 0 | P7: =O7/K7 -> 0 | Q7: =#REF! -> #REF! | R7: 0
A8: 7 | B8: ENTRADAS | C8: ENSALADA FRESCA | D8: ='ENTRADAS (2)'!R20 -> 2423.333 | E8: =D8/K8 -> 0.4026461 | F8: 0 | G8: =+D8+F8 -> 2423.333 | H8: =G8/K8 -> 0.4026461 | I8: =+D8+F8+H8 -> 2423.7356 | J8: ='ENTRADAS (2)'!R21 -> 6500 | K8: =+J8/1.08 -> 6018.5185 | L8: =J8 -> 6500 | M8: 0 | N8: =M8/K8 -> 0 | O8: 0 | P8: =O8/K8 -> 0 | Q8: =#REF! -> #REF! | R8: 0
A9: 8 | B9: ENTRADAS | C9: ABORRAJADOS | D9: ='ENTRADAS (2)'!F20 -> 6600 | E9: =D9/K9 -> 0.28512 | F9: 0 | G9: =+D9+F9 -> 6600 | H9: =G9/K9 -> 0.28512 | I9: =+D9+F9+H9 -> 6600.2851 | J9: ='ENTRADAS (2)'!F21 -> 25000 | K9: =+J9/1.08 -> 23148.148 | L9: =J9 -> 25000 | M9: 0 | N9: =M9/K9 -> 0 | O9: 0 | P9: =O9/K9 -> 0 | Q9: =#REF! -> #REF! | R9: 0
A10: 9 | B10: ENTRADAS | C10: SALPICON DE PULPÓ Y CHICHARON | D10: ='ENTRADAS (2)'!X20 -> 5704.6 | E10: =D10/K10 -> 0.16651265 | F10: 0 | G10: =+D10+F10 -> 5704.6 | H10: =G10/K10 -> 0.16651265 | I10: =+D10+F10+H10 -> 5704.7665 | J10: ='ENTRADAS (2)'!X21 -> 37000 | K10: =+J10/1.08 -> 34259.259 | L10: =J10 -> 37000 | M10: 0 | N10: =M10/K10 -> 0 | O10: 0 | P10: =O10/K10 -> 0 | Q10: =#REF! -> #REF! | R10: 0
A11: 10 | B11: ENTRADAS | C11: CARPACCIO DE BONDIOLA ACARAMELADA | D11: ='ENTRADAS (2)'!F42 -> 2939.2 | E11: =D11/K11 -> 0.1058112 | F11: 0 | G11: =+D11+F11 -> 2939.2 | H11: =G11/K11 -> 0.1058112 | I11: =+D11+F11+H11 -> 2939.3058 | J11: ='ENTRADAS (2)'!F43 -> 30000 | K11: =+J11/1.08 -> 27777.778 | L11: =J11 -> 30000 | M11: 0 | N11: =M11/K11 -> 0 | O11: 0 | P11: =O11/K11 -> 0 | Q11: =#REF! -> #REF! | R11: 0
A12: 11 | B12: ALMUERZOS | C12: BONDIOLA DE CERDO | D12: ='ALMUERZOS Y CREMAS '!AD21 -> 12276.87 | E12: =D12/K12 -> 0.51193126 | F12: ='ALMUERZOS Y CREMAS '!AD19 -> 1740 | G12: =+D12+F12 -> 14016.87 | H12: =G12/K12 -> 0.58448724 | I12: =+D12+F12+H12 -> 14017.454 | J12: ='ALMUERZOS Y CREMAS '!AD24 -> 25900 | K12: =+J12/1.08 -> 23981.481 | L12: =J12 -> 25900 | M12: =K12-D12 -> 11704.611 | N12: =M12/K12 -> 0.48806874 | O12: =K12-G12 -> 9964.6115 | P12: =O12/K12 -> 0.41551276 | Q12: =#REF! -> #REF! | R12: 0
A13: 12 | B13: ALMUERZOS | C13: FILETE TILAPIA | D13: ='ALMUERZOS Y CREMAS '!X22 -> 13935.74 | E13: =D13/K13 -> 0.539448 | F13: ='ALMUERZOS Y CREMAS '!X20 -> 1740 | G13: =+D13+F13 -> 15675.74 | H13: =G13/K13 -> 0.60680284 | I13: =+D13+F13+H13 -> 15676.347 | J13: ='ALMUERZOS Y CREMAS '!X25 -> 27900 | K13: =+J13/1.08 -> 25833.333 | L13: =J13 -> 27900 | M13: =K13-D13 -> 11897.593 | N13: =M13/K13 -> 0.460552 | O13: =K13-G13 -> 10157.593 | P13: =O13/K13 -> 0.39319716 | Q13: =#REF! -> #REF! | R13: 0
A14: 13 | B14: ALMUERZOS | C14: CADERITA SALSA DE CHAMPIÑON | D14: ='ALMUERZOS Y CREMAS '!R22 -> 14558.47 | E14: =D14/K14 -> 0.56355368 | F14: ='ALMUERZOS Y CREMAS '!R20 -> 1740 | G14: =+D14+F14 -> 16298.47 | H14: =G14/K14 -> 0.63090852 | I14: =+D14+F14+H14 -> 16299.101 | J14: ='ALMUERZOS Y CREMAS '!R25 -> 27900 | K14: =+J14/1.08 -> 25833.333 | L14: =J14 -> 27900 | M14: =K14-D14 -> 11274.863 | N14: =M14/K14 -> 0.43644632 | O14: =K14-G14 -> 9534.8633 | P14: =O14/K14 -> 0.36909148 | Q14: =#REF! -> #REF! | R14: 0
A15: 14 | B15: ALMUERZOS | C15: CUBITOS DE POLLO SALSA CILANTRO | D15: ='ALMUERZOS Y CREMAS '!L21 -> 12884.34 | E15: =D15/K15 -> 0.55883884 | F15: ='ALMUERZOS Y CREMAS '!L19 -> 1740 | G15: =+D15+F15 -> 14624.34 | H15: =G15/K15 -> 0.63430872 | I15: =+D15+F15+H15 -> 14624.974 | J15: ='ALMUERZOS Y CREMAS '!L24 -> 24900 | K15: =+J15/1.08 -> 23055.556 | L15: =J15 -> 24900 | M15: =K15-D15 -> 10171.216 | N15: =M15/K15 -> 0.44116116 | O15: =K15-G15 -> 8431.2156 | P15: =O15/K15 -> 0.36569128 | Q15: =#REF! -> #REF! | R15: 0
A16: 15 | B16: ALMUERZOS | C16: MILANESA DE CERDO | D16: ='ALMUERZOS Y CREMAS '!F22 -> 14659.47 | E16: =D16/K16 -> 0.56746335 | F16: ='ALMUERZOS Y CREMAS '!F20 -> 1740 | G16: =+D16+F16 -> 16399.47 | H16: =G16/K16 -> 0.63481819 | I16: =+D16+F16+H16 -> 16400.105 | J16: ='ALMUERZOS Y CREMAS '!F25 -> 27900 | K16: =+J16/1.08 -> 25833.333 | L16: =J16 -> 27900 | M16: =K16-D16 -> 11173.863 | N16: =M16/K16 -> 0.43253665 | O16: =K16-G16 -> 9433.8633 | P16: =O16/K16 -> 0.36518181 | Q16: =#REF! -> #REF! | R16: 0
A17: 16 | B17: ALMUERZOS | D17: =#REF! -> #REF! | E17: =D17/K17 -> #REF! | F17: 0 | G17: =+D17+F17 -> #REF! | H17: =G17/K17 -> #REF! | I17: =+D17+F17+H17 -> #REF! | J17: =#REF! -> #REF! | K17: =+J17/1.08 -> #REF! | L17: =J17 -> #REF! | M17: 0 | N17: =M17/K17 -> #REF! | O17: 0 | P17: =O17/K17 -> #REF! | Q17: =#REF! -> #REF! | R17: 0
A18: 17 | B18: PIZZAS | C18: MARGARITA | D18: =PIZZAS!R17 -> 12799.6 | E18: =D18/K18 -> 0.4607856 | F18: 0 | G18: =+D18+F18 -> 12799.6 | H18: =G18/K18 -> 0.4607856 | I18: =+D18+F18+H18 -> 12800.061 | J18: =PIZZAS!R18 -> 30000 | K18: =+J18/1.08 -> 27777.778 | L18: =J18 -> 30000 | M18: =K18-D18 -> 14978.178 | N18: =M18/K18 -> 0.5392144 | O18: =K18-G18 -> 14978.178 | P18: =O18/K18 -> 0.5392144 | Q18: =#REF! -> #REF! | R18: 0
A19: 18 | B19: PIZZAS | C19: SAMBA | D19: =PIZZAS!X17 -> 15083.64 | E19: =D19/K19 -> 0.50907285 | F19: 0 | G19: =+D19+F19 -> 15083.64 | H19: =G19/K19 -> 0.50907285 | J19: =PIZZAS!X18 -> 32000 | K19: =+J19/1.08 -> 29629.63 | L19: =J19 -> 32000 | M19: =K19-D19 -> 14545.99 | N19: =M19/K19 -> 0.49092715 | O19: =K19-G19 -> 14545.99 | P19: =O19/K19 -> 0.49092715 | Q19: =#REF! -> #REF! | R19: 0
A20: 19 | B20: PIZZAS | C20: ORIGEN | D20: =PIZZAS!AD17 -> 20785.831 | E20: =D20/K20 -> 0.56121744 | F20: 0 | G20: =+D20+F20 -> 20785.831 | H20: =G20/K20 -> 0.56121744 | J20: 40000 | K20: =+J20/1.08 -> 37037.037 | L20: =J20 -> 40000 | M20: =K20-D20 -> 16251.206 | N20: =M20/K20 -> 0.43878256 | O20: =K20-G20 -> 16251.206 | P20: =O20/K20 -> 0.43878256 | Q20: =#REF! -> #REF! | R20: 0
A21: 20 | B21: PIZZAS | C21: CARNES | D21: =PIZZAS!L17 -> 9971.5 | E21: =D21/K21 -> 0.28340053 | F21: =PIZZAS!L13 -> 1800 | G21: =+D21+F21 -> 11771.5 | H21: =G21/K21 -> 0.33455842 | I21: =+D21+F21+H21 -> 11771.835 | J21: =PIZZAS!L18 -> 38000 | K21: =+J21/1.08 -> 35185.185 | L21: =J21 -> 38000 | M21: =K21-D21 -> 25213.685 | N21: =M21/K21 -> 0.71659947 | O21: =K21-G21 -> 23413.685 | P21: =O21/K21 -> 0.66544158 | Q21: =#REF! -> #REF! | R21: 0
A22: 21 | B22: PASTAS | C22: CARBONARA | D22: =PASTAS!F20 -> 5161.497 | E22: =D22/K22 -> 0.18581389 | F22: 0 | G22: =+D22+F22 -> 5161.497 | H22: =G22/K22 -> 0.18581389 | J22: =PASTAS!F21 -> 30000 | K22: =+J22/1.08 -> 27777.778 | L22: =J22 -> 30000 | M22: =K22-D22 -> 22616.281 | N22: =M22/K22 -> 0.81418611 | O22: =K22-G22 -> 22616.281 | P22: =O22/K22 -> 0.81418611 | Q22: =#REF! -> #REF! | R22: 0
A23: 22 | B23: PASTAS | C23: NAPOLITANA | D23: =PASTAS!L20 -> 3912.997 | E23: =D23/K23 -> 0.15092988 | F23: 0 | G23: =+D23+F23 -> 3912.997 | H23: =G23/K23 -> 0.15092988 | J23: =PASTAS!L21 -> 28000 | K23: =+J23/1.08 -> 25925.926 | L23: =J23 -> 28000 | M23: =K23-D23 -> 22012.929 | N23: =M23/K23 -> 0.84907012 | O23: =K23-G23 -> 22012.929 | P23: =O23/K23 -> 0.84907012 | Q23: =#REF! -> #REF! | R23: 0
A24: 23 | B24: PASTAS | C24: AMATRICIANA | D24: =PASTAS!R20 -> 4544.705 | E24: =D24/K24 -> 0.16360938 | F24: 0 | G24: =+D24+F24 -> 4544.705 | H24: =G24/K24 -> 0.16360938 | J24: =PASTAS!R21 -> 30000 | K24: =+J24/1.08 -> 27777.778 | L24: =J24 -> 30000 | M24: =K24-D24 -> 23233.073 | N24: =M24/K24 -> 0.83639062 | O24: =K24-G24 -> 23233.073 | P24: =O24/K24 -> 0.83639062 | Q24: =#REF! -> #REF! | R24: 0
A25: 24 | B25: POSTRES | C25: CARLOTTA DE LIMON | D25: =POSTRES!F22 -> 4431.2033 | E25: =D25/K25 -> 0.3009874 | F25: 0 | G25: =+D25+F25 -> 4431.2033 | H25: =G25/K25 -> 0.3009874 | J25: =POSTRES!F21 -> 15900 | K25: =+J25/1.08 -> 14722.222 | L25: =J25 -> 15900 | M25: =K25-D25 -> 10291.019 | N25: =M25/K25 -> 0.6990126 | O25: =K25-G25 -> 10291.019 | P25: =O25/K25 -> 0.6990126 | Q25: =#REF! -> #REF! | R25: 0
A26: 25 | B26: POSTRES | C26: FLAN NAPOLITANO | D26: =POSTRES!L22 -> 2563.1788 | E26: =D26/K26 -> 0.2796195 | F26: 0 | G26: =+D26+F26 -> 2563.1788 | H26: =G26/K26 -> 0.2796195 | J26: =POSTRES!L21 -> 9900 | K26: =+J26/1.08 -> 9166.6667 | L26: =J26 -> 9900 | M26: =K26-D26 -> 6603.4879 | N26: =M26/K26 -> 0.7203805 | O26: =K26-G26 -> 6603.4879 | P26: =O26/K26 -> 0.7203805 | Q26: =#REF! -> #REF! | R26: 0
A27: 26 | B27: PLATOS | C27: CHICHARON ORNEADO | D27: =PLATOS!F20 -> 13773.32 | E27: =D27/K27 -> 0.31649331 | F27: =PLATOS!F16 -> 1740 | G27: =+D27+F27 -> 15513.32 | H27: =G27/K27 -> 0.35647629 | J27: =PLATOS!F21 -> 47000 | K27: =+J27/1.08 -> 43518.519 | L27: =J27 -> 47000 | M27: =K27-D27 -> 29745.199 | N27: =M27/K27 -> 0.68350669 | O27: =K27-G27 -> 28005.199 | P27: =O27/K27 -> 0.64352371 | Q27: =#REF! -> #REF! | R27: 0
A28: 27 | B28: PLATOS | C28: POLLO DORADO | D28: =PLATOS!L20 -> 11847 | E28: =D28/K28 -> 0.27222894 | F28: =PLATOS!L16 -> 1740 | G28: =+D28+F28 -> 13587 | H28: =G28/K28 -> 0.31221191 | J28: =PLATOS!L21 -> 47000 | K28: =+J28/1.08 -> 43518.519 | L28: =J28 -> 47000 | M28: =K28-D28 -> 31671.519 | N28: =M28/K28 -> 0.72777106 | O28: =K28-G28 -> 29931.519 | P28: =O28/K28 -> 0.68778809 | Q28: =#REF! -> #REF! | R28: 0
A29: 28 | B29: PLATOS | C29: ENSALADA DE BONDIOLA | D29: =PLATOS!R21 -> 10435.7 | E29: =D29/K29 -> 0.2817639 | F29: =PLATOS!L17 -> 0 | G29: =+D29+F29 -> 10435.7 | H29: =G29/K29 -> 0.2817639 | J29: =PLATOS!R22 -> 40000 | K29: =+J29/1.08 -> 37037.037 | L29: =J29 -> 40000 | M29: =K29-D29 -> 26601.337 | N29: =M29/K29 -> 0.7182361 | O29: =K29-G29 -> 26601.337 | P29: =O29/K29 -> 0.7182361 | Q29: =#REF! -> #REF! | R29: 0
A30: 29 | B30: PLATOS | C30: COSTILLA SOUS VIDE | D30: =PLATOS!F43 -> 17096.2 | E30: =D30/K30 -> 0.3357072 | F30: =PLATOS!F39 -> 1740 | G30: =+D30+F30 -> 18836.2 | H30: =G30/K30 -> 0.36987447 | J30: =PLATOS!F44 -> 55000 | K30: =+J30/1.08 -> 50925.926 | L30: =J30 -> 55000 | M30: =K30-D30 -> 33829.726 | N30: =M30/K30 -> 0.6642928 | O30: =K30-G30 -> 32089.726 | P30: =O30/K30 -> 0.63012553 | Q30: =#REF! -> #REF! | R30: 0
A31: 30 | B31: TARDEO | C31: PANCHO | D31: =TARDEO!F20 -> 6625.85 | E31: =D31/K31 -> 0.45005774 | F31: =PLATOS!F40 -> 0 | G31: =+D31+F31 -> 6625.85 | H31: =G31/K31 -> 0.45005774 | J31: =TARDEO!F21 -> 15900 | K31: =+J31/1.08 -> 14722.222 | L31: =J31 -> 15900 | M31: =K31-D31 -> 8096.3722 | N31: =M31/K31 -> 0.54994226 | O31: =K31-G31 -> 8096.3722 | P31: =O31/K31 -> 0.54994226 | Q31: =#REF! -> #REF! | R31: 0
A32: 31 | B32: TARDEO | C32: WRAPP | D32: =TARDEO!L20 -> 2962.08 | E32: =D32/K32 -> 0.2934905 | F32: 0 | G32: =+D32+F32 -> 2962.08 | H32: =G32/K32 -> 0.2934905 | J32: =TARDEO!L21 -> 10900 | K32: =+J32/1.08 -> 10092.593 | L32: =J32 -> 10900 | M32: =K32-D32 -> 7130.5126 | N32: =M32/K32 -> 0.7065095 | O32: =K32-G32 -> 7130.5126 | P32: =O32/K32 -> 0.7065095 | Q32: =#REF! -> #REF! | R32: 0
A33: 32 | B33: TARDEO | C33: COLOSO /PALMEÑO | D33: =TARDEO!R20 -> 5568.2 | E33: =D33/K33 -> 0.35583763 | F33: 0 | G33: =+D33+F33 -> 5568.2 | H33: =G33/K33 -> 0.35583763 | J33: =TARDEO!R21 -> 16900 | K33: =+J33/1.08 -> 15648.148 | L33: =J33 -> 16900 | M33: =K33-D33 -> 10079.948 | N33: =M33/K33 -> 0.64416237 | O33: =K33-G33 -> 10079.948 | P33: =O33/K33 -> 0.64416237 | Q33: =#REF! -> #REF! | R33: 0
A34: 33 | B34: ARROCES | C34: ARROZ CON POLLO | D34: =ARROCES!F20 -> 4565.924 | E34: =D34/K34 -> 0.29178686 | F34: 0 | G34: =+D34+F34 -> 4565.924 | H34: =G34/K34 -> 0.29178686 | J34: =ARROCES!F21 -> 16900 | K34: =+J34/1.08 -> 15648.148 | L34: =J34 -> 16900 | M34: =K34-D34 -> 11082.224 | N34: =M34/K34 -> 0.70821314 | O34: =K34-G34 -> 11082.224 | P34: =O34/K34 -> 0.70821314 | Q34: =#REF! -> #REF! | R34: 0
A35: 34 | B35: ARROCES | C35: ARROZ MIXTO | D35: =ARROCES!L20 -> 5863.924 | E35: =D35/K35 -> 0.353801 | F35: 0 | G35: =+D35+F35 -> 5863.924 | H35: =G35/K35 -> 0.353801 | J35: =ARROCES!L21 -> 17900 | K35: =+J35/1.08 -> 16574.074 | L35: =J35 -> 17900 | M35: =K35-D35 -> 10710.15 | N35: =M35/K35 -> 0.646199 | O35: =K35-G35 -> 10710.15 | P35: =O35/K35 -> 0.646199 | Q35: =#REF! -> #REF! | R35: 0
A36: 35 | B36: ARROCES | C36: ARROZ CON CAMARON | D36: 0
A37: 36 | B37: NAVIDEÑO | C37: LOMO DE CERDO AL HORNO | D37: ='CENAS DICIEMBRE '!L23 -> 16572.6 | E37: =D37/K37 -> 0.35796816 | F37: 0 | G37: =+D37+F37 -> 16572.6 | H37: =G37/K37 -> 0.35796816 | J37: ='CENAS DICIEMBRE '!L24 -> 50000 | K37: =+J37/1.08 -> 46296.296 | L37: =J37 -> 50000 | M37: =K37-D37 -> 29723.696 | N37: =M37/K37 -> 0.64203184 | O37: =K37-G37 -> 29723.696 | P37: =O37/K37 -> 0.64203184 | Q37: =#REF! -> #REF!
C38: PAQUETE NAVIDAD | D38: ='CENAS DICIEMBRE '!U8 -> 30549 | E38: =D38/K38 -> 0.366588 | F38: 0 | G38: =+D38+F38 -> 30549 | H38: =G38/K38 -> 0.366588 | J38: ='CENAS DICIEMBRE '!V8 -> 90000 | K38: =+J38/1.08 -> 83333.333 | L38: =J38 -> 90000 | M38: =K38-D38 -> 52784.333 | N38: =M38/K38 -> 0.633412 | O38: =K38-G38 -> 52784.333 | P38: =O38/K38 -> 0.633412 | Q38: =#REF! -> #REF!
D39: 0 | E39: =+#REF!/B39 -> #REF! | F39: 0 | G39: =+D39+F39 -> 0 | H39: =+#REF!/E39 -> #REF! | I39: =+D39+F39+H39 -> #REF! | J39: =#REF! -> #REF! | K39: =+J39/1.08 -> #REF! | L39: =J39 -> #REF! | M39: 0 | O39: 0 | Q39: =#REF! -> #REF! | R39: 0

Sheet CENAS DICIEMBRE 
B2: LOMO DE RES RELLENO | H2: LOMO DE CERDO AL HORNO | N2: PLATO NAVIDEÑO
B3: INGREDIENTES | C3: CANTIDAD | D3: UND MEDIDA | E3: COS/GR | F3: VALOR | H3: INGREDIENTES | I3: CANTIDAD | J3: UND MEDIDA | K3: COS/GR | L3: VALOR | N3: INGREDIENTES | O3: CANTIDAD | P3: UND MEDIDA | Q3: COS/GR | R3: VALOR | T3: Reserva para 80 personas | U3: Costo | V3: Precio venta | W3: Utilidad
B4: LOMO DE RES (REDONDO) | C4: 670 | D4: GR | E4: 50.3 | F4: =C4*E4 -> 33701 | H4: LOMO DE CERDO | I4: 250 | J4: GR | K4: 22.08 | L4: =I4*K4 -> 5520 | N4: MANJAR BLANCO | O4: 40 | P4: GR | Q4: 40 | R4: =O4*Q4 -> 1600 | T4: Churrasco 350 gr | U4: 20919
B5: ACETIE DE OLIVA | C5: 20 | D5: GR | E5: 38.8 | F5: =C5*E5 -> 776 | H5: AJO PICADO | I5: 5 | J5: GR | K5: 15 | L5: =I5*K5 -> 75 | N5: DES AMARGADO | O5: 35 | P5: GR | Q5: 48 | R5: =O5*Q5 -> 1680 | T5: Limonada | U5: 1000
B6: TOCINETA | C6: 50 | D6: GR | E6: 26.9 | F6: =C6*E6 -> 1345 | H6: ACEITE SOYA | I6: 165 | J6: GR | K6: 38.8 | L6: =I6*K6 -> 6402 | N6: HOJALDRA | O6: 0.5 | P6: UND | Q6: 700 | R6: =O6*Q6 -> 350 | T6: Aborrajados 2 | U6: 4000
B7: CHAMPIÑON | C7: 170 | D7: GR | E7: 34.4 | F7: =C7*E7 -> 5848 | H7: SAL MARINA | I7: 4 | J7: GR | K7: 5 | L7: =I7*K7 -> 20 | N7: NATILLA | O7: 1 | P7: UND | Q7: 1000 | R7: =O7*Q7 -> 1000 | T7: Plato Navideño | U7: 4630
B8: CEBOLLA CABEZONA | C8: 65 | D8: GR | E8: 3.8 | F8: =C8*E8 -> 247 | H8: PEREJIL FRESCO | I8: 15 | J8: GR | K8: 5 | L8: =I8*K8 -> 75 | P8: GR | R8: =O8*Q8 -> 0 | U8: =SUM(U4:U7) -> 30549 | V8: 90000 | W8: =V8-U8 -> 59451
B9: SAL MARINA | C9: 4 | D9: GR | E9: 4.8 | F9: =C9*E9 -> 19.2 | H9: CREMOSO DE PAPA | I9: 200 | J9: GR | K9: 7.52 | L9: =I9*K9 -> 1504 | P9: GR | R9: =O9*Q9 -> 0 | U9: 80 | V9: 80
B10: PIMIENTA NEGRA | C10: 0.5 | D10: GR | E10: 52 | F10: =C10*E10 -> 26 | H10: SALSA FRUTOS AMARILLOS | I10: 120 | J10: GR | K10: 8.5 | L10: =I10*K10 -> 1020 | P10: GR | R10: =O10*Q10 -> 0 | U10: =U8*U9 -> 2443920 | V10: =V8*V9 -> 7200000 | W10: =V10-U10 -> 4756080
B11: AJO PICADO | C11: 5 | D11: GR | E11: 15 | F11: =C11*E11 -> 75 | H11: ARROZ BLANCO | I11: 100 | J11: GR | K11: 4.5 | L11: =I11*K11 -> 450 | R11: =O11*Q11 -> 0
B12: PEREJIL FRESCO | C12: 15 | D12: GR | E12: 5 | F12: =C12*E12 -> 75 | T12: Punta 350 gr | U12: 30005
T13: Limonada | U13: 900
B14: TOTAL | F14: =SUM(F4:F13) -> 42112.2 | H14: TOTAL | L14: =SUM(L4:L13) -> 15066 | R14: =SUM(R4:R13) -> 4630 | T14: Aborrajados 2 | U14: 4000
B15: MATERIAL DE EMPAQUE | H15: MATERIAL DE EMPAQUE | N15: MATERIAL DE EMPAQUE | T15: Plato Navideño | U15: 4630
F16: =C16*140 -> 0 | L16: =I16*140 -> 0 | N16: VINO | O16: 3000 | P16: ML | Q16: 22.6 | R16: =O16*Q16 -> 67800 | U16: =SUM(U12:U15) -> 39535 | V16: 90000 | W16: =V16-U16 -> 50465
F17: =C17*140 -> 0 | L17: =I17*140 -> 0 | N17: SODA | O17: 1500 | P17: ML | Q17: 3.28 | R17: =O17*Q17 -> 4920 | U17: 80 | V17: 80
F18: =C18*140 -> 0 | L18: =I18*140 -> 0 | N18: CANADA DRY | O18: 1500 | P18: ML | Q18: 4.27 | R18: =O18*Q18 -> 6405 | U18: =U16*U17 -> 3162800 | V18: =V16*V17 -> 7200000 | W18: =V18-U18 -> 4037200
B19: TOTAL | F19: =SUM(F16:F18) -> 0 | H19: TOTAL | L19: =SUM(L16:L18) -> 0 | R19: =SUM(R16:R18) -> 79125 | S19: =R19/20 -> 3956.25
B20: COSTO + PRECIO DE VENTA | H20: COSTO + PRECIO DE VENTA | N20: COSTO + PRECIO DE VENTA | T20: Cervezas | U20: Costo Und | V20: Costo total | W20: Precio venta | X20: Utilidad | Z20: Precio venta | AA20: Utilidad
B21: COSTO DE INGREDIENTES | F21: =F14+F19 -> 42112.2 | H21: COSTO DE INGREDIENTES | L21: =L14+L19 -> 15066 | N21: COSTO DE INGREDIENTES | R21: =R14+R19 -> 83755 | T21: Corona | U21: 3787 | V21: =U21*160 -> 605920 | W21: 8000 | X21: =W21-U21 -> 4213 | Y21: 160 | Z21: =W21*Y21 -> 1280000 | AA21: =Z21-V21 -> 674080
B22: MARGEN DE ERROR O VARIACION 10% | F22: =F21*0.1 -> 4211.22 | H22: MARGEN DE ERROR O VARIACION 10% | L22: =L21*0.1 -> 1506.6 | N22: MARGEN DE ERROR O VARIACION 10% | R22: =R21*0.1 -> 8375.5 | T22: Stella | U22: 3462 | V22: =U22*160 -> 553920 | W22: 8000 | X22: =W22-U22 -> 4538 | Y22: 160 | Z22: =W22*Y22 -> 1280000 | AA22: =Z22-V22 -> 726080
B23: COSTO TOTAL DE LA PREPARACION | F23: =SUM(F21:F22) -> 46323.42 | H23: COSTO TOTAL DE LA PREPARACION | L23: =SUM(L21:L22) -> 16572.6 | N23: COSTO TOTAL DE LA PREPARACION | R23: =SUM(R21:R22) -> 92130.5 | T23: Clud dorada | U23: 3079 | V23: =U23*160 -> 492640 | W23: 8000 | X23: =W23-U23 -> 4921 | Y23: 160 | Z23: =W23*Y23 -> 1280000 | AA23: =Z23-V23 -> 787360
B24: PRECIO DE VENTA | F24: 45000 | H24: PRECIO DE VENTA | L24: 50000 | N24: PRECIO DE VENTA | R24: 30000 | T24: Michelado | W24: 3000 | Y24: 160 | Z24: =W24*Y24 -> 480000
V25: invercion | W25: utilidad
T26: total de la venta | U26: =V18+Z23 -> 8480000 | V26: =U18+V21 -> 3768720 | W26: =U26-V26 -> 4711280
B27: CREMOSO DE PAPA | H27: SALSA DE FRUTOS AMARILLOS | N27: PASTA CARBONARA
B28: INGREDIENTES | C28: CANTIDAD | D28: UND MEDIDA | E28: COS/GR | F28: VALOR | H28: INGREDIENTES | I28: CANTIDAD | J28: UND MEDIDA | K28: COS/GR | L28: VALOR | N28: INGREDIENTES | O28: CANTIDAD | P28: UND MEDIDA | Q28: COS/GR | R28: VALOR
B29: PAPA PARDA | C29: 150 | D29: GR | E29: 3.59 | F29: =C29*E29 -> 538.5 | H29: MARACUYA | I29: 50 | J29: gr | K29: 6.9 | L29: =I29*K29 -> 345 | P29: gr | R29: =O29*Q29 -> 0
B30: CREMA DE LECHE | C30: 50 | D30: GR | E30: 16.1 | F30: =C30*E30 -> 805 | H30: JUGO DE NARANJA | I30: 20 | J30: gr | K30: 4 | L30: =I30*K30 -> 80 | P30: gr | R30: =O30*Q30 -> 0
B31: PASTA AJO | C31: 2 | D31: GR | E31: 15 | F31: =C31*E31 -> 30 | H31: UCHUVA | I31: 15 | J31: gr | K31: 23.6 | L31: =I31*K31 -> 354 | P31: gr | R31: =O31*Q31 -> 0
B32: MANTEQUILLA | C32: 5 | D32: GR | E32: 26 | F32: =C32*E32 -> 130 | H32: AZUCAR | I32: 25 | J32: gr | K32: 4 | L32: =I32*K32 -> 100 | P32: gr | R32: =O32*Q32 -> 0
F33: =C33*E33 -> 0 | H33: ANIS ESTRELLADO | I33: 2 | J33: gr | K33: 12 | L33: =I33*K33 -> 24 | P33: gr | R33: =O33*Q33 -> 0
F34: =C34*E34 -> 0 | J34: gr | L34: =I34*K34 -> 0 | P34: gr | R34: =O34*Q34 -> 0
F35: =C35*E35 -> 0 | J35: gr | L35: =I35*K35 -> 0 | P35: gr | R35: =O35*Q35 -> 0
F36: =C36*E36 -> 0 | L36: =I36*K36 -> 0 | R36: =O36*Q36 -> 0
F37: =SUM(F29:F36) -> 1503.5 | L37: =I37*K37 -> 0 | R37: =O37*Q37 -> 0
B38: MATERIAL DE EMPAQUE | H38: MATERIAL DE EMPAQUE | N38: MATERIAL DE EMPAQUE
F39: =C39*140 -> 0 | L39: =I39*140 -> 0 | R39: =O39*140 -> 0
F40: =C40*140 -> 0 | L40: =I40*140 -> 0 | R40: =O40*140 -> 0
F41: =SUM(F39:F40) -> 0 | L41: =I41*140 -> 0 | R41: =O41*140 -> 0
B42: COSTO + PRECIO DE VENTA | H42: COSTO + PRECIO DE VENTA | N42: COSTO + PRECIO DE VENTA
B43: COSTO DE INGREDIENTES | F43: =F37+F41 -> 1503.5 | H43: COSTO DE INGREDIENTES | L43: =(L29+L30+L31+L32+L33+L34+L35+L36+L37+L41) -> 903 | N43: COSTO DE INGREDIENTES | R43: =(R29+R30+R31+R32+R33+R34+R35+R36+R37+R41) -> 0
B44: MARGEN DE ERROR O VARIACION 10% | F44: =F43*0.1 -> 150.35 | H44: MARGEN DE ERROR O VARIACION 10% | L44: =L43*0.1 -> 90.3 | N44: MARGEN DE ERROR O VARIACION 10% | R44: =R43*0.1 -> 0
B45: COSTO TOTAL DE LA PREPARACION | F45: =SUM(F43:F44) -> 1653.85 | H45: COSTO TOTAL DE LA PREPARACION | L45: =SUM(L43:L44) -> 993.3 | N45: COSTO TOTAL DE LA PREPARACION | R45: =SUM(R43:R44) -> 0
B46: PRECIO DE VENTA | F46: 30000 | H46: PRECIO DE VENTA | L46: 30000 | N46: PRECIO DE VENTA | R46: 30000
B49: PASTA CARBONARA | H49: PASTA CARBONARA | N49: PASTA CARBONARA
B50: INGREDIENTES | C50: CANTIDAD | D50: UND MEDIDA | E50: COS/GR | F50: VALOR | H50: INGREDIENTES | I50: CANTIDAD | J50: UND MEDIDA | K50: COS/GR | L50: VALOR | N50: INGREDIENTES | O50: CANTIDAD | P50: UND MEDIDA | Q50: COS/GR | R50: VALOR
D51: gr | F51: =C51*E51 -> 0 | J51: gr | L51: =I51*K51 -> 0 | P51: gr | R51: =O51*Q51 -> 0
D52: gr | F52: =C52*E52 -> 0 | J52: gr | L52: =I52*K52 -> 0 | P52: gr | R52: =O52*Q52 -> 0
D53: gr | F53: =C53*E53 -> 0 | J53: gr | L53: =I53*K53 -> 0 | P53: gr | R53: =O53*Q53 -> 0
D54: gr | F54: =C54*E54 -> 0 | J54: gr | L54: =I54*K54 -> 0 | P54: gr | R54: =O54*Q54 -> 0
D55: gr | F55: =C55*E55 -> 0 | J55: gr | L55: =I55*K55 -> 0 | P55: gr | R55: =O55*Q55 -> 0
D56: gr | F56: =C56*E56 -> 0 | J56: gr | L56: =I56*K56 -> 0 | P56: gr | R56: =O56*Q56 -> 0
D57: gr | F57: =C57*E57 -> 0 | J57: gr | L57: =I57*K57 -> 0 | P57: gr | R57: =O57*Q57 -> 0
F58: =C58*E58 -> 0 | L58: =I58*K58 -> 0 | R58: =O58*Q58 -> 0
F59: =C59*E59 -> 0 | L59: =I59*K59 -> 0 | R59: =O59*Q59 -> 0
B60: MATERIAL DE EMPAQUE | H60: MATERIAL DE EMPAQUE | N60: MATERIAL DE EMPAQUE
F61: =C61*140 -> 0 | L61: =I61*140 -> 0 | R61: =O61*140 -> 0
F62: =C62*140 -> 0 | L62: =I62*140 -> 0 | R62: =O62*140 -> 0
F63: =C63*140 -> 0 | L63: =I63*140 -> 0 | R63: =O63*140 -> 0
B64: COSTO + PRECIO DE VENTA | H64: COSTO + PRECIO DE VENTA | N64: COSTO + PRECIO DE VENTA
B65: COSTO DE INGREDIENTES | F65: =(F51+F52+F53+F54+F55+F56+F57+F58+F59+F63) -> 0 | H65: COSTO DE INGREDIENTES | L65: =(L51+L52+L53+L54+L55+L56+L57+L58+L59+L63) -> 0 | N65: COSTO DE INGREDIENTES | R65: =(R51+R52+R53+R54+R55+R56+R57+R58+R59+R63) -> 0
B66: MARGEN DE ERROR O VARIACION 10% | F66: =F65*0.1 -> 0 | H66: MARGEN DE ERROR O VARIACION 10% | L66: =L65*0.1 -> 0 | N66: MARGEN DE ERROR O VARIACION 10% | R66: =R65*0.1 -> 0
B67: COSTO TOTAL DE LA PREPARACION | F67: =SUM(F65:F66) -> 0 | H67: COSTO TOTAL DE LA PREPARACION | L67: =SUM(L65:L66) -> 0 | N67: COSTO TOTAL DE LA PREPARACION | R67: =SUM(R65:R66) -> 0
B68: PRECIO DE VENTA | F68: 30000 | H68: PRECIO DE VENTA | L68: 30000 | N68: PRECIO DE VENTA | R68: 30000

Sheet CORTES 
B2: CHURRASCO | H2: PUNTA DE ANCA | N2: BEBY BEEF
B3: INGREDIENTES | C3: CANTIDAD | D3: UND MEDIDA | E3: COS/GR | F3: VALOR | H3: INGREDIENTES | I3: CANTIDAD | J3: UND MEDIDA | K3: COS/GR | L3: VALOR | N3: INGREDIENTES | O3: CANTIDAD | P3: UND MEDIDA | Q3: COS/GR | R3: VALOR
B4: churrasco (res) | C4: 350 | D4: gr | E4: 47.04 | F4: =C4*E4 -> 16464 | H4: punta de anca | I4: 350 | J4: gr | K4: 73 | L4: =I4*K4 -> 25550 | N4: lomo viche | O4: 250 | P4: gr | Q4: 56 | R4: =O4*Q4 -> 14000
B5: Mix de papas | C5: 140 | D5: gr | E5: 5.5 | F5: =C5*E5 -> 770 | H5: ensalada | I5: 100 | J5: gr | K5: 20.71 | L5: =I5*K5 -> 2071 | N5: ensalada | O5: 100 | P5: gr | Q5: 20.71 | R5: =O5*Q5 -> 2071
B6: ensalada | C6: 100 | D6: gr | E6: 20.71 | F6: =C6*E6 -> 2071 | H6: Mix de papas | I6: 140 | J6: gr | K6: 5.5 | L6: =I6*K6 -> 770 | N6: Mix de papas | O6: 140 | P6: gr | Q6: 5.5 | R6: =O6*Q6 -> 770
B7: chimichurri argentino | C7: 60 | D7: gr | E7: 26.9 | F7: =C7*E7 -> 1614 | H7: chimichuri | I7: 60 | J7: gr | K7: 26.9 | L7: =I7*K7 -> 1614 | N7: chimichurri | O7: 60 | P7: gr | Q7: 26.9 | R7: =O7*Q7 -> 1614
B8: MATERIAL DE EMPAQUE | H8: MATERIAL DE EMPAQUE | N8: MATERIAL DE EMPAQUE
F9: =C9*140 -> 0 | L9: =I9*140 -> 0 | R9: =O9*140 -> 0
F10: =C10*140 -> 0 | L10: =I10*140 -> 0 | R10: =O10*140 -> 0
F11: =C11*140 -> 0 | L11: =I11*140 -> 0 | R11: =O11*140 -> 0
B12: COSTO + PRECIO DE VENTA | H12: COSTO + PRECIO DE VENTA | N12: COSTO + PRECIO DE VENTA
B13: COSTO DE INGREDIENTES | F13: =(F4+F5+F6+F7+F9+F10+F11) -> 20919 | H13: COSTO DE INGREDIENTES | L13: =(L4+L5+L6+L7+L9+L10+L11) -> 30005 | N13: COSTO DE INGREDIENTES | R13: =(R4+R5+R6+R7+R9+R10+R11) -> 18455
B14: MARGEN DE ERROR O VARIACION 10% | F14: =F13*0.1 -> 2091.9 | H14: MARGEN DE ERROR O VARIACION 10% | L14: =L13*0.1 -> 3000.5 | N14: MARGEN DE ERROR O VARIACION 10% | R14: =R13*0.1 -> 1845.5
B15: COSTO TOTAL DE LA PREPARACION | F15: =SUM(F13:F14) -> 23010.9 | H15: COSTO TOTAL DE LA PREPARACION | L15: =SUM(L13:L14) -> 33005.5 | N15: COSTO TOTAL DE LA PREPARACION | R15: =SUM(R13:R14) -> 20300.5
B16: PRECIO DE VENTA | F16: 55000 | H16: PRECIO DE VENTA | L16: 50000 | N16: PRECIO DE VENTA | R16: 64000
D19: malta | E19: 44000 | K19: 48000
D20: cañaveral | E20: 47040 | F20: =E20/1000 -> 47.04 | K20: 73000

Sheet TARDEO
B2: PANCHO | H2: WRAPP | N2: EL DORADO
B3: INGREDIENTES | C3: CANTIDAD | D3: UND MEDIDA | E3: COS/GR | F3: VALOR | H3: INGREDIENTES | I3: CANTIDAD | J3: UND MEDIDA | K3: COS/GR | L3: VALOR | N3: INGREDIENTES | O3: CANTIDAD | P3: UND MEDIDA | Q3: COS/GR | R3: VALOR
B4: CHORIZO | C4: 1 | D4: gr | E4: 2690 | F4: =C4*E4 -> 2690 | H4: HUEVOS | I4: 2 | J4: UND | K4: 498 | L4: =I4*K4 -> 996 | N4: COLESTLAW | O4: 80 | P4: gr | Q4: 20 | R4: =O4*Q4 -> 1600
B5: COLESTLAW | C5: 70 | D5: gr | E5: 20 | F5: =C5*E5 -> 1400 | H5: JAMON | I5: 20 | J5: gr | K5: 32.25 | L5: =I5*K5 -> 645 | N5: PAN HAMBURGUESA | O5: 1 | P5: gr | Q5: 780 | R5: =O5*Q5 -> 780
B6: LECHUGA | C6: 15 | D6: gr | E6: 20 | F6: =C6*E6 -> 300 | H6: QUESO | I6: 20 | J6: gr | K6: 21.6 | L6: =I6*K6 -> 432 | N6: PECHUGA | O6: 100 | P6: gr | Q6: 20 | R6: =O6*Q6 -> 2000
B7: PAN PERRO | C7: 1 | D7: gr | E7: 925 | F7: =C7*E7 -> 925 | H7: SAL | I7: 2 | J7: gr | K7: 2 | L7: =I7*K7 -> 4 | N7: ALIOLI CILANTRO | O7: 10 | P7: gr | Q7: 10.8 | R7: =O7*Q7 -> 108
B8: CHIMICHURRI | C8: 5 | D8: gr | E8: 26.9 | F8: =C8*E8 -> 134.5 | H8: ALBAHACA | I8: 10 | J8: gr | K8: 55.8 | L8: =I8*K8 -> 558 | N8: PAPA FRANCESA | O8: 70 | P8: gr | Q8: 8.2 | R8: =O8*Q8 -> 574
B9: PAPA FRANCESA | C9: 70 | D9: gr | E9: 8.2 | F9: =C9*E9 -> 574 | H9: TOMATE | I9: 10 | J9: gr | K9: 5.78 | L9: =I9*K9 -> 57.8 | P9: gr | R9: =O9*Q9 -> 0
D10: gr | F10: =C10*E10 -> 0 | L10: =I10*K10 -> 0 | P10: gr | R10: =O10*Q10 -> 0
F11: =C11*E11 -> 0 | L11: =I11*K11 -> 0 | R11: =O11*Q11 -> 0
F12: =SUM(F4:F11) -> 6023.5 | L12: =SUM(L4:L11) -> 2692.8 | R12: =O12*Q12 -> 0
B13: MATERIAL DE EMPAQUE | H13: MATERIAL DE EMPAQUE | N13: MATERIAL DE EMPAQUE
F14: =C14*140 -> 0 | L14: =I14*140 -> 0 | R14: =O14*140 -> 0
F15: =C15*140 -> 0 | L15: =I15*140 -> 0 | R15: =O15*140 -> 0
F16: =SUM(F14:F15) -> 0 | L16: =I16*140 -> 0 | R16: =O16*140 -> 0
B17: COSTO + PRECIO DE VENTA | H17: COSTO + PRECIO DE VENTA | N17: COSTO + PRECIO DE VENTA
B18: COSTO DE INGREDIENTES | F18: =F16+F12 -> 6023.5 | H18: COSTO DE INGREDIENTES | L18: =L12+L16 -> 2692.8 | N18: COSTO DE INGREDIENTES | R18: =(R4+R5+R6+R7+R8+R9+R10+R11+R12+R16) -> 5062
B19: MARGEN DE ERROR O VARIACION 10% | F19: =F18*0.1 -> 602.35 | H19: MARGEN DE ERROR O VARIACION 10% | L19: =L18*0.1 -> 269.28 | N19: MARGEN DE ERROR O VARIACION 10% | R19: =R18*0.1 -> 506.2
B20: COSTO TOTAL DE LA PREPARACION | F20: =SUM(F18:F19) -> 6625.85 | H20: COSTO TOTAL DE LA PREPARACION | L20: =SUM(L18:L19) -> 2962.08 | N20: COSTO TOTAL DE LA PREPARACION | R20: =SUM(R18:R19) -> 5568.2
B21: PRECIO DE VENTA | F21: 15900 | H21: PRECIO DE VENTA | L21: 10900 | N21: PRECIO DE VENTA | R21: 16900
B24: TIRAMISU | H24: COLESTLAW PARA 2 | N24: MAYONESA ARTESANAL
B25: INGREDIENTES | C25: CANTIDAD | D25: UND MEDIDA | E25: COS/GR | F25: VALOR | H25: INGREDIENTES | I25: CANTIDAD | J25: UND MEDIDA | K25: COS/GR | L25: VALOR | N25: INGREDIENTES | O25: CANTIDAD | P25: UND MEDIDA | Q25: COS/GR | R25: VALOR
B26: HUEVOS | C26: 5 | D26: gr | E26: 498 | F26: =C26*E26 -> 2490 | H26: ZANAHORIA | I26: 50 | J26: gr | K26: 4.6 | L26: =I26*K26 -> 230 | N26: HUEVO | O26: 1 | P26: gr | Q26: 498 | R26: =O26*Q26 -> 498
B27: MASCARPONE | C27: 500 | D27: gr | E27: 59.6 | F27: =C27*E27 -> 29800 | H27: REPOLLO | I27: 100 | J27: gr | K27: 11.6 | L27: =I27*K27 -> 1160 | N27: MOSTAZA | O27: 10 | P27: gr | Q27: 17.9 | R27: =O27*Q27 -> 179
B28: LICOR DE CAFÉ | C28: 56 | D28: gr | E28: 85.2 | F28: =C28*E28 -> 4771.2 | H28: PIÑA | I28: 50 | J28: gr | K28: 4.9 | L28: =I28*K28 -> 245 | N28: ACEITE SOYA | O28: 500 | P28: ML | Q28: 8.27 | R28: =O28*Q28 -> 4135
B29: EXPRESO | C29: 100 | D29: gr | E29: 50.4 | F29: =C29*E29 -> 5040 | H29: AZUCAR | I29: 30 | J29: gr | K29: 4.4 | L29: =I29*K29 -> 132 | N29: SAL | O29: 5 | P29: gr | Q29: 2 | R29: =O29*Q29 -> 10
B30: AZUCAR | C30: 220 | D30: gr | E30: 4.4 | F30: =C30*E30 -> 968 | H30: CREMA DE LECHE | I30: 20 | J30: gr | K30: 21.1 | L30: =I30*K30 -> 422 | N30: PIMIENTA | O30: 1 | P30: gr | Q30: 52 | R30: =O30*Q30 -> 52
B31: SAL | C31: 2 | D31: gr | E31: 2 | F31: =C31*E31 -> 4 | H31: LECHE CONDENSADA | I31: 20 | J31: gr | K31: 12.9 | L31: =I31*K31 -> 258 | R31: =O31*Q31 -> 0
B32: LADY FINGER | C32: 150 | D32: gr | E32: 94.3 | F32: =C32*E32 -> 14145 | H32: MAYONESA | I32: 10 | J32: gr | K32: 8.9 | L32: =I32*K32 -> 89 | R32: =O32*Q32 -> 0
B33: COCOA POLVO | C33: 20 | D33: gr | E33: 71.5 | F33: =C33*E33 -> 1430 | L33: =I33*K33 -> 0 | R33: =O33*Q33 -> 0
F34: =SUM(F26:F33) -> 58648.2 | L34: =I34*K34 -> 0 | R34: =O34*Q34 -> 0
B35: MATERIAL DE EMPAQUE | H35: MATERIAL DE EMPAQUE | N35: MATERIAL DE EMPAQUE
F36: =C36*140 -> 0 | L36: =I36*140 -> 0 | R36: =O36*140 -> 0
F37: =C37*140 -> 0 | L37: =I37*140 -> 0 | R37: =O37*140 -> 0
F38: =SUM(F36:F37) -> 0 | L38: =I38*140 -> 0 | R38: =O38*140 -> 0
B39: COSTO + PRECIO DE VENTA | H39: COSTO + PRECIO DE VENTA | N39: COSTO + PRECIO DE VENTA
B40: COSTO DE INGREDIENTES | F40: =F34+F38 -> 58648.2 | H40: COSTO DE INGREDIENTES | L40: =(L26+L27+L28+L29+L30+L31+L32+L33+L34+L38) -> 2536 | N40: COSTO DE INGREDIENTES | R40: =(R26+R27+R28+R29+R30+R31+R32+R33+R34+R38) -> 4874
B41: MARGEN DE ERROR O VARIACION 10% | F41: =F40*0.1 -> 5864.82 | H41: MARGEN DE ERROR O VARIACION 10% | L41: =L40*0.1 -> 253.6 | N41: MARGEN DE ERROR O VARIACION 10% | R41: =R40*0.1 -> 487.4
B42: COSTO TOTAL DE LA PREPARACION | F42: =SUM(F40:F41) -> 64513.02 | H42: COSTO TOTAL DE LA PREPARACION | L42: =SUM(L40:L41) -> 2789.6 | N42: COSTO TOTAL DE LA PREPARACION | R42: =SUM(R40:R41) -> 5361.4
B43: PRECIO DE VENTA | F43: 18900 | H43: PRECIO DE VENTA | L43: 0 | N43: PRECIO DE VENTA | R43: 0
E44: 6 | F44: =F42/E44 -> 10752.17 | K44: 140 | L44: =L42/K44 -> 19.925714 | Q44: 600 | R44: =R42/Q44 -> 8.9356667
B46: QUESADILLA | H46: PASTA CARBONARA | N46: PASTA CARBONARA
B47: INGREDIENTES | C47: CANTIDAD | D47: UND MEDIDA | E47: COS/GR | F47: VALOR | H47: INGREDIENTES | I47: CANTIDAD | J47: UND MEDIDA | K47: COS/GR | L47: VALOR | N47: INGREDIENTES | O47: CANTIDAD | P47: UND MEDIDA | Q47: COS/GR | R47: VALOR
B48: TORTILLA | C48: 1 | D48: UND | F48: =C48*E48 -> 0 | J48: gr | L48: =I48*K48 -> 0 | P48: gr | R48: =O48*Q48 -> 0
B49: QUESO | D49: gr | F49: =C49*E49 -> 0 | J49: gr | L49: =I49*K49 -> 0 | P49: gr | R49: =O49*Q49 -> 0
B50: CHORIZO | D50: gr | F50: =C50*E50 -> 0 | J50: gr | L50: =I50*K50 -> 0 | P50: gr | R50: =O50*Q50 -> 0
D51: gr | F51: =C51*E51 -> 0 | J51: gr | L51: =I51*K51 -> 0 | P51: gr | R51: =O51*Q51 -> 0
D52: gr | F52: =C52*E52 -> 0 | J52: gr | L52: =I52*K52 -> 0 | P52: gr | R52: =O52*Q52 -> 0
D53: gr | F53: =C53*E53 -> 0 | J53: gr | L53: =I53*K53 -> 0 | P53: gr | R53: =O53*Q53 -> 0
D54: gr | F54: =C54*E54 -> 0 | J54: gr | L54: =I54*K54 -> 0 | P54: gr | R54: =O54*Q54 -> 0
F55: =C55*E55 -> 0 | L55: =I55*K55 -> 0 | R55: =O55*Q55 -> 0
F56: =C56*E56 -> 0 | L56: =I56*K56 -> 0 | R56: =O56*Q56 -> 0
B57: MATERIAL DE EMPAQUE | H57: MATERIAL DE EMPAQUE | N57: MATERIAL DE EMPAQUE
F58: =C58*140 -> 0 | L58: =I58*140 -> 0 | R58: =O58*140 -> 0
F59: =C59*140 -> 0 | L59: =I59*140 -> 0 | R59: =O59*140 -> 0
F60: =C60*140 -> 0 | L60: =I60*140 -> 0 | R60: =O60*140 -> 0
B61: COSTO + PRECIO DE VENTA | H61: COSTO + PRECIO DE VENTA | N61: COSTO + PRECIO DE VENTA
B62: COSTO DE INGREDIENTES | F62: =(F48+F49+F50+F51+F52+F53+F54+F55+F56+F60) -> 0 | H62: COSTO DE INGREDIENTES | L62: =(L48+L49+L50+L51+L52+L53+L54+L55+L56+L60) -> 0 | N62: COSTO DE INGREDIENTES | R62: =(R48+R49+R50+R51+R52+R53+R54+R55+R56+R60) -> 0
B63: MARGEN DE ERROR O VARIACION 10% | F63: =F62*0.1 -> 0 | H63: MARGEN DE ERROR O VARIACION 10% | L63: =L62*0.1 -> 0 | N63: MARGEN DE ERROR O VARIACION 10% | R63: =R62*0.1 -> 0
B64: COSTO TOTAL DE LA PREPARACION | F64: =SUM(F62:F63) -> 0 | H64: COSTO TOTAL DE LA PREPARACION | L64: =SUM(L62:L63) -> 0 | N64: COSTO TOTAL DE LA PREPARACION | R64: =SUM(R62:R63) -> 0
B65: PRECIO DE VENTA | F65: 30000 | H65: PRECIO DE VENTA | L65: 30000 | N65: PRECIO DE VENTA | R65: 30000

Sheet ARROCES
B2: ARROZ POLLO | H2: ARROZ MIXTO | N2: PASTA CARBONARA
B3: INGREDIENTES | C3: CANTIDAD | D3: UND MEDIDA | E3: COS/GR | F3: VALOR | H3: INGREDIENTES | I3: CANTIDAD | J3: UND MEDIDA | K3: COS/GR | L3: VALOR | N3: INGREDIENTES | O3: CANTIDAD | P3: UND MEDIDA | Q3: COS/GR | R3: VALOR
B4: ARROZ | C4: 200 | D4: gr | E4: 4.11 | F4: =C4*E4 -> 822 | H4: ARROZ | I4: 200 | J4: gr | K4: 4.11 | L4: =I4*K4 -> 822 | P4: gr | R4: =O4*Q4 -> 0
B5: PIMENTON | C5: 12 | D5: gr | E5: 3.58 | F5: =C5*E5 -> 42.96 | H5: PIMENTON | I5: 12 | J5: gr | K5: 3.58 | L5: =I5*K5 -> 42.96 | P5: gr | R5: =O5*Q5 -> 0
B6: CEBOLLA | C6: 12 | D6: gr | E6: 3.78 | F6: =C6*E6 -> 45.36 | H6: CEBOLLA | I6: 12 | J6: gr | K6: 3.78 | L6: =I6*K6 -> 45.36 | P6: gr | R6: =O6*Q6 -> 0
B7: TOMATE | C7: 14 | D7: gr | E7: 5.78 | F7: =C7*E7 -> 80.92 | H7: TOMATE | I7: 14 | J7: gr | K7: 5.78 | L7: =I7*K7 -> 80.92 | P7: gr | R7: =O7*Q7 -> 0
B8: ALVERJAS | C8: 12 | D8: gr | E8: 23.8 | F8: =C8*E8 -> 285.6 | H8: ALVERJAS | I8: 12 | J8: gr | K8: 23.8 | L8: =I8*K8 -> 285.6 | P8: gr | R8: =O8*Q8 -> 0
B9: GUISO | C9: 20 | D9: gr | E9: 10 | F9: =C9*E9 -> 200 | H9: GUISO | I9: 20 | J9: gr | K9: 10 | L9: =I9*K9 -> 200 | P9: gr | R9: =O9*Q9 -> 0
B10: POLLO | C10: 100 | D10: gr | E10: 21 | F10: =C10*E10 -> 2100 | H10: CHORIZO | I10: 50 | J10: gr | K10: 26.9 | L10: =I10*K10 -> 1345 | P10: gr | R10: =O10*Q10 -> 0
B11: PAPAS FRANCESAS | C11: 70 | D11: gr | E11: 8.2 | F11: =C11*E11 -> 574 | H11: CADERITA | I11: 50 | J11: gr | K11: 38.7 | L11: =I11*K11 -> 1935 | R11: =O11*Q11 -> 0
F12: =C12*E12 -> 0 | H12: PAPAS FRANCESAS | I12: 70 | J12: gr | K12: 8.2 | L12: =I12*K12 -> 574 | R12: =O12*Q12 -> 0
B13: MATERIAL DE EMPAQUE | H13: MATERIAL DE EMPAQUE | N13: MATERIAL DE EMPAQUE
F14: =C14*140 -> 0 | L14: =I14*140 -> 0 | R14: =O14*140 -> 0
F15: =C15*140 -> 0 | L15: =I15*140 -> 0 | R15: =O15*140 -> 0
F16: =C16*140 -> 0 | L16: =I16*140 -> 0 | R16: =O16*140 -> 0
B17: COSTO + PRECIO DE VENTA | H17: COSTO + PRECIO DE VENTA | N17: COSTO + PRECIO DE VENTA
B18: COSTO DE INGREDIENTES | F18: =(F4+F5+F6+F7+F8+F9+F10+F11+F12+F16) -> 4150.84 | H18: COSTO DE INGREDIENTES | L18: =(L4+L5+L6+L7+L8+L9+L10+L11+L12+L16) -> 5330.84 | N18: COSTO DE INGREDIENTES | R18: =(R4+R5+R6+R7+R8+R9+R10+R11+R12+R16) -> 0
B19: MARGEN DE ERROR O VARIACION 10% | F19: =F18*0.1 -> 415.084 | H19: MARGEN DE ERROR O VARIACION 10% | L19: =L18*0.1 -> 533.084 | N19: MARGEN DE ERROR O VARIACION 10% | R19: =R18*0.1 -> 0
B20: COSTO TOTAL DE LA PREPARACION | F20: =SUM(F18:F19) -> 4565.924 | H20: COSTO TOTAL DE LA PREPARACION | L20: =SUM(L18:L19) -> 5863.924 | N20: COSTO TOTAL DE LA PREPARACION | R20: =SUM(R18:R19) -> 0
B21: PRECIO DE VENTA | F21: 16900 | H21: PRECIO DE VENTA | L21: 17900 | N21: PRECIO DE VENTA | R21: 30000
B24: PASTA CARBONARA
B25: INGREDIENTES | C25: CANTIDAD | D25: UND MEDIDA | E25: COS/GR | F25: VALOR
D26: gr | F26: =C26*E26 -> 0
D27: gr | F27: =C27*E27 -> 0
D28: gr | F28: =C28*E28 -> 0
D29: gr | F29: =C29*E29 -> 0
D30: gr | F30: =C30*E30 -> 0
D31: gr | F31: =C31*E31 -> 0
D32: gr | F32: =C32*E32 -> 0
F33: =C33*E33 -> 0
F34: =C34*E34 -> 0
B35: MATERIAL DE EMPAQUE
F36: =C36*140 -> 0
F37: =C37*140 -> 0
F38: =C38*140 -> 0
B39: COSTO + PRECIO DE VENTA
B40: COSTO DE INGREDIENTES | F40: =(F26+F27+F28+F29+F30+F31+F32+F33+F34+F38) -> 0
B41: MARGEN DE ERROR O VARIACION 10% | F41: =F40*0.1 -> 0
B42: COSTO TOTAL DE LA PREPARACION | F42: =SUM(F40:F41) -> 0
B43: PRECIO DE VENTA | F43: 30000

Sheet ALMUERZOS Y CREMAS 
B2: MILANESA DE CERDO | H2: CUBITOS DE POLLO SALSA DE CILANTRO | N2: CADERITA EN SALSA DE CHAMPIÑON | T2: FILETE DE TILAPIA | Z2: BONDIOLA DE CERDO
B3: INGREDIENTES | C3: CANTIDAD | D3: UND MEDIDA | E3: COS/GR | F3: VALOR | H3: INGREDIENTES | I3: CANTIDAD | J3: UND MEDIDA | K3: COS/GR | L3: VALOR | N3: INGREDIENTES | O3: CANTIDAD | P3: UND MEDIDA | Q3: COS/GR | R3: VALOR | T3: INGREDIENTES | U3: CANTIDAD | V3: UND MEDIDA | W3: COS/GR | X3: VALOR | Z3: INGREDIENTES | AA3: CANTIDAD | AB3: UND MEDIDA | AC3: COS/GR | AD3: VALOR
B4: brazo de cerdo | C4: 150 | D4: gr | E4: 18.9 | F4: =C4*E4 -> 2835 | H4: pechuga de pollo | I4: 150 | J4: gr | K4: 21 | L4: =I4*K4 -> 3150 | N4: caderita | O4: 150 | P4: gr | Q4: 30.33 | R4: =O4*Q4 -> 4549.5 | T4: filete de tilapia | U4: 150 | V4: gr | W4: 32.8 | X4: =U4*W4 -> 4920 | Z4: Bondiola de cerdo | AA4: 150 | AB4: gr | AC4: 20 | AD4: =AA4*AC4 -> 3000
B5: sal | C5: 2 | D5: gr | E5: 2.6 | F5: =C5*E5 -> 5.2 | H5: sal | I5: 4 | J5: gr | K5: 2.6 | L5: =I5*K5 -> 10.4 | N5: sal | O5: 2 | P5: gr | Q5: 2.6 | R5: =O5*Q5 -> 5.2 | T5: sal | U5: 4 | V5: gr | W5: 2.6 | X5: =U5*W5 -> 10.4 | Z5: sal | AA5: 2 | AB5: gr | AC5: 2.6 | AD5: =AA5*AC5 -> 5.2
B6: pimienta | C6: 1 | D6: gr | E6: 58.17 | F6: =C6*E6 -> 58.17 | H6: ajo | I6: 4 | J6: gr | K6: 11 | L6: =I6*K6 -> 44 | N6: pimienta | O6: 1 | P6: gr | Q6: 58.17 | R6: =O6*Q6 -> 58.17 | T6: pimienta | U6: 2 | V6: gr | W6: 58.17 | X6: =U6*W6 -> 116.34 | Z6: pimienta | AA6: 1 | AB6: gr | AC6: 58.17 | AD6: =AA6*AC6 -> 58.17
B7: ajo | C7: 2 | D7: gr | E7: 11 | F7: =C7*E7 -> 22 | H7: pimienta | I7: 2 | J7: gr | K7: 58.17 | L7: =I7*K7 -> 116.34 | N7: pasta de ajo | O7: 3 | P7: gr | Q7: 11 | R7: =O7*Q7 -> 33 | T7: ajo | U7: 6 | V7: gr | W7: 11 | X7: =U7*W7 -> 66 | Z7: ajo | AA7: 2 | AB7: gr | AC7: 11 | AD7: =AA7*AC7 -> 22
B8: panko | C8: 70 | D8: gr | E8: 23.9 | F8: =C8*E8 -> 1673 | H8: cilantro | I8: 4 | J8: gr | K8: 10 | L8: =I8*K8 -> 40 | N8: cebolla cabezona | O8: 20 | P8: gr | Q8: 3.9 | R8: =O8*Q8 -> 78 | T8: limon | U8: 10 | V8: ml | W8: 4.9 | X8: =U8*W8 -> 49 | Z8: Papa cocida | AA8: 100 | AB8: UNID. | AC8: 2.5 | AD8: =AA8*AC8 -> 250
B9: agua | C9: 50 | D9: ml | E9: 26.35 | F9: =C9*E9 -> 1317.5 | H9: crema de leche | I9: 40 | J9: ml | K9: 23.74 | L9: =I9*K9 -> 949.6 | N9: crema de leche | O9: 40 | P9: gr | Q9: 23.74 | R9: =O9*Q9 -> 949.6 | T9: cilantro | U9: 4 | V9: gr | W9: 10 | X9: =U9*W9 -> 40 | Z9: Maduro Cocido | AA9: 125 | AB9: ml | AC9: 2.94 | AD9: =AA9*AC9 -> 367.5
B10: harina | C10: 60 | D10: gr | E10: 2.91 | F10: =C10*E10 -> 174.6 | H10: crema | I10: 1 | J10: gr | K10: 3950 | L10: =I10*K10 -> 3950 | N10: champiñon | O10: 10 | P10: gr | Q10: 31.1 | R10: =O10*Q10 -> 311 | T10: mantequilla | U10: 10 | V10: gr | W10: 16 | X10: =U10*W10 -> 160 | Z10: crema | AA10: 1 | AB10: gr | AC10: 3950 | AD10: =AA10*AC10 -> 3950
B11: crema | C11: 1 | D11: und | E11: 3950 | F11: =C11*E11 -> 3950 | H11: Ensalada | I11: 1 | J11: und | K11: 2278 | L11: =I11*K11 -> 2278 | N11: crema | O11: 1 | P11: gr | Q11: 3950 | R11: =O11*Q11 -> 3950 | T11: crema | U11: 1 | V11: gr | W11: 3950 | X11: =U11*W11 -> 3950 | Z11: Ensalada | AA11: 1 | AB11: und | AC11: 2278 | AD11: =AA11*AC11 -> 2278
B12: Arroz | C12: 100 | D12: gr | E12: 4.11 | F12: =C12*E12 -> 411 | H12: Arroz | I12: 100 | J12: gr | K12: 4.11 | L12: =I12*K12 -> 411 | N12: Arroz | O12: 100 | P12: gr | Q12: 4.11 | R12: =O12*Q12 -> 411 | T12: Arroz | U12: 100 | V12: gr | W12: 4.11 | X12: =U12*W12 -> 411 | Z12: Arroz | AA12: 100 | AB12: gr | AC12: 4.11 | AD12: =AA12*AC12 -> 411
B13: Maduro | C13: 25 | D13: gr | E13: 3.3 | F13: =C13*E13 -> 82.5 | H13: Maduro | I13: 25 | J13: gr | K13: 3.3 | L13: =I13*K13 -> 82.5 | N13: Maduro | O13: 25 | P13: gr | Q13: 3.3 | R13: =O13*Q13 -> 82.5 | T13: Maduro | U13: 25 | V13: gr | W13: 3.3 | X13: =U13*W13 -> 82.5 | Z13: Maduro | AA13: 25 | AB13: gr | AC13: 3.3 | AD13: =AA13*AC13 -> 82.5
B14: Papa | C14: 25 | D14: gr | E14: 4.5 | F14: =C14*E14 -> 112.5 | H14: Papa | I14: 25 | J14: gr | K14: 4.5 | L14: =I14*K14 -> 112.5 | N14: Papa | O14: 25 | P14: gr | Q14: 4.5 | R14: =O14*Q14 -> 112.5 | T14: Papa | U14: 25 | V14: gr | W14: 4.5 | X14: =U14*W14 -> 112.5 | Z14: Papa | AA14: 25 | AB14: gr | AC14: 4.5 | AD14: =AA14*AC14 -> 112.5
B15: Ensalada | C15: 1 | D15: und | E15: 2278 | F15: =C15*E15 -> 2278 | H15: Total | L15: =SUM(L4:L14) -> 11144.34 | N15: Ensalada | O15: 1 | P15: und | Q15: 2278 | R15: =O15*Q15 -> 2278 | T15: Ensalada | U15: 1 | V15: und | W15: 2278 | X15: =U15*W15 -> 2278 | Z15: Total | AD15: =SUM(AD4:AD14) -> 10536.87
B16: Total | F16: =SUM(F4:F15) -> 12919.47 | H16: MATERIAL DE EMPAQUE | N16: Total | R16: =SUM(R4:R15) -> 12818.47 | T16: Total | X16: =SUM(X4:X15) -> 12195.74 | Z16: MATERIAL DE EMPAQUE
B17: MATERIAL DE EMPAQUE | H17: Enpaque Roauter | I17: 1 | J17: und | K17: 1600 | L17: =I17*K17 -> 1600 | N17: MATERIAL DE EMPAQUE | T17: MATERIAL DE EMPAQUE | Z17: Enpaque Roauter | AA17: 1 | AB17: und | AC17: 1600 | AD17: =AA17*AC17 -> 1600
B18: Enpaque Roauter | C18: 1 | D18: und | E18: 1600 | F18: =C18*E18 -> 1600 | H18: tenedor y cuchillo | I18: 2 | J18: und | K18: 70 | L18: =I18*K18 -> 140 | N18: Enpaque Roauter | O18: 1 | P18: und | Q18: 1600 | R18: =O18*Q18 -> 1600 | T18: Enpaque Roauter | U18: 1 | V18: und | W18: 1600 | X18: =U18*W18 -> 1600 | Z18: tenedor y cuchillo | AA18: 2 | AB18: und | AC18: 70 | AD18: =AA18*AC18 -> 140
B19: tenedor y cuchillo | C19: 2 | D19: und | E19: 70 | F19: =C19*E19 -> 140 | H19: Total | L19: =SUM(L17:L18) -> 1740 | N19: tenedor y cuchillo | O19: 2 | P19: und | Q19: 70 | R19: =O19*Q19 -> 140 | T19: tenedor y cuchillo | U19: 2 | V19: und | W19: 70 | X19: =U19*W19 -> 140 | AD19: =SUM(AD17:AD18) -> 1740
B20: Total | F20: =SUM(F18:F19) -> 1740 | H20: COSTO + PRECIO DE VENTA | N20: Total | R20: =SUM(R18:R19) -> 1740 | T20: Total | X20: =SUM(X18:X19) -> 1740 | Z20: COSTO + PRECIO DE VENTA
B21: COSTO + PRECIO DE VENTA | H21: COSTO DE INGREDIENTES | L21: =L19+L15 -> 12884.34 | N21: COSTO + PRECIO DE VENTA | T21: COSTO + PRECIO DE VENTA | Z21: COSTO DE INGREDIENTES | AD21: =AD19+AD15 -> 12276.87
B22: COSTO DE INGREDIENTES | F22: =F20+F16 -> 14659.47 | H22: MARGEN DE ERROR O VARIACION 10% | L22: =L21*0.1 -> 1288.434 | N22: COSTO DE INGREDIENTES | R22: =R20+R16 -> 14558.47 | T22: COSTO DE INGREDIENTES | X22: =X20+X16 -> 13935.74 | Z22: MARGEN DE ERROR O VARIACION 10% | AD22: =AD21*0.1 -> 1227.687
B23: MARGEN DE ERROR O VARIACION 10% | F23: =F22*0.1 -> 1465.947 | H23: COSTO TOTAL DE LA PREPARACION | L23: =SUM(L21:L22) -> 14172.774 | N23: MARGEN DE ERROR O VARIACION 10% | R23: =R22*0.1 -> 1455.847 | T23: MARGEN DE ERROR O VARIACION 10% | X23: =X22*0.1 -> 1393.574 | Z23: COSTO TOTAL DE LA PREPARACION | AD23: =SUM(AD21:AD22) -> 13504.557
B24: COSTO TOTAL DE LA PREPARACION | F24: =SUM(F22:F23) -> 16125.417 | H24: PRECIO DE VENTA | L24: 24900 | N24: COSTO TOTAL DE LA PREPARACION | R24: =SUM(R22:R23) -> 16014.317 | T24: COSTO TOTAL DE LA PREPARACION | X24: =SUM(X22:X23) -> 15329.314 | Z24: PRECIO DE VENTA | AD24: 25900
B25: PRECIO DE VENTA | F25: 27900 | N25: PRECIO DE VENTA | R25: 27900 | T25: PRECIO DE VENTA | X25: 27900

Sheet PLATOS
B2: CHICHARON OREADO | H2: POLLO DORADO | N2: ENSALADA DE BONDIOLA
B3: INGREDIENTES | C3: CANTIDAD | D3: UND MEDIDA | E3: COS/GR | F3: VALOR | H3: INGREDIENTES | I3: CANTIDAD | J3: UND MEDIDA | K3: COS/GR | L3: VALOR | N3: INGREDIENTES | O3: CANTIDAD | P3: UND MEDIDA | Q3: COS/GR | R3: VALOR
B4: Chicharrón Oreado | C4: 250 | D4: gr | E4: 26.9 | F4: =C4*E4 -> 6725 | H4: Churrasquillo de pollo | I4: 470 | J4: gr | K4: 11.5 | L4: =I4*K4 -> 5405 | N4: Jamón de Bondiola Acaramelada | O4: 100 | P4: gr | Q4: 24.4 | R4: =O4*Q4 -> 2440
B5: Mix de papas | C5: 140 | D5: gr | E5: 5.5 | F5: =C5*E5 -> 770 | H5: Pure de maduro | I5: 200 | J5: gr | K5: 10 | L5: =I5*K5 -> 2000 | N5: Mix de Lechugas | O5: 100 | P5: gr | Q5: 20 | R5: =O5*Q5 -> 2000
B6: Miel de Caña | C6: 80 | D6: gr | E6: 8.14 | F6: =C6*E6 -> 651.2 | H6: Salsa artesanal de tomate y romero | I6: 100 | J6: gr | K6: 6.25 | L6: =I6*K6 -> 625 | N6: Cebolla Encurtida | O6: 40 | P6: gr | Q6: 12.6 | R6: =O6*Q6 -> 504
B7: ensalada | C7: 100 | D7: gr | E7: 20.71 | F7: =C7*E7 -> 2071 | H7: Jardinera | I7: 100 | J7: gr | K7: 10 | L7: =I7*K7 -> 1000 | N7: Miel de Caña | O7: 10 | P7: gr | Q7: 8.14 | R7: =O7*Q7 -> 81.4
B8: alioli cilantro | C8: 40 | D8: gr | E8: 10.8 | F8: =C8*E8 -> 432 | L8: =I8*K8 -> 0 | N8: chuney de piña | O8: 10 | P8: gr | Q8: 8.8 | R8: =O8*Q8 -> 88
B9: Chuney de piña | C9: 15 | D9: gr | E9: 8.8 | F9: =C9*E9 -> 132 | L9: =I9*K9 -> 0 | N9: queso costeño | O9: 20 | P9: gr | Q9: 22 | R9: =O9*Q9 -> 440
F10: =C10*E10 -> 0 | L10: =I10*K10 -> 0 | N10: almendras rebanadas | O10: 10 | P10: gr | Q10: 120 | R10: =O10*Q10 -> 1200
F11: =C11*E11 -> 0 | L11: =I11*K11 -> 0 | N11: tomate cherry | O11: 30 | P11: gr | Q11: 18.36 | R11: =O11*Q11 -> 550.8
F12: =SUM(F4:F11) -> 10781.2 | L12: =SUM(L4:L11) -> 9030 | N12: uchuva | O12: 30 | P12: gr | Q12: 14.76 | R12: =O12*Q12 -> 442.8
B13: MATERIAL DE EMPAQUE | H13: MATERIAL DE EMPAQUE | R13: =SUM(R4:R12) -> 7747
B14: Enpaque Roauter | C14: 1 | D14: und | E14: 1600 | F14: =C14*E14 -> 1600 | H14: Enpaque Roauter | I14: 1 | J14: und | K14: 1600 | L14: =I14*K14 -> 1600 | N14: MATERIAL DE EMPAQUE
B15: tenedor y cuchillo | C15: 2 | D15: und | E15: 70 | F15: =C15*E15 -> 140 | H15: tenedor y cuchillo | I15: 2 | J15: und | K15: 70 | L15: =I15*K15 -> 140 | N15: Enpaque Roauter | O15: 1 | P15: und | Q15: 1600 | R15: =O15*Q15 -> 1600
B16: Total | F16: =SUM(F14:F15) -> 1740 | H16: Total | L16: =SUM(L14:L15) -> 1740 | N16: tenedor y cuchillo | O16: 2 | P16: und | Q16: 70 | R16: =O16*Q16 -> 140
B17: COSTO + PRECIO DE VENTA | H17: COSTO + PRECIO DE VENTA | N17: Total | R17: =SUM(R15:R16) -> 1740
B18: COSTO DE INGREDIENTES | F18: =F12+F16 -> 12521.2 | H18: COSTO DE INGREDIENTES | L18: =L12+L16 -> 10770 | N18: COSTO + PRECIO DE VENTA
B19: MARGEN DE ERROR O VARIACION 10% | F19: =F18*0.1 -> 1252.12 | H19: MARGEN DE ERROR O VARIACION 10% | L19: =L18*0.1 -> 1077 | N19: COSTO DE INGREDIENTES | R19: =R13+R17 -> 9487
B20: COSTO TOTAL DE LA PREPARACION | F20: =SUM(F18:F19) -> 13773.32 | H20: COSTO TOTAL DE LA PREPARACION | L20: =SUM(L18:L19) -> 11847 | N20: MARGEN DE ERROR O VARIACION 10% | R20: =R19*0.1 -> 948.7
B21: PRECIO DE VENTA | F21: 47000 | H21: PRECIO DE VENTA | L21: 47000 | N21: COSTO TOTAL DE LA PREPARACION | R21: =SUM(R19:R20) -> 10435.7
N22: PRECIO DE VENTA | R22: 40000
B24: COSTILLA SOUS VIDE | H24: HAMBURGUESA MALAGANA
B25: INGREDIENTES | C25: CANTIDAD | D25: UND MEDIDA | E25: COS/GR | F25: VALOR | H25: INGREDIENTES | I25: CANTIDAD | J25: UND MEDIDA | K25: COS/GR | L25: VALOR | N25: HAMBURGUESA CACIQUE
B26: COSTILLA TIPO LLANERA | C26: 500 | D26: gr | E26: 21 | F26: =C26*E26 -> 10500 | H26: Pan brioche | I26: 1 | J26: Und | K26: 1050 | L26: =I26*K26 -> 1050 | N26: INGREDIENTES | O26: CANTIDAD | P26: UND MEDIDA | Q26: COS/GR | R26: VALOR
B27: REDUCCION DE FLOR DE JAMAICA | C27: 90 | D27: gr | F27: =C27*E27 -> 0 | H27: mantequilla de chontaduro | I27: 10 | J27: gr | K27: 18.5 | L27: =I27*K27 -> 185 | N27: Carne angus americana | O27: 180 | P27: gr | Q27: 22.9 | R27: =O27*Q27 -> 4122
B28: ENSALADA FRESCA | C28: 100 | D28: gr | E28: 21 | F28: =C28*E28 -> 2100 | H28: carne artesanal | I28: 150 | J28: gr | K28: 22.9 | L28: =I28*K28 -> 3435 | N28: queso philadelphia | O28: 40 | P28: gr | Q28: 32.28 | R28: =O28*Q28 -> 1291.2
B29: PAPAS AMARILLAS EN CASCO | C29: 140 | D29: gr | E29: 5.5 | F29: =C29*E29 -> 770 | H29: Dip de tocineta | I29: 30 | J29: gr | K29: 24.47 | L29: =I29*K29 -> 734.1 | N29: cebolla crispy | O29: 30 | P29: gr | Q29: 4.4 | R29: =O29*Q29 -> 132
B30: ALIOLI DE CILANTRO | C30: 40 | D30: gr | E30: 10.8 | F30: =C30*E30 -> 432 | H30: cebolla caramelizada en uchuva | I30: 30 | J30: gr | K30: 5.2 | L30: =I30*K30 -> 156 | N30: lechuga de temporada | O30: 10 | P30: gr | Q30: 20 | R30: =O30*Q30 -> 200
F31: =C31*E31 -> 0 | H31: lechuga de temporada | I31: 10 | J31: gr | K31: 20 | L31: =I31*K31 -> 200 | N31: tomate milano | O31: 30 | P31: gr | Q31: 7.98 | R31: =O31*Q31 -> 239.4
F32: =C32*E32 -> 0 | H32: tomate milano | I32: 30 | J32: gr | K32: 7.98 | L32: =I32*K32 -> 239.4 | N32: pan brioche artesanal | O32: 1 | P32: gr | Q32: 1050 | R32: =O32*Q32 -> 1050
F33: =C33*E33 -> 0 | H33: mix de papa | I33: 140 | J33: gr | K33: 5.5 | L33: =I33*K33 -> 770 | N33: tocineta | O33: 25 | P33: gr | Q33: 25.9 | R33: =O33*Q33 -> 647.5
H34: alioli cilantro | I34: 40 | J34: gr | K34: 10.8 | L34: =I34*K34 -> 432 | N34: Dip de pepinillos | O34: 40 | P34: gr | R34: =O34*Q34 -> 0
F35: =SUM(F26:F34) -> 13802 | L35: =SUM(L26:L34) -> 7201.5 | N35: mix de papas | O35: 140 | P35: gr | Q35: 5.5 | R35: =O35*Q35 -> 770
B36: MATERIAL DE EMPAQUE | H36: MATERIAL DE EMPAQUE | N36: salsa de la casa | O36: 40 | P36: gr | Q36: 10.8 | R36: =O36*Q36 -> 432
B37: Enpaque Roauter | C37: 1 | D37: und | E37: 1600 | F37: =C37*E37 -> 1600 | H37: Enpaque Roauter | I37: 1 | J37: und | K37: 1600 | L37: =I37*K37 -> 1600 | N37: MATERIAL DE EMPAQUE
B38: tenedor y cuchillo | C38: 2 | D38: und | E38: 70 | F38: =C38*E38 -> 140 | H38: tenedor y cuchillo | I38: 2 | J38: und | K38: 70 | L38: =I38*K38 -> 140 | R38: =O38*140 -> 0
B39: Total | F39: =SUM(F37:F38) -> 1740 | H39: Total | L39: =SUM(L37:L38) -> 1740 | R39: =O39*140 -> 0
B40: COSTO + PRECIO DE VENTA | H40: COSTO + PRECIO DE VENTA | R40: =O40*140 -> 0
B41: COSTO DE INGREDIENTES | F41: =F35+F39 -> 15542 | H41: COSTO DE INGREDIENTES | L41: =L35+L39 -> 8941.5 | N41: COSTO + PRECIO DE VENTA
B42: MARGEN DE ERROR O VARIACION 10% | F42: =F41*0.1 -> 1554.2 | H42: MARGEN DE ERROR O VARIACION 10% | L42: =L41*0.1 -> 894.15 | N42: COSTO DE INGREDIENTES | R42: =(R27+R28+R29+R30+R31+R32+R33+R34+R35+R36+R40) -> 8884.1
B43: COSTO TOTAL DE LA PREPARACION | F43: =SUM(F41:F42) -> 17096.2 | H43: COSTO TOTAL DE LA PREPARACION | L43: =SUM(L41:L42) -> 9835.65 | N43: MARGEN DE ERROR O VARIACION 10% | R43: =R42*0.1 -> 888.41
B44: PRECIO DE VENTA | F44: 55000 | H44: PRECIO DE VENTA | L44: 30000 | N44: COSTO TOTAL DE LA PREPARACION | R44: =SUM(R42:R43) -> 9772.51
N45: PRECIO DE VENTA | R45: 38000
B47: PASTA CARBONARA | H47: PASTA CARBONARA
B48: INGREDIENTES | C48: CANTIDAD | D48: UND MEDIDA | E48: COS/GR | F48: VALOR | H48: INGREDIENTES | I48: CANTIDAD | J48: UND MEDIDA | K48: COS/GR | L48: VALOR | N48: PASTA CARBONARA
D49: gr | F49: =C49*E49 -> 0 | J49: gr | L49: =I49*K49 -> 0 | N49: INGREDIENTES | O49: CANTIDAD | P49: UND MEDIDA | Q49: COS/GR | R49: VALOR
D50: gr | F50: =C50*E50 -> 0 | J50: gr | L50: =I50*K50 -> 0 | P50: gr | R50: =O50*Q50 -> 0
D51: gr | F51: =C51*E51 -> 0 | J51: gr | L51: =I51*K51 -> 0 | P51: gr | R51: =O51*Q51 -> 0
D52: gr | F52: =C52*E52 -> 0 | J52: gr | L52: =I52*K52 -> 0 | P52: gr | R52: =O52*Q52 -> 0
D53: gr | F53: =C53*E53 -> 0 | J53: gr | L53: =I53*K53 -> 0 | P53: gr | R53: =O53*Q53 -> 0
D54: gr | F54: =C54*E54 -> 0 | J54: gr | L54: =I54*K54 -> 0 | P54: gr | R54: =O54*Q54 -> 0
D55: gr | F55: =C55*E55 -> 0 | J55: gr | L55: =I55*K55 -> 0 | P55: gr | R55: =O55*Q55 -> 0
F56: =C56*E56 -> 0 | L56: =I56*K56 -> 0 | P56: gr | R56: =O56*Q56 -> 0
R57: =O57*Q57 -> 0
F58: =C58*E58 -> 0 | L58: =I58*K58 -> 0
B59: MATERIAL DE EMPAQUE | H59: MATERIAL DE EMPAQUE | R59: =O59*Q59 -> 0
F60: =C60*140 -> 0 | L60: =I60*140 -> 0 | N60: MATERIAL DE EMPAQUE
F61: =C61*140 -> 0 | L61: =I61*140 -> 0 | R61: =O61*140 -> 0
F62: =C62*140 -> 0 | L62: =I62*140 -> 0 | R62: =O62*140 -> 0
B63: COSTO + PRECIO DE VENTA | H63: COSTO + PRECIO DE VENTA | R63: =O63*140 -> 0
B64: COSTO DE INGREDIENTES | F64: =(F49+F50+F51+F52+F53+F54+F55+F56+F58+F60+F61+F62) -> 0 | H64: COSTO DE INGREDIENTES | L64: =(L49+L50+L51+L52+L53+L54+L55+L56+L58+L60+L61+L62) -> 0 | N64: COSTO + PRECIO DE VENTA
B65: MARGEN DE ERROR O VARIACION 10% | F65: =F64*0.1 -> 0 | H65: MARGEN DE ERROR O VARIACION 10% | L65: =L64*0.1 -> 0 | N65: COSTO DE INGREDIENTES | R65: =(R50+R51+R52+R53+R54+R55+R56+R57+R59+R61+R62+R63) -> 0
B66: COSTO TOTAL DE LA PREPARACION | F66: =SUM(F64:F65) -> 0 | H66: COSTO TOTAL DE LA PREPARACION | L66: =SUM(L64:L65) -> 0 | N66: MARGEN DE ERROR O VARIACION 10% | R66: =R65*0.1 -> 0
B67: PRECIO DE VENTA | F67: 30000 | H67: PRECIO DE VENTA | L67: 30000 | N67: COSTO TOTAL DE LA PREPARACION | R67: =SUM(R65:R66) -> 0
N68: PRECIO DE VENTA | R68: 30000

Sheet PIZZAS
B2: MASA PARA PIZZA X 4 | H2: CARNES | N2: MARGARITA | T2: SAMBA | Z2: ORIGEN
B3: INGREDIENTES | C3: CANTIDAD | D3: UND MEDIDA | E3: COS/GR | F3: VALOR | H3: INGREDIENTES | I3: CANTIDAD | J3: UND MEDIDA | K3: COS/GR | L3: VALOR | N3: INGREDIENTES | O3: CANTIDAD | P3: UND MEDIDA | Q3: COS/GR | R3: VALOR | T3: INGREDIENTES | U3: CANTIDAD | V3: UND MEDIDA | W3: COS/GR | X3: VALOR | Z3: INGREDIENTES | AA3: CANTIDAD | AB3: UND MEDIDA | AC3: COS/GR | AD3: VALOR
B4: Harina de trigo | C4: 600 | D4: gr | E4: 9.2 | F4: =C4*E4 -> 5520 | H4: Masa para Pizza | I4: 150 | J4: gr | K4: 10.4 | L4: =I4*K4 -> 1560 | N4: Masa para Pizza | O4: 150 | P4: gr | Q4: 10.4 | R4: =O4*Q4 -> 1560 | T4: napolitana | U4: 60 | V4: gr | W4: 34.7 | X4: =U4*W4 -> 2082 | Z4: napolitana | AA4: 60 | AB4: gr | AC4: 34.7 | AD4: =AA4*AC4 -> 2082
B5: Levadura | C5: 5 | D5: gr | E5: 23.8 | F5: =C5*E5 -> 119 | H5: Salsa Napolitana | I5: 80 | J5: gr | K5: 11 | L5: =I5*K5 -> 880 | N5: Salsa Napolitana | O5: 80 | P5: gr | Q5: 34.7 | R5: =O5*Q5 -> 2776 | T5: queso mozarella | U5: 150 | V5: gr | W5: 23.2 | X5: =U5*W5 -> 3480 | Z5: queso mozarella | AA5: 150 | AB5: gr | AC5: 23.2 | AD5: =AA5*AC5 -> 3480
B6: Sal | C6: 3 | D6: gr | E6: 2.6 | F6: =C6*E6 -> 7.8 | H6: Queso Mozarrella | I6: 150 | J6: gr | K6: 19.5 | L6: =I6*K6 -> 2925 | N6: Tomate Chery | O6: 20 | P6: gr | Q6: 34 | R6: =O6*Q6 -> 680 | T6: maduro | U6: 40 | V6: gr | W6: 5.16 | X6: =U6*W6 -> 206.4 | Z6: chorizo | AA6: 47 | AB6: gr | AC6: 52.63 | AD6: =AA6*AC6 -> 2473.61
B7: Agua | C7: 250 | D7: ml | E7: 26 | F7: =C7*E7 -> 6500 | H7: Bondiola | I7: 40 | J7: gr | K7: 36 | L7: =I7*K7 -> 1440 | N7: Queso Mozarrella | O7: 150 | P7: gr | Q7: 19.5 | R7: =O7*Q7 -> 2925 | T7: tocineta | U7: 80 | V7: gr | W7: 34.8 | X7: =U7*W7 -> 2784 | Z7: merma de carne | AA7: 90 | AB7: gr | AC7: 58 | AD7: =AA7*AC7 -> 5220
F8: =C8*E8 -> 0 | H8: Tocineta | I8: 20 | J8: gr | K8: 23 | L8: =I8*K8 -> 460 | N8: Albahaca Genovesa | O8: 5 | P8: gr | Q8: 11 | R8: =O8*Q8 -> 55 | T8: masa de pizza | U8: 150 | V8: gr | W8: 10.4 | X8: =U8*W8 -> 1560 | Z8: chimichurri | AA8: 20 | AB8: gr | AC8: 24.03 | AD8: =AA8*AC8 -> 480.6
F9: =C9*E9 -> 0 | H9: Miel Caña | I9: 5 | J9: ml | K9: 0 | L9: =I9*K9 -> 0 | N9: Aceite de Oliva | O9: 5 | P9: ml | Q9: 8 | R9: =O9*Q9 -> 40 | X9: =U9*W9 -> 0 | Z9: masa de pizza | AA9: 150 | AB9: gr | AC9: 10.4 | AD9: =AA9*AC9 -> 1560
B10: MATERIAL DE EMPAQUE | H10: MATERIAL DE EMPAQUE | N10: MATERIAL DE EMPAQUE | T10: MATERIAL DE EMPAQUE | Z10: MATERIAL DE EMPAQUE
F11: =C11*140 -> 0 | H11: Caja de Pizza | I11: 1 | J11: und | K11: 1800 | L11: =I11*K11 -> 1800 | N11: Caja de Pizza | O11: 1 | P11: und | Q11: 1800 | R11: =O11*Q11 -> 1800 | T11: Caja de Pizza | U11: 1 | V11: und | W11: 1800 | X11: =U11*W11 -> 1800 | Z11: Caja de Pizza | AA11: 1 | AB11: und | AC11: 1800 | AD11: =AA11*AC11 -> 1800
F12: =C12*140 -> 0 | L12: =I12*140 -> 0 | R12: =O12*140 -> 0 | X12: =U12*140 -> 0 | AD12: =AA12*140 -> 0
F13: =C13*140 -> 0 | L13: =SUM(L11:L12) -> 1800 | R13: =SUM(R11:R12) -> 1800 | X13: =SUM(X11:X12) -> 1800 | AD13: =SUM(AD11:AD12) -> 1800
B14: COSTO + PRECIO DE VENTA | H14: COSTO + PRECIO DE VENTA | N14: COSTO + PRECIO DE VENTA | T14: COSTO + PRECIO DE VENTA | Z14: COSTO + PRECIO DE VENTA
B15: COSTO DE INGREDIENTES | F15: =(F4+F5+F6+F7+F8+F9+F11+F12+F13) -> 12146.8 | H15: COSTO DE INGREDIENTES | L15: =(L4+L5+L6+L7+L8+L9+L13) -> 9065 | N15: COSTO DE INGREDIENTES | R15: =(R4+R5+R6+R7+R8+R9+R11+R12+R13) -> 11636 | T15: COSTO DE INGREDIENTES | X15: =(X4+X5+X6+X7+X8+X9+X11+X12+X13) -> 13712.4 | Z15: COSTO DE INGREDIENTES | AD15: =(AD4+AD5+AD6+AD7+AD8+AD9+AD11+AD12+AD13) -> 18896.21
B16: MARGEN DE ERROR O VARIACION 10% | F16: =F15*0.1 -> 1214.68 | H16: MARGEN DE ERROR O VARIACION 10% | L16: =L15*0.1 -> 906.5 | N16: MARGEN DE ERROR O VARIACION 10% | R16: =R15*0.1 -> 1163.6 | T16: MARGEN DE ERROR O VARIACION 10% | X16: =X15*0.1 -> 1371.24 | Z16: MARGEN DE ERROR O VARIACION 10% | AD16: =AD15*0.1 -> 1889.621
B17: COSTO TOTAL DE LA PREPARACION | F17: =SUM(F15:F16) -> 13361.48 | H17: COSTO TOTAL DE LA PREPARACION | L17: =SUM(L15:L16) -> 9971.5 | N17: COSTO TOTAL DE LA PREPARACION | R17: =SUM(R15:R16) -> 12799.6 | T17: COSTO TOTAL DE LA PREPARACION | X17: =SUM(X15:X16) -> 15083.64 | Z17: COSTO TOTAL DE LA PREPARACION | AD17: =SUM(AD15:AD16) -> 20785.831
B18: PRECIO DE VENTA | F18: =F17 -> 13361.48 | H18: PRECIO DE VENTA | L18: 38000 | N18: PRECIO DE VENTA | R18: 30000 | T18: PRECIO DE VENTA | X18: 32000 | Z18: PRECIO DE VENTA | AD18: 38000
X22: =X17/X18 -> 0.47136375

Sheet SUB RESETAS
B2: CEBOLLAS ENCURTIDAS | H2: ALIOLI DE CILANTRO | N2: SALSA DE AJO
B3: INGREDIENTES | C3: CANTIDAD | D3: UND MEDIDA | E3: COS/GR | F3: VALOR | H3: INGREDIENTES | I3: CANTIDAD | J3: UND MEDIDA | K3: COS/GR | L3: VALOR | N3: INGREDIENTES | O3: CANTIDAD | P3: UND MEDIDA | Q3: COS/GR | R3: VALOR
B4: cebolla cabezona | C4: 300 | D4: gr | E4: 3.8 | F4: =C4*E4 -> 1140 | H4: Cilantro | I4: 100 | J4: gr | K4: 6 | L4: =I4*K4 -> 600 | N4: HUEVOS | O4: 2 | P4: gr | Q4: 498 | R4: =O4*Q4 -> 996
B5: azucar | C5: 60 | D5: gr | E5: 4.4 | F5: =C5*E5 -> 264 | H5: huevo | I5: 2 | J5: gr | K5: 498 | L5: =I5*K5 -> 996 | N5: DIENTES DE AJO | O5: 20 | P5: gr | Q5: 15 | R5: =O5*Q5 -> 300
B6: sal | C6: 25 | D6: gr | E6: 2.4 | F6: =C6*E6 -> 60 | H6: vinagre blanco | I6: 10 | J6: gr | K6: 7.6 | L6: =I6*K6 -> 76 | N6: ACEITE | O6: 1000 | P6: gr | Q6: 8.27 | R6: =O6*Q6 -> 8270
B7: pimienta dulce | C7: 10 | D7: gr | E7: 52 | F7: =C7*E7 -> 520 | H7: sal | I7: 10 | J7: gr | K7: 2.4 | L7: =I7*K7 -> 24 | N7: PAN DE MOLDE | O7: 20 | P7: gr | Q7: 6.8 | R7: =O7*Q7 -> 136
B8: vinagre blanco | C8: 100 | D8: gr | E8: 7.6 | F8: =C8*E8 -> 760 | H8: pimienta | I8: 10 | J8: gr | K8: 52 | L8: =I8*K8 -> 520 | N8: LECHE | O8: 50 | P8: gr | Q8: 4.9 | R8: =O8*Q8 -> 245
F9: =C9*E9 -> 0 | H9: ajo | I9: 20 | J9: gr | K9: 13 | L9: =I9*K9 -> 260 | N9: SAL | O9: 10 | P9: gr | Q9: 2.4 | R9: =O9*Q9 -> 24
F10: =C10*E10 -> 0 | H10: aceite de soya | I10: 500 | J10: gr | K10: 8.27 | L10: =I10*K10 -> 4135 | N10: PIMIENTA | O10: 5 | P10: gr | Q10: 52 | R10: =O10*Q10 -> 260
F11: =C11*E11 -> 0 | H11: cebolla | I11: 20 | J11: gr | K11: 4.4 | L11: =I11*K11 -> 88 | R11: =O11*Q11 -> 0
F12: =C12*E12 -> 0 | J12: gr
F13: =C13*E13 -> 0 | J13: gr | L13: =I13*K13 -> 0 | R13: =O13*Q13 -> 0
B14: MATERIAL DE EMPAQUE | H14: MATERIAL DE EMPAQUE | N14: MATERIAL DE EMPAQUE
F15: =C15*E15 -> 0 | L15: =I15*140 -> 0 | R15: =O15*140 -> 0
F16: =C16*E16 -> 0 | L16: =I16*140 -> 0 | R16: =O16*140 -> 0
F17: =C17*140 -> 0 | L17: =I17*140 -> 0 | R17: =O17*140 -> 0
B18: COSTO + PRECIO DE VENTA | H18: COSTO + PRECIO DE VENTA | N18: COSTO + PRECIO DE VENTA
B19: COSTO DE INGREDIENTES | F19: =F17+F16+F15+F13+F12+F11+F10+F9+F8+F7+F6+F5+F4 -> 2744 | H19: COSTO DE INGREDIENTES | L19: =(L4+L5+L6+L7+L8+L9+L10+L11+L13+L17) -> 6699 | N19: COSTO DE INGREDIENTES | R19: =(R4+R5+R6+R7+R8+R9+R10+R11+R13+R17) -> 10231
B20: MARGEN DE ERROR O VARIACION 10% | F20: =F19*0.1 -> 274.4 | H20: MARGEN DE ERROR O VARIACION 10% | L20: =L19*0.1 -> 669.9 | N20: MARGEN DE ERROR O VARIACION 10% | R20: =R19*0.1 -> 1023.1
B21: COSTO TOTAL DE LA PREPARACION | F21: =SUM(F19:F20) -> 3018.4 | H21: COSTO TOTAL DE LA PREPARACION | L21: =SUM(L19:L20) -> 7368.9 | N21: COSTO TOTAL DE LA PREPARACION | R21: =SUM(R19:R20) -> 11254.1
B22: PRECIO DE VENTA | F22: 0 | H22: PRECIO DE VENTA | L22: 0 | N22: PRECIO DE VENTA | R22: 0
E23: 495 | F23: =F21/E23 -> 6.0977778 | K23: 680 | L23: =L21/K23 -> 10.836618 | Q23: 1100 | R23: =R21/Q23 -> 10.231
B25: JARDINERA | H25: PULPO | N25: PURE DE MADURO
B26: INGREDIENTES | C26: CANTIDAD | D26: UND MEDIDA | E26: COS/GR | F26: VALOR | H26: INGREDIENTES | I26: CANTIDAD | J26: UND MEDIDA | K26: COS/GR | L26: VALOR | N26: INGREDIENTES | O26: CANTIDAD | P26: UND MEDIDA | Q26: COS/GR | R26: VALOR
B27: Pimenton | C27: 50 | D27: gr | E27: 3.58 | F27: =C27*E27 -> 179 | H27: Pulpo | I27: 2000 | J27: gr | K27: 63.5 | L27: =I27*K27 -> 127000 | N27: Platano Guayabo | O27: 200 | P27: gr | Q27: 3.98 | R27: =O27*Q27 -> 796
B28: Cebolla morada | C28: 50 | D28: gr | E28: 4.58 | F28: =C28*E28 -> 229 | H28: Zanahoria | I28: 50 | J28: gr | K28: 4.6 | L28: =I28*K28 -> 230 | N28: Merjumbre de maduro | O28: 50 | P28: gr | Q28: 30 | R28: =O28*Q28 -> 1500
B29: Ajo | C29: 2 | D29: gr | E29: 15 | F29: =C29*E29 -> 30 | H29: Cebolla blanca | I29: 100 | J29: gr | K29: 3.8 | L29: =I29*K29 -> 380 | P29: gr | R29: =O29*Q29 -> 0
B30: Sal | C30: 1 | D30: gr | E30: 2.4 | F30: =C30*E30 -> 2.4 | H30: Apio | I30: 50 | J30: gr | K30: 5.3 | L30: =I30*K30 -> 265 | P30: gr | R30: =O30*Q30 -> 0
B31: Menjumbre | C31: 20 | D31: gr | E31: 30 | F31: =C31*E31 -> 600 | H31: Pimineta | I31: 5 | J31: gr | K31: 52 | L31: =I31*K31 -> 260 | P31: gr | R31: =O31*Q31 -> 0
B32: Curcuma | C32: 2 | D32: gr | E32: 44.8 | F32: =C32*E32 -> 89.6 | H32: puerro | I32: 100 | J32: gr | K32: 52 | L32: =I32*K32 -> 5200 | P32: gr | R32: =O32*Q32 -> 0
F33: =C33*E33 -> 0 | H33: Ajo | I33: 10 | J33: gr | K33: 15 | L33: =I33*K33 -> 150 | P33: gr | R33: =O33*Q33 -> 0
F34: =C34*E34 -> 0 | H34: Laurel | I34: 1 | J34: gr | K34: 55.6 | L34: =I34*K34 -> 55.6 | R34: =O34*Q34 -> 0
H35: Tomillo | I35: 5 | J35: gr | K35: 45 | L35: =I35*K35 -> 225
H36: Sal | I36: 50 | J36: gr | K36: 2.4 | L36: =I36*K36 -> 120 | R36: =O36*Q36 -> 0
B37: MATERIAL DE EMPAQUE | N37: MATERIAL DE EMPAQUE
F38: =C38*140 -> 0 | R38: =O38*140 -> 0
F39: =C39*140 -> 0 | R39: =O39*140 -> 0
F40: =C40*140 -> 0 | R40: =O40*140 -> 0
B41: COSTO + PRECIO DE VENTA | H41: COSTO + PRECIO DE VENTA | N41: COSTO + PRECIO DE VENTA
B42: COSTO DE INGREDIENTES | F42: =(F27+F28+F29+F30+F31+F32+F33+F34+F36+F40) -> 1130 | H42: COSTO DE INGREDIENTES | L42: =(L27+L28+L29+L30+L31+L32+L33+L34+L36+L40) -> 133660.6 | N42: COSTO DE INGREDIENTES | R42: =(R27+R28+R29+R30+R31+R32+R33+R34+R36+R40) -> 2296
B43: MARGEN DE ERROR O VARIACION 10% | F43: =F42*0.1 -> 113 | H43: MARGEN DE ERROR O VARIACION 10% | L43: =L42*0.1 -> 13366.06 | N43: MARGEN DE ERROR O VARIACION 10% | R43: =R42*0.1 -> 229.6
B44: COSTO TOTAL DE LA PREPARACION | F44: =SUM(F42:F43) -> 1243 | H44: COSTO TOTAL DE LA PREPARACION | L44: =SUM(L42:L43) -> 147026.66 | N44: COSTO TOTAL DE LA PREPARACION | R44: =SUM(R42:R43) -> 2525.6
B45: PRECIO DE VENTA | F45: 0 | H45: PRECIO DE VENTA | N45: PRECIO DE VENTA | R45: 0
E46: 125 | F46: =F44/E46 -> 9.944 | K46: 2480 | L46: =L44/K46 -> 59.284944 | Q46: 250 | R46: =R44/Q46 -> 10.1024
B48: CHICHARON OREADO | H48: CHURRASQUILLO DE POLLO | N48: COSTILLA SOUS VIDE
B49: INGREDIENTES | C49: CANTIDAD | D49: UND MEDIDA | E49: COS/GR | F49: VALOR | H49: INGREDIENTES | I49: CANTIDAD | J49: UND MEDIDA | K49: COS/GR | L49: VALOR | N49: INGREDIENTES | O49: CANTIDAD | P49: UND MEDIDA | Q49: COS/GR | R49: VALOR
B50: Chicharon barriguero | C50: 250 | D50: gr | E50: 25.4 | F50: =C50*E50 -> 6350 | H50: Pernil de pollo | I50: 450 | J50: gr | K50: 9.98 | L50: =I50*K50 -> 4491 | N50: Costilla tipo llanera | O50: 500 | P50: gr | Q50: 19.9 | R50: =O50*Q50 -> 9950
B51: Azucar | C51: 11.4 | D51: gr | E51: 4.4 | F51: =C51*E51 -> 50.16 | H51: Pasta de ajo | I51: 3.25 | J51: gr | K51: 15 | L51: =I51*K51 -> 48.75 | N51: Pasta de ajo | O51: 11.25 | P51: gr | Q51: 15 | R51: =O51*Q51 -> 168.75
B52: Sal refinada | C52: 7 | D52: gr | E52: 2.4 | F52: =C52*E52 -> 16.8 | H52: Limon | I52: 3.5 | J52: gr | K52: 2 | L52: =I52*K52 -> 7 | N52: Cebolla | O52: 20 | P52: gr | Q52: 3.8 | R52: =O52*Q52 -> 76
B53: Paprika | C53: 8.5 | D53: gr | E53: 48 | F53: =C53*E53 -> 408 | H53: Sal | I53: 4.25 | J53: gr | K53: 2.4 | L53: =I53*K53 -> 10.2 | N53: Tomillo | O53: 1.25 | P53: gr | Q53: 45 | R53: =O53*Q53 -> 56.25
B54: Comino | C54: 0.5 | D54: gr | E54: 24 | F54: =C54*E54 -> 12 | H54: Pimienta | I54: 4.75 | J54: gr | K54: 52 | L54: =I54*K54 -> 247 | N54: Pimenta | O54: 1.25 | P54: gr | Q54: 52 | R54: =O54*Q54 -> 65
B55: Pasta de ajo | C55: 1.4 | D55: gr | E55: 15 | F55: =C55*E55 -> 21 | H55: Vino blanco | I55: 5.25 | J55: gr | K55: 19.5 | L55: =I55*K55 -> 102.375 | N55: Naranja | O55: 15 | P55: gr | Q55: 3.99 | R55: =O55*Q55 -> 59.85
D56: gr | F56: =C56*E56 -> 0 | J56: gr | L56: =I56*K56 -> 0 | N56: Paprika | O56: 0.6 | P56: gr | Q56: 48 | R56: =O56*Q56 -> 28.8
F57: =C57*E57 -> 0 | L57: =I57*K57 -> 0 | N57: Vinagre de manzana | O57: 15 | P57: gr | Q57: 32 | R57: =O57*Q57 -> 480
F58: =C58*E58 -> 0 | L58: =I58*K58 -> 0 | N58: Comino | O58: 1.25 | P58: gr | Q58: 24 | R58: =O58*Q58 -> 30
B59: MATERIAL DE EMPAQUE | H59: MATERIAL DE EMPAQUE | N59: Sal | O59: 6.25 | P59: gr | Q59: 2.4 | R59: =O59*Q59 -> 15
F60: =C60*140 -> 0 | L60: =I60*140 -> 0 | R60: =O60*140 -> 0
F61: =C61*140 -> 0 | L61: =I61*140 -> 0 | R61: =O61*140 -> 0
F62: =C62*140 -> 0 | L62: =I62*140 -> 0 | R62: =O62*140 -> 0
B63: COSTO + PRECIO DE VENTA | H63: COSTO + PRECIO DE VENTA | N63: COSTO + PRECIO DE VENTA
B64: COSTO DE INGREDIENTES | F64: =(F50+F51+F52+F53+F54+F55+F56+F57+F58+F62) -> 6857.96 | H64: COSTO DE INGREDIENTES | L64: =(L50+L51+L52+L53+L54+L55+L56+L57+L58+L62) -> 4906.325 | N64: COSTO DE INGREDIENTES | R64: =(R50+R51+R52+R53+R54+R55+R56+R57+R58+R59+R62) -> 10929.65
B65: MARGEN DE ERROR O VARIACION 10% | F65: =F64*0.1 -> 685.796 | H65: MARGEN DE ERROR O VARIACION 10% | L65: =L64*0.1 -> 490.6325 | N65: MARGEN DE ERROR O VARIACION 10% | R65: =R64*0.1 -> 1092.965
B66: COSTO TOTAL DE LA PREPARACION | F66: =SUM(F64:F65) -> 7543.756 | H66: COSTO TOTAL DE LA PREPARACION | L66: =SUM(L64:L65) -> 5396.9575 | N66: COSTO TOTAL DE LA PREPARACION | R66: =SUM(R64:R65) -> 12022.615
B67: PRECIO DE VENTA | F67: 0 | H67: PRECIO DE VENTA | L67: 0 | N67: PRECIO DE VENTA | R67: 0
E68: 280 | F68: =F66/E68 -> 26.941986 | K68: 471 | L68: =L66/K68 -> 11.458508 | Q68: 572 | R68: =R66/Q68 -> 21.018558
B70: JAMON DE BONDIOLA ACARAMELADO | H70: MINI BAOS | N70: MANJUMBRE
B71: INGREDIENTES | C71: CANTIDAD | D71: UND MEDIDA | E71: COS/GR | F71: VALOR | H71: INGREDIENTES | I71: CANTIDAD | J71: UND MEDIDA | K71: COS/GR | L71: VALOR | N71: INGREDIENTES | O71: CANTIDAD | P71: UND MEDIDA | Q71: COS/GR | R71: VALOR
B72: Bondiola | C72: 1300 | D72: gr | E72: 22.8 | F72: =C72*E72 -> 29640 | H72: aceite soya | I72: 50 | J72: gr | K72: 8.27 | L72: =I72*K72 -> 413.5 | N72: LECHE DE COCO | O72: 180 | P72: gr | Q72: 37.48 | R72: =O72*Q72 -> 6746.4
B73: Viche | C73: 10 | D73: gr | E73: 93.3 | F73: =C73*E73 -> 933 | H73: sal | I73: 10 | J73: gr | K73: 2.4 | L73: =I73*K73 -> 24 | N73: ESENCIA DE COCO | O73: 20 | P73: gr | Q73: 31.4 | R73: =O73*Q73 -> 628
B74: Comino | C74: 5 | D74: gr | E74: 24 | F74: =C74*E74 -> 120 | H74: levadura seca | I74: 14 | J74: gr | K74: 23.8 | L74: =I74*K74 -> 333.2 | N74: CREMA DE LECHE | O74: 100 | P74: gr | Q74: 21.1 | R74: =O74*Q74 -> 2110
B75: Paprika | C75: 10 | D75: gr | E75: 48 | F75: =C75*E75 -> 480 | H75: azucar corriente | I75: 30 | J75: gr | K75: 4.4 | L75: =I75*K75 -> 132 | N75: GOMA (AGUA CON AZUCAR) | O75: 50 | P75: gr | Q75: 4.4 | R75: =O75*Q75 -> 220
B76: Panela granulada | C76: 80 | D76: gr | E76: 7.98 | F76: =C76*E76 -> 638.4 | H76: fecula | I76: 30 | J76: gr | K76: 5.04 | L76: =I76*K76 -> 151.2 | R76: =O76*Q76 -> 0
B77: Pimienta negra | C77: 5 | D77: gr | E77: 52 | F77: =C77*E77 -> 260 | H77: harina de trigo | I77: 400 | J77: gr | K77: 3.61 | L77: =I77*K77 -> 1444 | R77: =O77*Q77 -> 0
B78: Sal refinada | C78: 40 | D78: gr | E78: 2.4 | F78: =C78*E78 -> 96 | J78: gr | L78: =I78*K78 -> 0 | R78: =O78*Q78 -> 0
B79: Azucar | C79: 200 | D79: gr | E79: 4.4 | F79: =C79*E79 -> 880 | L79: =I79*K79 -> 0 | R79: =O79*Q79 -> 0
F80: =C80*E80 -> 0 | L80: =I80*K80 -> 0 | R80: =O80*Q80 -> 0
B81: MATERIAL DE EMPAQUE | H81: MATERIAL DE EMPAQUE | N81: MATERIAL DE EMPAQUE
F82: =C82*140 -> 0 | L82: =I82*140 -> 0 | R82: =O82*140 -> 0
F83: =C83*140 -> 0 | L83: =I83*140 -> 0 | R83: =O83*140 -> 0
F84: =C84*140 -> 0 | L84: =I84*140 -> 0 | R84: =O84*140 -> 0
B85: COSTO + PRECIO DE VENTA | H85: COSTO + PRECIO DE VENTA | N85: COSTO + PRECIO DE VENTA
B86: COSTO DE INGREDIENTES | F86: =(F72+F73+F74+F75+F76+F77+F78+F79+F80+F84) -> 33047.4 | H86: COSTO DE INGREDIENTES | L86: =(L72+L73+L74+L75+L76+L77+L78+L79+L80+L84) -> 2497.9 | N86: COSTO DE INGREDIENTES | R86: =(R72+R73+R74+R75+R76+R77+R78+R79+R80+R84) -> 9704.4
B87: MARGEN DE ERROR O VARIACION 10% | F87: =F86*0.1 -> 3304.74 | H87: MARGEN DE ERROR O VARIACION 10% | L87: =L86*0.1 -> 249.79 | N87: MARGEN DE ERROR O VARIACION 10% | R87: =R86*0.1 -> 970.44
B88: COSTO TOTAL DE LA PREPARACION | F88: =SUM(F86:F87) -> 36352.14 | H88: COSTO TOTAL DE LA PREPARACION | L88: =SUM(L86:L87) -> 2747.69 | N88: COSTO TOTAL DE LA PREPARACION | R88: =SUM(R86:R87) -> 10674.84
B89: PRECIO DE VENTA | F89: 0 | H89: PRECIO DE VENTA | L89: 0 | N89: PRECIO DE VENTA | R89: 0
E90: 1450 | F90: =F88/E90 -> 25.070441 | I90: 30 und | J90: 17.8 | K90: 534 | L90: =L88/K90 -> 5.1454869 | Q90: 350 | R90: =R88/Q90 -> 30.499543
B92: DIP DE TOCINETA | H92: CEBOLLA CARMELIZADA DE UCHUVA | N92: SALSA AGRIDULCE
B93: INGREDIENTES | C93: CANTIDAD | D93: UND MEDIDA | E93: COS/GR | F93: VALOR | H93: INGREDIENTES | I93: CANTIDAD | J93: UND MEDIDA | K93: COS/GR | L93: VALOR | N93: INGREDIENTES | O93: CANTIDAD | P93: UND MEDIDA | Q93: COS/GR | R93: VALOR
B94: tocineta | C94: 4000 | D94: gr | E94: 26.9 | F94: =C94*E94 -> 107600 | H94: cebolla cabezona blanca | I94: 4000 | J94: gr | K94: 3.8 | L94: =I94*K94 -> 15200 | N94: Panela | P94: gr | R94: =O94*Q94 -> 0
B95: cebolla blanca | C95: 200 | D95: gr | E95: 3.8 | F95: =C95*E95 -> 760 | H95: uchuva | I95: 250 | J95: gr | K95: 14.76 | L95: =I95*K95 -> 3690 | N95: Piña | P95: gr | R95: =O95*Q95 -> 0
B96: cebolla morada | C96: 200 | D96: gr | E96: 4.58 | F96: =C96*E96 -> 916 | H96: canela | I96: 15 | J96: gr | K96: 89 | L96: =I96*K96 -> 1335 | N96: Azucar Morena | P96: gr | R96: =O96*Q96 -> 0
B97: sal | C97: 20 | D97: gr | E97: 2.4 | F97: =C97*E97 -> 48 | H97: limon | I97: 10 | J97: gr | K97: 2 | L97: =I97*K97 -> 20 | N97: Pasta de tomate | P97: gr | R97: =O97*Q97 -> 0
B98: pimienta | C98: 10 | D98: gr | E98: 52 | F98: =C98*E98 -> 520 | I98: =SUM(I94:I97) -> 4275 | L98: =I98*K98 -> 0 | N98: Soya | P98: gr | R98: =O98*Q98 -> 0
B99: pasta de ajo | C99: 50 | D99: gr | E99: 15 | F99: =C99*E99 -> 750 | L99: =I99*K99 -> 0 | N99: Anis estrellado | P99: gr | R99: =O99*Q99 -> 0
B100: azucar morena | C100: 250 | D100: gr | E100: 4.4 | F100: =C100*E100 -> 1100 | L100: =I100*K100 -> 0 | N100: Vinagre de manzana | P100: gr | R100: =O100*Q100 -> 0
B101: salsa de soya | C101: 180 | D101: gr | E101: 10.92 | F101: =C101*E101 -> 1965.6 | L101: =I101*K101 -> 0 | N101: Naranja | P101: gr | R101: =O101*Q101 -> 0
B102: miel | C102: 160 | D102: gr | E102: 13 | F102: =C102*E102 -> 2080 | N102: Poleo | P102: gr | R102: =O102*Q102 -> 0
B103: vinagre blanco | C103: 40 | D103: gr | E103: 7.6 | F103: =C103*E103 -> 304
C104: =SUM(C94:C103) -> 5110 | D104: gr | F104: =C104*E104 -> 0 | L104: =I104*K104 -> 0 | N104: Tomillo | P104: gr | R104: =O104*Q104 -> 0
B105: MATERIAL DE EMPAQUE | H105: MATERIAL DE EMPAQUE | N105: MATERIAL DE EMPAQUE
...

Sheet ENTRADAS (2)
B2: ABORRAJADOS | H2: CHORIZO PARRILLERO | N2: ENSALADA FRESCA | T2: SALPICON DE PULPO Y CHICHARON
B3: INGREDIENTES | C3: CANTIDAD | D3: UND MEDIDA | E3: COS/GR | F3: VALOR | H3: INGREDIENTES | I3: CANTIDAD | J3: UND MEDIDA | K3: COS/GR | L3: VALOR | N3: INGREDIENTES | O3: CANTIDAD | P3: UND MEDIDA | Q3: COS/GR | R3: VALOR | T3: INGREDIENTES | U3: CANTIDAD | V3: UND MEDIDA | W3: COS/GR | X3: VALOR
B4: Aborajados | C4: 3 | D4: Und | E4: 2000 | F4: =C4*E4 -> 6000 | H4: chorizo de cerdo | I4: 2 | J4: gr | K4: 2680 | L4: =I4*K4 -> 5360 | N4: lechuga | O4: 30 | P4: gr | Q4: 17.18 | R4: =O4*Q4 -> 515.4 | T4: Pulpo Cocido | U4: 50 | V4: gr | W4: 59.3 | X4: =U4*W4 -> 2965
D5: gr | F5: =C5*E5 -> 0 | H5: papas | I5: 150 | J5: gr | K5: 5.83 | L5: =I5*K5 -> 874.5 | N5: tomate cherry | O5: 25 | P5: gr | Q5: 19.6 | R5: =O5*Q5 -> 490 | T5: Chicharrón Oreado | U5: 50 | V5: gr | W5: 26.9 | X5: =U5*W5 -> 1345
D6: gr | F6: =C6*E6 -> 0 | H6: chimichurri | I6: 60 | J6: gr | K6: 24.03 | L6: =I6*K6 -> 1441.8 | N6: uchuva | O6: 25 | P6: gr | Q6: 11.4 | R6: =O6*Q6 -> 285 | T6: Cebollitas encurtidas | U6: 30 | V6: gr | W6: 6.1 | X6: =U6*W6 -> 183
D7: gr | F7: =C7*E7 -> 0 | L7: =I7*K7 -> 0 | N7: cebolla | O7: 6 | P7: gr | Q7: 92.58 | R7: =O7*Q7 -> 555.48 | T7: Tomate Cherry | U7: 25 | V7: gr | W7: 20 | X7: =U7*W7 -> 500
F8: =C8*E8 -> 0 | L8: =I8*K8 -> 0 | N8: chuney piña | O8: 15 | Q8: 23.81 | R8: =O8*Q8 -> 357.15 | T8: Suero costeño | U8: 10 | V8: gr | W8: 19.3 | X8: =U8*W8 -> 193
F9: =C9*E9 -> 0 | L9: =I9*K9 -> 0 | R9: =O9*Q9 -> 0 | V9: gr | X9: =U9*W9 -> 0
F10: =C10*E10 -> 0 | L10: =I10*K10 -> 0 | R10: =O10*Q10 -> 0 | X10: =U10*W10 -> 0
F11: =C11*E11 -> 0 | L11: =I11*K11 -> 0 | R11: =O11*Q11 -> 0 | X11: =U11*W11 -> 0
F12: =C12*E12 -> 0 | L12: =I12*K12 -> 0 | R12: =O12*Q12 -> 0 | X12: =U12*W12 -> 0
B13: MATERIAL DE EMPAQUE | H13: MATERIAL DE EMPAQUE | N13: MATERIAL DE EMPAQUE | T13: MATERIAL DE EMPAQUE
F14: =C14*140 -> 0 | L14: =I14*140 -> 0 | R14: =O14*140 -> 0 | X14: =U14*140 -> 0
F15: =C15*140 -> 0 | L15: =I15*140 -> 0 | R15: =O15*140 -> 0 | X15: =U15*140 -> 0
F16: =C16*140 -> 0 | L16: =I16*140 -> 0 | R16: =O16*140 -> 0 | X16: =U16*140 -> 0
B17: COSTO + PRECIO DE VENTA | H17: COSTO + PRECIO DE VENTA | N17: COSTO + PRECIO DE VENTA | T17: COSTO + PRECIO DE VENTA
B18: COSTO DE INGREDIENTES | F18: =(F4+F5+F6+F7+F8+F9+F10+F11+F12+F14+F15+F16) -> 6000 | H18: COSTO DE INGREDIENTES | L18: =(L4+L5+L6+L7+L8+L9+L10+L11+L12+L14+L15+L16) -> 7676.3 | N18: COSTO DE INGREDIENTES | R18: =(R4+R5+R6+R7+R8+R9+R10+R11+R12+R14+R15+R16) -> 2203.03 | T18: COSTO DE INGREDIENTES | X18: =(X4+X5+X6+X7+X8+X9+X10+X11+X12+X14+X15+X16) -> 5186
B19: MARGEN DE ERROR O VARIACION 10% | F19: =F18*0.1 -> 600 | H19: MARGEN DE ERROR O VARIACION 10% | L19: =L18*0.1 -> 767.63 | N19: MARGEN DE ERROR O VARIACION 10% | R19: =R18*0.1 -> 220.303 | T19: MARGEN DE ERROR O VARIACION 10% | X19: =X18*0.1 -> 518.6
B20: COSTO TOTAL DE LA PREPARACION | F20: =SUM(F18:F19) -> 6600 | H20: COSTO TOTAL DE LA PREPARACION | L20: =SUM(L18:L19) -> 8443.93 | N20: COSTO TOTAL DE LA PREPARACION | R20: =SUM(R18:R19) -> 2423.333 | T20: COSTO TOTAL DE LA PREPARACION | X20: =SUM(X18:X19) -> 5704.6
B21: PRECIO DE VENTA | F21: 25000 | H21: PRECIO DE VENTA | L21: 25000 | N21: PRECIO DE VENTA | R21: 6500 | T21: PRECIO DE VENTA | X21: 37000
B24: CARPACCIO DE BONDIOLA ACARAMELADA | H24: MINI BAOS RELLENOS
B25: INGREDIENTES | C25: CANTIDAD | D25: UND MEDIDA | E25: COS/GR | F25: VALOR | H25: INGREDIENTES | I25: CANTIDAD | J25: UND MEDIDA | K25: COS/GR | L25: VALOR | N25: INGREDIENTES | O25: CANTIDAD | P25: UND MEDIDA | Q25: COS/GR | R25: VALOR | T25: INGREDIENTES | U25: CANTIDAD | V25: UND MEDIDA | W25: COS/GR | X25: VALOR
B26: Bondiola acarmelada | C26: 80 | D26: gr | E26: 25.1 | F26: =C26*E26 -> 2008 | H26: Mini baos | I26: 3 | J26: gr | K26: 17.8 | L26: =I26*K26 -> 53.4 | P26: gr | R26: =O26*Q26 -> 0 | V26: gr | X26: =U26*W26 -> 0
B27: Rugula | C27: 20 | D27: gr | E27: 33.2 | F27: =C27*E27 -> 664 | H27: Jamón de Bondiola Acaramelada | I27: 100 | J27: gr | K27: 25.1 | L27: =I27*K27 -> 2510 | P27: gr | R27: =O27*Q27 -> 0 | V27: gr | X27: =U27*W27 -> 0
B28: Cebolla encurtida | C28: 15 | D28: gr | F28: =C28*E28 -> 0 | H28: Salsa agridulce | I28: 50 | J28: gr | L28: =I28*K28 -> 0 | P28: gr | R28: =O28*Q28 -> 0 | V28: gr | X28: =U28*W28 -> 0
B29: Miel de caña | C29: 15 | D29: gr | F29: =C29*E29 -> 0 | H29: Lechuga | I29: 10 | J29: gr | K29: 9.4 | L29: =I29*K29 -> 94 | P29: gr | R29: =O29*Q29 -> 0 | V29: gr | X29: =U29*W29 -> 0
B30: Aceite de oliva | C30: 10 | D30: gr | F30: =C30*E30 -> 0 | H30: Alioli de cilantro | I30: 10 | J30: gr | K30: 10.8 | L30: =I30*K30 -> 108 | R30: =O30*Q30 -> 0 | X30: =U30*W30 -> 0
F31: =C31*E31 -> 0 | L31: =I31*K31 -> 0 | R31: =O31*Q31 -> 0 | X31: =U31*W31 -> 0
F32: =C32*E32 -> 0 | L32: =I32*K32 -> 0 | R32: =O32*Q32 -> 0 | X32: =U32*W32 -> 0
F33: =C33*E33 -> 0 | L33: =I33*K33 -> 0 | R33: =O33*Q33 -> 0 | X33: =U33*W33 -> 0
F34: =C34*E34 -> 0 | L34: =I34*K34 -> 0 | R34: =O34*Q34 -> 0 | X34: =U34*W34 -> 0
B35: MATERIAL DE EMPAQUE | H35: MATERIAL DE EMPAQUE | N35: MATERIAL DE EMPAQUE | T35: MATERIAL DE EMPAQUE
F36: =C36*140 -> 0 | L36: =I36*140 -> 0 | R36: =O36*140 -> 0 | X36: =U36*W36 -> 0
F37: =C37*140 -> 0 | L37: =I37*140 -> 0 | R37: =O37*140 -> 0 | X37: =U37*140 -> 0
F38: =C38*140 -> 0 | L38: =I38*140 -> 0 | R38: =O38*140 -> 0 | X38: =U38*140 -> 0
B39: COSTO + PRECIO DE VENTA | H39: COSTO + PRECIO DE VENTA | N39: COSTO + PRECIO DE VENTA | T39: COSTO + PRECIO DE VENTA
B40: COSTO DE INGREDIENTES | F40: =(F26+F27+F28+F29+F30+F31+F32+F33+F34+F36+F37+F38) -> 2672 | H40: COSTO DE INGREDIENTES | L40: =(L26+L27+L28+L29+L30+L31+L32+L33+L34+L36+L37+L38) -> 2765.4 | N40: COSTO DE INGREDIENTES | R40: =(R26+R27+R28+R29+R30+R31+R32+R33+R34+R36+R37+R38) -> 0 | T40: COSTO DE INGREDIENTES | X40: =(X26+X27+X28+X29+X30+X31+X32+X33+X34+X36+X37+X38) -> 0
B41: MARGEN DE ERROR O VARIACION 10% | F41: =F40*0.1 -> 267.2 | H41: MARGEN DE ERROR O VARIACION 10% | L41: =L40*0.1 -> 276.54 | N41: MARGEN DE ERROR O VARIACION 10% | R41: =R40*0.1 -> 0 | T41: MARGEN DE ERROR O VARIACION 10% | X41: =X40*0.1 -> 0
B42: COSTO TOTAL DE LA PREPARACION | F42: =SUM(F40:F41) -> 2939.2 | H42: COSTO TOTAL DE LA PREPARACION | L42: =SUM(L40:L41) -> 3041.94 | N42: COSTO TOTAL DE LA PREPARACION | R42: =SUM(R40:R41) -> 0 | T42: COSTO TOTAL DE LA PREPARACION | X42: =SUM(X40:X41) -> 0
B43: PRECIO DE VENTA | F43: 30000 | H43: PRECIO DE VENTA | L43: 13900 | N43: PRECIO DE VENTA | R43: 13900 | T43: PRECIO DE VENTA | X43: 13900

Sheet ENTRADAS
A4: RECETA ESTANDAR
A7: PREPARACION | B7: CHORIZO PARRILLERO
F10: FECHA:
A11: INGREDIENTES | D11: CANT. | E11: UNID. | F11: VALORES
F12: UNITARIO | G12: TOTAL | H12: TOTAL GRAMAJE | I12: COSTO POR INGREDIENTE | J12: TOTAL PARA EL SERVICIO
A13: chorizo de cerdo | D13: 2 | E13: gr | F13: 2680 | G13: =F13*D13 -> 5360 | H13: =D13*L13 -> 2 | I13: =F13*H13 -> 5360 | J13: COMENSALES | L13: 1
A14: papas | D14: 150 | E14: gr | F14: 5.83 | G14: =D14*F14 -> 874.5 | H14: =D14*L13 -> 150 | I14: =F14*H14 -> 874.5 | J14: MATERIAS PRIMAS | L14: =SUM(I13:I16) -> 7676.3
A15: chimichurri | D15: 60 | E15: gr | F15: 24.03 | G15: =D15*F15 -> 1441.8 | H15: =D15*L13 -> 60 | I15: =F15*H15 -> 1441.8 | J15: COSTO TOTAL | L15: =G23*L13 -> 23000
A16: Enmpaques | G16: 2700 | H16: =D16*L13 -> 0 | I16: =F16*H16 -> 0
A17: COSTO TOTAL DE LOS INGREDIENTES | G17: =SUM(G13:G15) -> 7676.3
A18: MARGEN DE ERROR O VARIACION 10% | G18: =G17*0.1 -> 767.63
A19: COSTO TOTAL DE LA PREPARACION | G19: =SUM(G17:G18) -> 8443.93
A20: EMPAQUES | G20: =G16 -> 2700
A21: COSTO PORCION | F21: 1 | G21: =G20+G19 -> 11143.93
A22: % COSTO MATERIA PRIMA ESTABLECIDA POR EL CENTRO | G22: =G21/G23 -> 0.4845187
A23: PRECIO POTENCIAL DE VENTA | G23: 23000
A24: impuesto al consumo 8% | G24: 2000
A25: PRECIO DE VENTA | G25: =G24+G23 -> 25000
A26: PRECIO REAL DE VENTA | G26: =G25 -> 25000
A27: % REAL DEL COSTO | G27: =(G21+G24)/G26 -> 0.5257572
A29: RECETA ESTANDAR
A32: PREPARACION | B32: PAPAS AL HORNO
F35: FECHA:
A36: INGREDIENTES | D36: CANT. | E36: UNID. | F36: VALORES
F37: UNITARIO | G37: TOTAL | H37: TOTAL GRAMAJE | I37: COSTO POR INGREDIENTE | J37: TOTAL PARA EL SERVICIO
A38: papas casco (maccain) | D38: 200 | E38: gr | F38: 20.6 | G38: =F38*D38 -> 4120 | H38: =D38*L38 -> 200 | I38: =F38*H38 -> 4120 | J38: COMENSALES | L38: 1
A39: sal | D39: 2 | E39: gr | F39: 2.6 | G39: =D39*F39 -> 5.2 | H39: =D39*L38 -> 2 | I39: =F39*H39 -> 5.2 | J39: MATERIAS PRIMAS | L39: =SUM(I38:I42) -> 4220.87
A40: pimienta | D40: 1 | E40: gr | F40: 58.17 | G40: =D40*F40 -> 58.17 | H40: =D40*L38 -> 1 | I40: =F40*H40 -> 58.17 | J40: COSTO TOTAL | L40: =G48*L38 -> 12000
A41: romero | D41: 2.5 | E41: gr | F41: 15 | G41: =D41*F41 -> 37.5 | H41: =D41*L38 -> 2.5 | I41: =F41*H41 -> 37.5
G42: =D42*F42 -> 0 | H42: =D42*L38 -> 0 | I42: =F42*H42 -> 0
A43: COSTO TOTAL DE LOS INGREDIENTES | G43: =SUM(G38:G42) -> 4220.87
A44: MARGEN DE ERROR O VARIACION 10% | G44: =G43*0.1 -> 422.087
A45: COSTO TOTAL DE LA PREPARACION | G45: =SUM(G43:G44) -> 4642.957
A46: COSTO PORCION | F46: 1 | G46: =G45/F46 -> 4642.957
A47: % COSTO MATERIA PRIMA ESTABLECIDA POR EL CENTRO | G47: =G46/G48 -> 0.38691308
A48: PRECIO POTENCIAL DE VENTA | G48: 12000
A49: impuesto al consumo 8% | G49: =G48*0.08 -> 960
A50: PRECIO DE VENTA | G50: =G49+G48 -> 12960
A51: PRECIO REAL DE VENTA | G51: =G50 -> 12960
A52: % REAL DEL COSTO | G52: =(G46+G49)/G51 -> 0.43232693
A54: RECETA ESTANDAR
A57: PREPARACION | B57: ENSALDA FRESCA
F60: FECHA:
A61: INGREDIENTES | D61: CANT. | E61: UNID. | F61: VALORES
F62: UNITARIO | G62: TOTAL | H62: TOTAL GRAMAJE | I62: COSTO POR INGREDIENTE | J62: TOTAL PARA EL SERVICIO
A63: lechuga | D63: 30 | E63: gr | F63: 17.18 | G63: =D63*F63 -> 515.4 | H63: =D63*L63 -> 30 | I63: =F63*H63 -> 515.4 | J63: COMENSALES | L63: 1
A64: tomate cherry | D64: 25 | E64: gr | F64: 14.3 | G64: =D64*F64 -> 357.5 | H64: =D64*L63 -> 25 | I64: =F64*H64 -> 357.5 | J64: MATERIAS PRIMAS | L64: =SUM(I63:I68) -> 2070.53
A65: uchuva | D65: 25 | E65: gr | F65: 11.4 | G65: =D65*F65 -> 285 | H65: =D65*L63 -> 25 | I65: =F65*H65 -> 285 | J65: COSTO TOTAL | L65: =G74*L63 -> 6000
A66: cebolla | D66: 6 | E66: gr | F66: 92.58 | G66: =D66*F66 -> 555.48 | H66: =D66*L63 -> 6 | I66: =F66*H66 -> 555.48
A67: chuney piña | D67: 15 | E67: gr | F67: 23.81 | G67: =D67*F67 -> 357.15 | H67: =D67*L63 -> 15 | I67: =F67*H67 -> 357.15
G68: =D68*F68 -> 0 | H68: =D68*L63 -> 0 | I68: =F68*H68 -> 0
A69: COSTO TOTAL DE LOS INGREDIENTES | G69: =SUM(G63:G68) -> 2070.53
A70: MARGEN DE ERROR O VARIACION 10% | G70: =G69*0.1 -> 207.053
A71: COSTO TOTAL DE LA PREPARACION | G71: =SUM(G69:G70) -> 2277.583
A72: COSTO PORCION | F72: 1 | G72: =G71/F72 -> 2277.583
A73: % COSTO MATERIA PRIMA ESTABLECIDA POR EL CENTRO | G73: =G72/G74 -> 0.37959717
A74: PRECIO POTENCIAL DE VENTA | G74: 6000
A75: impuesto al consumo 8% | G75: =G74*0.08 -> 480
A76: PRECIO DE VENTA | G76: =G75+G74 -> 6480
A77: PRECIO REAL DE VENTA | G77: =G76 -> 6480
A78: % REAL DEL COSTO | G78: =(G72+G75)/G77 -> 0.42555293

Sheet POSTRES
B2: CARLOTTA DE LIMON | H2: FLAN | N2: PASTA AMATRICIANA
B3: INGREDIENTES | C3: CANTIDAD | D3: UND MEDIDA | E3: COS/GR | F3: VALOR | H3: INGREDIENTES | I3: CANTIDAD | J3: UND MEDIDA | K3: COS/GR | L3: VALOR | N3: INGREDIENTES | O3: CANTIDAD | P3: UND MEDIDA | Q3: COS/GR | R3: VALOR
B4: crema de leche | C4: 600 | D4: gr | E4: 21.1 | F4: =C4*E4 -> 12660 | H4: agua | I4: 30 | J4: ml | K4: 26.35 | L4: =I4*K4 -> 790.5 | N4: tomate | O4: 50 | P4: gr | Q4: 7.5 | R4: =O4*Q4 -> 375
B5: leche condensada | C5: 400 | D5: gr | E5: 13.5 | F5: =C5*E5 -> 5400 | H5: azucar | I5: 64 | J5: gr | K5: 4.9 | L5: =I5*K5 -> 313.6 | N5: napolitana | O5: 30 | P5: gr | Q5: 10.72 | R5: =O5*Q5 -> 321.6
B6: limon | C6: 490 | D6: gr | E6: 1.98 | F6: =C6*E6 -> 970.2 | H6: leche | I6: 770 | J6: gr | K6: 4.96 | L6: =I6*K6 -> 3819.2 | N6: cebolla roja | O6: 10 | P6: gr | Q6: 5.98 | R6: =O6*Q6 -> 59.8
B7: galletas sultana | C7: 200 | D7: gr | E7: 25.7 | F7: =C7*E7 -> 5140 | H7: leche condensada | I7: 440 | J7: gr | K7: 13.5 | L7: =I7*K7 -> 5940 | N7: tocineta | O7: 50 | P7: gr | Q7: 26.9 | R7: =O7*Q7 -> 1345
F8: =C8*E8 -> 0 | H8: crema de leche | I8: 240 | J8: gr | K8: 21.1 | L8: =I8*K8 -> 5064 | N8: peperoncino | O8: 1 | P8: gr | Q8: 2.55 | R8: =O8*Q8 -> 2.55
F9: =C9*E9 -> 0 | H9: huevos | I9: 4 | J9: und | K9: 600 | L9: =I9*K9 -> 2400 | N9: genovesa | O9: 2 | P9: gr | Q9: 55 | R9: =O9*Q9 -> 110
F10: =C10*E10 -> 0 | H10: esencia de vainilla | I10: 10 | J10: gr | K10: 31.4 | L10: =I10*K10 -> 314 | N10: Pasta Fetuccinni | O10: 120 | P10: gr | Q10: 15.98 | R10: =O10*Q10 -> 1917.6
F11: =C11*E11 -> 0 | L11: =I11*K11 -> 0 | R11: =O11*Q11 -> 0
F12: =C12*E12 -> 0 | L12: =I12*K12 -> 0 | R12: =O12*Q12 -> 0
B13: MATERIAL DE EMPAQUE | H13: MATERIAL DE EMPAQUE | N13: MATERIAL DE EMPAQUE
F14: =C14*140 -> 0 | L14: =I14*140 -> 0 | R14: =O14*140 -> 0
F15: =C15*140 -> 0 | L15: =I15*140 -> 0 | R15: =O15*140 -> 0
F16: =C16*140 -> 0 | L16: =I16*140 -> 0 | R16: =O16*140 -> 0
B17: COSTO + PRECIO DE VENTA | H17: COSTO + PRECIO DE VENTA | N17: COSTO + PRECIO DE VENTA
B18: COSTO DE INGREDIENTES | F18: =(F4+F5+F6+F7+F8+F9+F10+F11+F12+F14+F15+F16) -> 24170.2 | H18: COSTO DE INGREDIENTES | L18: =(L4+L5+L6+L7+L8+L9+L10+L11+L12+L14+L15+L16) -> 18641.3 | N18: COSTO DE INGREDIENTES | R18: =(R4+R5+R6+R7+R8+R9+R10+R11+R12+R14+R15+R16) -> 4131.55
B19: MARGEN DE ERROR O VARIACION 10% | F19: =F18*0.1 -> 2417.02 | H19: MARGEN DE ERROR O VARIACION 10% | L19: =L18*0.1 -> 1864.13 | N19: MARGEN DE ERROR O VARIACION 10% | R19: =R18*0.1 -> 413.155
B20: COSTO TOTAL DE LA PREPARACION | F20: =SUM(F18:F19) -> 26587.22 | H20: COSTO TOTAL DE LA PREPARACION | L20: =SUM(L18:L19) -> 20505.43 | N20: COSTO TOTAL DE LA PREPARACION | R20: =SUM(R18:R19) -> 4544.705
B21: PRECIO DE VENTA | F21: 15900 | H21: PRECIO DE VENTA | L21: 9900 | N21: PRECIO DE VENTA | R21: 30000
B22: PORCINES | E22: 6 | F22: =F20/E22 -> 4431.2033 | H22: PORCINES | K22: 8 | L22: =L20/K22 -> 2563.1788

Sheet PASTAS
B2: PASTA CARBONARA | H2: PASTA NAPOLITANA | N2: PASTA AMATRICIANA
B3: INGREDIENTES | C3: CANTIDAD | D3: UND MEDIDA | E3: COS/GR | F3: VALOR | H3: INGREDIENTES | I3: CANTIDAD | J3: UND MEDIDA | K3: COS/GR | L3: VALOR | N3: INGREDIENTES | O3: CANTIDAD | P3: UND MEDIDA | Q3: COS/GR | R3: VALOR
B4: tocineta | C4: 50 | D4: gr | E4: 26.9 | F4: =C4*E4 -> 1345 | H4: napolitana | I4: 100 | J4: gr | K4: 10.72 | L4: =I4*K4 -> 1072 | N4: tomate | O4: 50 | P4: gr | Q4: 7.5 | R4: =O4*Q4 -> 375
B5: parmesano | C5: 30 | D5: gr | E5: 13.15 | F5: =C5*E5 -> 394.5 | H5: parmesano | I5: 30 | J5: gr | K5: 13.15 | L5: =I5*K5 -> 394.5 | N5: napolitana | O5: 30 | P5: gr | Q5: 10.72 | R5: =O5*Q5 -> 321.6
B6: crema de leche | C6: 50 | D6: gr | E6: 19 | F6: =C6*E6 -> 950 | H6: genovesa | I6: 2 | J6: gr | K6: 55 | L6: =I6*K6 -> 110 | N6: cebolla roja | O6: 10 | P6: gr | Q6: 5.98 | R6: =O6*Q6 -> 59.8
B7: sal | C7: 2 | D7: gr | E7: 2.5 | F7: =C7*E7 -> 5 | H7: sal | I7: 2 | J7: gr | K7: 2.5 | L7: =I7*K7 -> 5 | N7: tocineta | O7: 50 | P7: gr | Q7: 26.9 | R7: =O7*Q7 -> 1345
B8: pimienta | C8: 1 | D8: gr | E8: 58.17 | F8: =C8*E8 -> 58.17 | H8: pimienta | I8: 1 | J8: gr | K8: 58.17 | L8: =I8*K8 -> 58.17 | N8: peperoncino | O8: 1 | P8: gr | Q8: 2.55 | R8: =O8*Q8 -> 2.55
B9: ajo | C9: 2 | D9: gr | E9: 11 | F9: =C9*E9 -> 22 | H9: Pasta Fetuccinni | I9: 120 | J9: gr | K9: 15.98 | L9: =I9*K9 -> 1917.6 | N9: genovesa | O9: 2 | P9: gr | Q9: 55 | R9: =O9*Q9 -> 110
B10: Pasta Fetuccinni | C10: 120 | D10: gr | E10: 15.98 | F10: =C10*E10 -> 1917.6 | L10: =I10*K10 -> 0 | N10: Pasta Fetuccinni | O10: 120 | P10: gr | Q10: 15.98 | R10: =O10*Q10 -> 1917.6
F11: =C11*E11 -> 0 | L11: =I11*K11 -> 0 | R11: =O11*Q11 -> 0
F12: =C12*E12 -> 0 | L12: =I12*K12 -> 0 | R12: =O12*Q12 -> 0
B13: MATERIAL DE EMPAQUE | H13: MATERIAL DE EMPAQUE | N13: MATERIAL DE EMPAQUE
F14: =C14*140 -> 0 | L14: =I14*140 -> 0 | R14: =O14*140 -> 0
F15: =C15*140 -> 0 | L15: =I15*140 -> 0 | R15: =O15*140 -> 0
F16: =C16*140 -> 0 | L16: =I16*140 -> 0 | R16: =O16*140 -> 0
B17: COSTO + PRECIO DE VENTA | H17: COSTO + PRECIO DE VENTA | N17: COSTO + PRECIO DE VENTA
B18: COSTO DE INGREDIENTES | F18: =(F4+F5+F6+F7+F8+F9+F10+F11+F12+F14+F15+F16) -> 4692.27 | H18: COSTO DE INGREDIENTES | L18: =(L4+L5+L6+L7+L8+L9+L10+L11+L12+L14+L15+L16) -> 3557.27 | N18: COSTO DE INGREDIENTES | R18: =(R4+R5+R6+R7+R8+R9+R10+R11+R12+R14+R15+R16) -> 4131.55
B19: MARGEN DE ERROR O VARIACION 10% | F19: =F18*0.1 -> 469.227 | H19: MARGEN DE ERROR O VARIACION 10% | L19: =L18*0.1 -> 355.727 | N19: MARGEN DE ERROR O VARIACION 10% | R19: =R18*0.1 -> 413.155
B20: COSTO TOTAL DE LA PREPARACION | F20: =SUM(F18:F19) -> 5161.497 | H20: COSTO TOTAL DE LA PREPARACION | L20: =SUM(L18:L19) -> 3912.997 | N20: COSTO TOTAL DE LA PREPARACION | R20: =SUM(R18:R19) -> 4544.705
B21: PRECIO DE VENTA | F21: 30000 | H21: PRECIO DE VENTA | L21: 28000 | N21: PRECIO DE VENTA | R21: 30000

Sheet SALSA Y PASTA 
A4: RECETA ESTANDAR
A7: PREPARACION | B7: CHIMICHURRI ARGENTINO
F10: FECHA:
A11: INGREDIENTES | D11: CANT. | E11: UNID. | F11: VALORES
F12: UNITARIO | G12: TOTAL | H12: TOTAL GRAMAJE | I12: COSTO POR INGREDIENTE | J12: TOTAL PARA EL SERVICIO
A13: perejil | D13: 300 | E13: gr | F13: 1.5 | G13: =F13*D13 -> 450 | H13: =D13*L13 -> 300 | I13: =F13*H13 -> 450 | J13: COMENSALES | L13: 1
A14: oregano fresco | D14: 30 | E14: gr | F14: 3 | G14: =D14*F14 -> 90 | H14: =D14*L13 -> 30 | I14: =F14*H14 -> 90 | J14: MATERIAS PRIMAS | L14: =SUM(I13:I22) -> 24520.11
A15: ajo | D15: 30 | E15: gr | F15: 11 | G15: =D15*F15 -> 330 | H15: =D15*L13 -> 30 | I15: =F15*H15 -> 330 | J15: COSTO TOTAL | L15: =G29*L13 -> 0
A16: cebolla larga | D16: 200 | E16: gr | F16: 5 | G16: =D16*F16 -> 1000 | H16: =D16*L13 -> 200 | I16: =F16*H16 -> 1000
A17: pimenton | D17: 10 | E17: gr | F17: 5 | G17: =D17*F17 -> 50 | H17: =D17*L13 -> 10 | I17: =F17*H17 -> 50
A18: vinagre | D18: 65 | E18: ml | F18: 2.85 | G18: =D18*F18 -> 185.25 | H18: =D18*L13 -> 65 | I18: =F18*H18 -> 185.25
A19: limon | D19: 65 | E19: ml | F19: 4.9 | G19: =D19*F19 -> 318.5 | H19: =D19*L13 -> 65 | I19: =F19*H19 -> 318.5
A20: aceite de oliva | D20: 300 | E20: ml | F20: 71.93 | G20: =D20*F20 -> 21579 | H20: =D20*L13 -> 300 | I20: =F20*H20 -> 21579
A21: sal | D21: 20 | E21: gr | F21: 2.6 | G21: =D21*F21 -> 52 | H21: =D21*L13 -> 20 | I21: =F21*H21 -> 52
A22: pimienta | D22: 8 | E22: gr | F22: 58.17 | G22: =D22*F22 -> 465.36 | H22: =D22*L13 -> 8 | I22: =F22*H22 -> 465.36
G23: =D23*F23 -> 0 | H23: =D23*L13 -> 0 | I23: =F23*H23 -> 0
A24: COSTO TOTAL DE LOS INGREDIENTES | G24: =SUM(G13:G23) -> 24520.11
A25: MARGEN DE ERROR O VARIACION 10% | G25: =G24*0.1 -> 2452.011
A26: COSTO TOTAL DE LA PREPARACION | G26: =SUM(G24:G25) -> 26972.121
A27: COSTO PORCION | F27: 17 | G27: =G26/F27 -> 1586.5954
A28: % COSTO MATERIA PRIMA ESTABLECIDA POR EL CENTRO | G28: =G27/G29 -> #DIV/0!
A29: PRECIO POTENCIAL DE VENTA
A30: impuesto al consumo 8% | G30: =G29*0.08 -> 0
A31: PRECIO DE VENTA | G31: =G30+G29 -> 0
A32: PRECIO REAL DE VENTA | G32: =G31 -> 0
A33: % REAL DEL COSTO | G33: =(G27+G30)/G32 -> #DIV/0!
A36: RECETA ESTANDAR
A39: PREPARACION | B39: SALSA MORNAY
F42: FECHA:
A43: INGREDIENTES | D43: CANT. | E43: UNID. | F43: VALORES
F44: UNITARIO | G44: TOTAL | H44: TOTAL GRAMAJE | I44: COSTO POR INGREDIENTE | J44: TOTAL PARA EL SERVICIO
A45: mantequilla | D45: 10 | E45: gr | F45: 26.10 | G45: 261 | H45: =D45*L45 -> 10 | I45: 261 | J45: COMENSALES | L45: 1
A46: harina | D46: 10 | E46: gr | F46: 2.91 | G46: $ 29.1 | H46: =D46*L45 -> 10 | I46: $ 29.1 | J46: MATERIAS PRIMAS | L46: =SUM(I45:I52) -> 2770.2
A47: leche | D47: 100 | E47: gr | F47: 3.73 | G47: 373 | H47: =D47*L45 -> 100 | I47: 373 | J47: COSTO TOTAL | L47: =G58*L45 -> 12000
A48: nuez moscada | D48: 0.12 | E48: gr | F48: 410 | G48: $ 49.2 | H48: =D48*L45 -> 0.12 | I48: =F48*H48 -> 49.2
A49: sal | D49: 1 | E49: gr | F49: 2.61 | G49: $ 2.61 | H49: =D49*L45 -> 1 | I49: $ 2.61
A50: pimienta | D50: 1 | E50: gr | F50: 58.41 | G50: $ 58.41 | H50: =D50*L45 -> 1 | I50: $ 58.41
A51: parmesano | D51: 25 | E51: gr | F51: 83.5 | G51: 2087 | H51: =D51*L45 -> 25 | I51: 2087
G52: =D52*F52 -> 0 | H52: =D52*L45 -> 0 | I52: =F52*H52 -> 0
A53: COSTO TOTAL DE LOS INGREDIENTES | G53: =SUM(G45:G52) -> 2721
A54: MARGEN DE ERROR O VARIACION 10% | G54: =G53*0.1 -> 272.1
A55: COSTO TOTAL DE LA PREPARACION | G55: =SUM(G53:G54) -> 2993.1
A56: COSTO PORCION | F56: 1 | G56: =G55/F56 -> 2993.1
A57: % COSTO MATERIA PRIMA ESTABLECIDA POR EL CENTRO | G57: =G56/G58 -> 0.249425
A58: PRECIO POTENCIAL DE VENTA | G58: 12000
A59: impuesto al consumo 8% | G59: =G58*0.08 -> 960
A60: PRECIO DE VENTA | G60: =G59+G58 -> 12960
A61: PRECIO REAL DE VENTA | G61: =G60 -> 12960
A62: % REAL DEL COSTO | G62: =(G56+G59)/G61 -> 0.30502315
A64: RECETA ESTANDAR
A67: PREPARACION | B67: SALSA MIGNON
F70: FECHA:
A71: INGREDIENTES | D71: CANT. | E71: UNID. | F71: VALORES
F72: UNITARIO | G72: TOTAL | H72: TOTAL GRAMAJE | I72: COSTO POR INGREDIENTE | J72: TOTAL PARA EL SERVICIO
A73: champiñon gourmet | D73: 40 | E73: gr | F73: 2.55 | G73: 102 | H73: =D73*L73 -> 40 | I73: 102 | J73: COMENSALES | L73: 1
A74: crema de leche | D74: 50 | E74: gr | F74: 23.54 | G74: 1177 | H74: =D74*L73 -> 50 | I74: 1177 | J74: MATERIAS PRIMAS | L74: =SUM(I73:I79) -> 4501.6
A75: vino tinto | D75: 50 | E75: gr | F75: 25.4 | G75: 1250 | H75: =D75*L73 -> 50 | I75: 1250 | J75: COSTO TOTAL | L75: =G85*L73 -> 12000
A76: sal | D76: 2 | E76: gr | F76: 2.61 | G76: $ 5.22 | H76: =D76*L73 -> 2 | I76: $ 5.22
A77: pimienta | D77: 1 | E77: gr | F77: 58.41 | G77: $ 58.41 | H77: =D77*L73 -> 1 | I77: $ 58.41
A78: ajo | D78: 5 | E78: gr | F78: 11.00 | G78: 55 | H78: =D78*L73 -> 5 | I78: 55
A79: Pasta Fetuccinni | D79: 120 | E79: gr | F79: 15.98 | G79: =D79*F79 -> 1917.6 | H79: =D79*L73 -> 120 | I79: =F79*H79 -> 1917.6
A80: COSTO TOTAL DE LOS INGREDIENTES | G80: =SUM(G73:G79) -> 4501.6
A81: MARGEN DE ERROR O VARIACION 10% | G81: =G80*0.1 -> 450.16
A82: COSTO TOTAL DE LA PREPARACION | G82: =SUM(G80:G81) -> 4951.76
A83: COSTO PORCION | F83: 1 | G83: =G82/F83 -> 4951.76 | K83: 7990 | L83: =K83/500 -> 15.98
A84: % COSTO MATERIA PRIMA ESTABLECIDA POR EL CENTRO | G84: =G83/G85 -> 0.41264667
A85: PRECIO POTENCIAL DE VENTA | G85: 12000
A86: impuesto al consumo 8% | G86: =G85*0.08 -> 960
A87: PRECIO DE VENTA | G87: =G86+G85 -> 12960
A88: PRECIO REAL DE VENTA | G88: =G87 -> 12960
A89: % REAL DEL COSTO | G89: =(G83+G86)/G88 -> 0.45615432
A91: RECETA ESTANDAR
A94: PREPARACION | B94: SALSA AMATRICIANA
F97: FECHA:
A98: INGREDIENTES | D98: CANT. | E98: UNID. | F98: VALORES
F99: UNITARIO | G99: TOTAL | H99: TOTAL GRAMAJE | I99: COSTO POR INGREDIENTE | J99: TOTAL PARA EL SERVICIO
A100: tomate | D100: 50 | E100: gr | F100: 7.5 | G100: =F100*D100 -> 375 | H100: =D100*L100 -> 50 | I100: =F100*H100 -> 375 | J100: COMENSALES | L100: 1
A101: napolitana | D101: 30 | E101: gr | F101: 10.78 | G101: =D101*F101 -> 323.4 | H101: =D101*L100 -> 30 | I101: =F101*H101 -> 323.4 | J101: MATERIAS PRIMAS | L101: =SUM(I100:I106) -> 4538.55
A102: cebolla roja | D102: 10 | E102: gr | F102: 5,98 | G102: 60 | H102: 10 | I102: 60 | J102: COSTO TOTAL | L102: =G112*L100 -> 28000
A103: tocineta | D103: 50 | E103: gr | F103: 35 | G103: =D103*F103 -> 1750 | H103: =D103*L100 -> 50 | I103: =F103*H103 -> 1750
A104: peperoncino | D104: 1 | E104: gr | F104: 2.55 | G104: =D104*F104 -> 2.55 | H104: =D104*L100 -> 1 | I104: =F104*H104 -> 2.55
A105: genovesa | D105: 2 | E105: gr | F105: 55 | G105: =D105*F105 -> 110 | H105: =D105*L100 -> 2 | I105: =F105*H105 -> 110
A106: Pasta Fetuccinni | D106: 120 | E106: gr | F106: 15.98 | G106: =D106*F106 -> 1917.6 | H106: =D106*L100 -> 120 | I106: =F106*H106 -> 1917.6
A107: COSTO TOTAL DE LOS INGREDIENTES | G107: =SUM(G100:G106) -> 4538.55
A108: MARGEN DE ERROR O VARIACION 10% | G108: =G107*0.1 -> 453.855
A109: COSTO TOTAL DE LA PREPARACION | G109: =SUM(G107:G108) -> 4992.405
A110: COSTO PORCION | F110: 1 | G110: =G109/F110 -> 4992.405
A111: % COSTO MATERIA PRIMA ESTABLECIDA POR EL CENTRO | G111: =G110/G112 -> 0.17830018
A112: PRECIO POTENCIAL DE VENTA | G112: 28000
A113: impuesto al consumo 8% | G113: =G112*0.08 -> 2240
A114: PRECIO DE VENTA | G114: =G113+G112 -> 30240
A115: PRECIO REAL DE VENTA | G115: =G114 -> 30240
A116: % REAL DEL COSTO | G116: =(G110+G113)/G115 -> 0.23916683
A118: RECETA ESTANDAR
A121: PREPARACION | B121: SALSA NAPOLITANA
F124: FECHA:
A125: INGREDIENTES | D125: CANT. | E125: UNID. | F125: VALORES
F126: UNITARIO | G126: TOTAL | H126: TOTAL GRAMAJE | I126: COSTO POR INGREDIENTE | J126: TOTAL PARA EL SERVICIO
A127: napolitana | D127: 100 | E127: gr | F127: 10.72 | G127: =D127*F127 -> 1072 | H127: =D127*L127 -> 100 | I127: =F127*H127 -> 1072 | J127: COMENSALES | L127: 1
A128: parmesano | D128: 30 | E128: gr | F128: 83.45 | G128: =D128*F128 -> 2503.5 | H128: =D128*L127 -> 30 | I128: =F128*H128 -> 2503.5 | J128: MATERIAS PRIMAS | L128: =SUM(I127:I132) -> 5666.47
...

Sheet Propuesta Alm
A2: ELIGE TU PLATO | B2: PRECIO DE VENTA | C2: COSTO | D2: ELIGE UN ACOMPAÑANTE | E2: ELIGE UNA CREMA | F2: ELIGE UNA BEBIDA ADICIONAL | G2: POSTRE
A3: BONDIOLA DE CERDO 150 GR | B3: 21900 | C3: 0.5 | D3: Arroz tradicional | E3: Verduras (Miercoles Jueves) | F3: Limonada $6000 | G3: BREBA AREQUIPE
A4: CUBITOS DE POLLO SALSA CILANTRO 150 GR | B4: 22900 | C4: 0.51 | D4: Maduro y papa cocido | E4: Maiz (Viernes Sabado) | F4: Gaseosa $5000 | G4: FLAN
A5: FILETE DE TILAPIA 150 gr | B5: 24900 | C5: 0.51 | D5: Papa Casco | E5: Champiñones (Domingos) | F5: Cerveza ncional $7500
A6: CADERITA SALSA DE CHAMPIÑON 150 GR | B6: 25900 | C6: 0.52 | D6: Pasta napolitana | F6: Botella de Agua $4500
A7: MILANESA DE CERDO 150 Gr | B7: 25900 | C7: 0.52
B8: Todos nuestros platos van con ensalsda de la casa y un vaso de jugo de 9 0nz | G8: Aguapanela con limon
A11: Miercolea 18 de junio
A12: Fudis 4 a 6
A13: Volantes
A14: 1 semana de volanteo
A16: ELIGE TU PLATO | B16: PRECIO DE VENTA | C16: COSTO | D16: ELIGE UN ACOMPAÑANTE | E16: CREMA | F16: TOTAL
A17: BONDIOLA DE CERDO 150 GR | B17: 21900 | C17: 0.5 | D17: Arroz tradicional | E17: Verduras
A18: CUBITOS DE POLLO SALSA CILANTRO 150 GR | B18: 22900 | C18: 0.51 | D18: Maduro y papa cocido | E18: Verduras
A19: FILETE DE TILAPIA 150 gr | B19: 24900 | C19: 0.51 | E19: Verduras
A20: CADERITA SALSA DE CHAMPIÑON 150 GR | B20: 25900 | C20: 0.52 | E20: Verduras
A21: MILANESA DE CERDO 150 Gr | B21: 25900 | C21: 0.52 | E21: Verduras
B22: Todos nuestros platos van con ensalsda de la casa y un vaso de limonada de 9 0nz
A25: QPONERA
A26: PIZZA
A27: HAMBURGUESA
A28: ALMUERZOS
A30: DE LUNES A VIERNES
A31: DOS POR
A32: UNA PRECIO FULL
A33: UNA AL 50%
A34: QPON PARA 2 SOLO 1

Sheet HAMB 2 X1
A3: RECETA ESTANDAR
A6: PREPARACION | B6: HAMBURGUESA PROMOCION 2*1
F9: FECHA:
A10: INGREDIENTES | D10: CANT. | E10: UNID. | F10: VALORES
F11: UNITARIO | G11: TOTAL | H11: TOTAL GRAMAJE | I11: COSTO POR INGREDIENTE | J11: TOTAL PARA EL SERVICIO
A12: PAN DE HAMBURGUESA | D12: 1 | E12: und | F12: 780 | G12: =D12*F12 -> 780 | H12: =D12*L12 -> 1 | I12: =F12*H12 -> 780 | J12: COMENSALES | L12: 1
A13: CARNE NACIONAL | D13: 120 | E13: gr | F13: 20.5 | G13: =D13*F13 -> 2460 | H13: =D13*L12 -> 120 | I13: =F13*H13 -> 2460 | J13: MATERIAS PRIMAS | L13: =SUM(I12:I20) -> 6463.8
A14: QUESO | D14: 25 | E14: gr | F14: 19.2 | G14: =D14*F14 -> 480 | H14: =D14*L12 -> 25 | I14: =F14*H14 -> 480 | J14: COSTO TOTAL | L14: =G26*L12 -> 28000
A15: LECHUGA | D15: 15 | E15: gr | F15: 17 | G15: =D15*F15 -> 255 | H15: =D15*L12 -> 15 | I15: =F15*H15 -> 255
A16: TOMATE | D16: 20 | E16: gr | F16: 7.5 | G16: =D16*F16 -> 150 | H16: =D16*L12 -> 20 | I16: =F16*H16 -> 150
A17: CEBOLLA CARAMELIZADA | D17: 20 | E17: gr | F17: 3.9 | G17: =D17*F17 -> 78 | H17: =D17*L12 -> 20 | I17: =F17*H17 -> 78
A18: SALSA DE AJO | D18: 40 | E18: gr | F18: 28.26 | G18: =D18*F18 -> 1130.4 | H18: =D18*L12 -> 40 | I18: =F18*H18 -> 1130.4
A19: SALSA DE MIEL MOSTAZA | D19: 40 | E19: gr | F19: 28.26 | G19: =D19*F19 -> 1130.4 | H19: =D19*L12 -> 40 | I19: =F19*H19 -> 1130.4
G20: =D20*F20 -> 0 | H20: =D20*L12 -> 0 | I20: =F20*H20 -> 0
A21: COSTO TOTAL DE LOS INGREDIENTES | G21: =SUM(G12:G20) -> 6463.8
A22: MARGEN DE ERROR O VARIACION 10% | G22: =G21*0.1 -> 646.38
A23: COSTO TOTAL DE LA PREPARACION | G23: =SUM(G21:G22) -> 7110.18
A24: COSTO PORCION | F24: 1 | G24: =G23/F24 -> 7110.18 | H24: =G24*2 -> 14220.36 | I24: 30000 | J24: =H24/I24 -> 0.474012 | K24: =I24-H24 -> 15779.64
A25: % COSTO MATERIA PRIMA ESTABLECIDA POR EL CENTRO | G25: =G24/G26 -> 0.253935
A26: PRECIO POTENCIAL DE VENTA | G26: 28000
A27: impuesto al consumo 8% | G27: =G26*0.08 -> 2240
A28: PRECIO DE VENTA | G28: =G27+G26 -> 30240
A29: PRECIO REAL DE VENTA | G29: =G28 -> 30240
A30: % REAL DEL COSTO | G30: =(G24+G27)/G29 -> 0.30919907

Sheet CREMAS
A2: RECETA ESTANDAR
A5: PREPARACION | B5: crema de verduras
F8: FECHA:
A9: INGREDIENTES | D9: CANT. | E9: UNID. | F9: VALORES
F10: UNITARIO | G10: TOTAL | H10: TOTAL GRAMAJE | I10: COSTO POR INGREDIENTE | J10: TOTAL PARA EL SERVICIO
A11: zanahoria | D11: 200 | E11: gr | F11: 4.1 | G11: =D11*F11 -> 820 | H11: =D11*L11 -> 200 | I11: =F11*H11 -> 820 | J11: COMENSALES | L11: 1
A12: cebolla | D12: 250 | E12: gr | F12: 3.9 | G12: =D12*F12 -> 975 | H12: =D12*L11 -> 250 | I12: =F12*H12 -> 975 | J12: MATERIAS PRIMAS | L12: =SUM(I11:I20) -> 10114.6
A13: puerro | D13: 180 | E13: gr | F13: 7.46 | G13: =D13*F13 -> 1342.8 | H13: =D13*L11 -> 180 | I13: =F13*H13 -> 1342.8 | J13: COSTO TOTAL | L13: =G26*L11 -> 0
A14: apio | D14: 260 | E14: gr | F14: 2.68 | G14: =D14*F14 -> 696.8 | H14: =D14*L11 -> 260 | I14: =F14*H14 -> 696.8
A15: papa amarilla | D15: 500 | E15: gr | F15: 3.5 | G15: =D15*F15 -> 1750 | H15: =D15*L11 -> 500 | I15: =F15*H15 -> 1750
A16: zapallo | D16: 300 | E16: gr | F16: 3.1 | G16: =D16*F16 -> 930 | H16: =D16*L11 -> 300 | I16: =F16*H16 -> 930
A17: agua | D17: 1000 | E17: ml | F17: 3.6 | G17: =D17*F17 -> 3600 | H17: =D17*L11 -> 1000 | I17: =F17*H17 -> 3600
G18: =D18*F18 -> 0 | H18: =D18*L11 -> 0 | I18: =F18*H18 -> 0
G19: =D19*F19 -> 0 | H19: =D19*L11 -> 0 | I19: =F19*H19 -> 0
G20: =D20*F20 -> 0 | H20: =D20*L11 -> 0 | I20: =F20*H20 -> 0
A21: COSTO TOTAL DE LOS INGREDIENTES | G21: =SUM(G11:G20) -> 10114.6
A22: MARGEN DE ERROR O VARIACION 10% | G22: =G21*0.1 -> 1011.46
A23: COSTO TOTAL DE LA PREPARACION | G23: =SUM(G21:G22) -> 11126.06
A24: COSTO PORCION | F24: 15 | G24: =G23/F24 -> 741.73733
A25: % COSTO MATERIA PRIMA ESTABLECIDA POR EL CENTRO | G25: =G24/G26 -> #DIV/0!
A26: PRECIO POTENCIAL DE VENTA | G26: 0
A27: impuesto al consumo 8% | G27: =G26*0.08 -> 0
A28: PRECIO DE VENTA | G28: =G27+G26 -> 0
A29: PRECIO REAL DE VENTA | G29: =G28 -> 0
A30: % REAL DEL COSTO | G30: =(G24+G27)/G29 -> #DIV/0!
A32: RECETA ESTANDAR
A34: PREPARACION | B34: CREMA DE MAIZ
F37: FECHA:
A38: INGREDIENTES | D38: CANT. | E38: UNID. | F38: VALORES
F39: UNITARIO | G39: TOTAL | H39: TOTAL GRAMAJE | I39: COSTO POR INGREDIENTE | J39: TOTAL PARA EL SERVICIO
A40: maiz trillado | D40: 1000 | E40: gr | F40: 2 | G40: =D40*F40 -> 2000 | H40: =D40*L40 -> 1000 | I40: =F40*H40 -> 2000 | J40: COMENSALES | L40: 1
A41: crema de leche | D41: 400 | E41: gr | F41: 23.74 | G41: =D41*F41 -> 9496 | H41: =D41*L40 -> 400 | I41: =F41*H41 -> 9496 | J41: MATERIAS PRIMAS | L41: =SUM(I40:I48) -> 16162
A42: sal | D42: 10 | E42: gr | F42: 2.6 | G42: =D42*F42 -> 26 | H42: =D42*L40 -> 10 | I42: =F42*H42 -> 26 | J42: COSTO TOTAL | L42: =G54*L40 -> 0
A43: ajo | D43: 20 | E43: gr | F43: 11 | G43: =D43*F43 -> 220 | H43: =D43*L40 -> 20 | I43: =F43*H43 -> 220
A44: leche | D44: 400 | E44: gr | F44: 5.65 | G44: =D44*F44 -> 2260 | H44: =D44*L40 -> 400 | I44: =F44*H44 -> 2260
A45: agua | D45: 600 | E45: ml | F45: 3.6 | G45: =D45*F45 -> 2160 | H45: =D45*L40 -> 600 | I45: =F45*H45 -> 2160
G46: =D46*F46 -> 0 | H46: =D46*L40 -> 0 | I46: =F46*H46 -> 0
G47: =D47*F47 -> 0 | H47: =D47*L40 -> 0 | I47: =F47*H47 -> 0
G48: =D48*F48 -> 0 | H48: =D48*L40 -> 0 | I48: =F48*H48 -> 0
A49: COSTO TOTAL DE LOS INGREDIENTES | G49: =SUM(G40:G48) -> 16162
A50: MARGEN DE ERROR O VARIACION 10% | G50: =G49*0.1 -> 1616.2
A51: COSTO TOTAL DE LA PREPARACION | G51: =SUM(G49:G50) -> 17778.2
A52: COSTO PORCION | F52: 15 | G52: =G51/F52 -> 1185.2133
A53: % COSTO MATERIA PRIMA ESTABLECIDA POR EL CENTRO | G53: =G52/G54 -> #DIV/0!
A54: PRECIO POTENCIAL DE VENTA | G54: 0
A55: impuesto al consumo 8% | G55: =G54*0.08 -> 0
A56: PRECIO DE VENTA | G56: =G55+G54 -> 0
A57: PRECIO REAL DE VENTA | G57: =G56 -> 0
A58: % REAL DEL COSTO | G58: =(G52+G55)/G57 -> #DIV/0!
A61: RECETA ESTANDAR
A63: PREPARACION | B63: crema de champiñones
F66: FECHA:
A67: INGREDIENTES | D67: CANT. | E67: UNID. | F67: VALORES
F68: UNITARIO | G68: TOTAL | H68: TOTAL GRAMAJE | I68: COSTO POR INGREDIENTE | J68: TOTAL PARA EL SERVICIO
A69: champiñones | D69: 500 | E69: gr | F69: 31.1 | G69: =D69*F69 -> 15550 | H69: =D69*L69 -> 500 | I69: =F69*H69 -> 15550 | J69: COMENSALES | L69: 1
A70: agua | D70: 1000 | E70: gr | F70: 3.6 | G70: =D70*F70 -> 3600 | H70: =D70*L69 -> 1000 | I70: =F70*H70 -> 3600 | J70: MATERIAS PRIMAS | L70: =SUM(I69:I76) -> 31116
A71: leche | D71: 400 | E71: gr | F71: 5.65 | G71: =D71*F71 -> 2260 | H71: =D71*L69 -> 400 | I71: =F71*H71 -> 2260 | J71: COSTO TOTAL | L71: =G82*L69 -> 0
A72: crema de leche | D72: 400 | E72: gr | F72: 23.74 | G72: 0 | H72: =D72*L69 -> 400 | I72: =F72*H72 -> 9496
A73: papas fosforos | D73: 60 | E73: gr | F73: 3.5 | G73: =D73*F73 -> 210 | H73: =D73*L69 -> 60 | I73: =F73*H73 -> 210
G74: =D74*F74 -> 0 | H74: =D74*L69 -> 0 | I74: =F74*H74 -> 0
G75: =D75*F75 -> 0 | H75: =D75*L69 -> 0 | I75: =F75*H75 -> 0
G76: =D76*F76 -> 0 | H76: =D76*L69 -> 0 | I76: =F76*H76 -> 0
A77: COSTO TOTAL DE LOS INGREDIENTES | G77: =SUM(G69:G76) -> 21620
A78: MARGEN DE ERROR O VARIACION 10% | G78: =G77*0.1 -> 2162
A79: COSTO TOTAL DE LA PREPARACION | G79: =SUM(G77:G78) -> 23782
A80: COSTO PORCION | F80: 15 | G80: =G79/F80 -> 1585.4667
A81: % COSTO MATERIA PRIMA ESTABLECIDA POR EL CENTRO | G81: =G80/G82 -> #DIV/0!
A82: PRECIO POTENCIAL DE VENTA | G82: 0
A83: impuesto al consumo 8% | G83: =G82*0.08 -> 0
A84: PRECIO DE VENTA | G84: =G83+G82 -> 0
A85: PRECIO REAL DE VENTA | G85: =G84 -> 0
A86: % REAL DEL COSTO | G86: =(G80+G83)/G85 -> #DIV/0!

Sheet FICHAS TECNICAS 
A2: CHULETON DE CERDON | B2: CANT. | C2: GRAMAJE O UNIDAD | D2: INGREDIENTES | E2: PREPARACIÓN
A3: TIEMPO DE PREPARACION | C3: gr
A4: 12 minutos | C4: gr
C5: gr
C7: PRECIO VENTA | D7: % Ingredientes
C8: 29900 | D8: 0.35
A12: tener en cuenta
A14: MILANESA DE CERDO | B14: CANT. | C14: GRAMAJE O UNIDAD | D14: INGREDIENTES | E14: PREPARACIÓN
A15: TIEMPO DE PREPARACION | B15: 180 | C15: gr | D15: milanesa de cerdo
A16: 15 minutos | B16: 200 | C16: gr | D16: arroz blanco
B17: 86 | C17: gr | D17: ensalda fresca
B18: 15 | C18: gr | D18: chuney de piña
C19: PRECIO VENTA | D19: % Ingredientes
C20: 29900 | D20: 0.37
A24: tener en cuenta
A26: CORDON BLUE | B26: CANT. | C26: GRAMAJE O UNIDAD | D26: INGREDIENTES | E26: PREPARACIÓN
A27: TIEMPO DE PREPARACION | B27: 180 | C27: gr | D27: cordon blue
A28: 15 minutos | B28: 80 | C28: gr | D28: salsa de mornay
B29: 200 | C29: gr | D29: acompañamiento 1 (pure de papa)
B30: 100 | C30: gr | D30: acompañamiento 2 ( pasta )
C31: PRECIO VENTA | D31: % Ingredientes
C32: 40900 | D32: 0.36
A36: tener en cuenta
A38: LOMITOS EN SALSA MIGNON | B38: CANT. | C38: GRAMAJE O UNIDAD | D38: INGREDIENTES | E38: PREPARACIÓN
A39: TIEMPO DE PREPARACION | B39: 180 | C39: gr | D39: lomitos de res
A40: 15 minutos | B40: 80 | C40: gr | D40: salsa mignon
B41: 200 | C41: gr | D41: cremoso de papa
C43: PRECIO VENTA | D43: % Ingredientes
C44: 36900 | D44: 0.42
A48: tener en cuenta
A50: PIERNA PERNIL ASADO | B50: CANT. | C50: GRAMAJE O UNIDAD | D50: INGREDIENTES | E50: PREPARACIÓN
A51: TIEMPO DE PREPARACION | B51: 180 | C51: gr | D51: pierna pernil
A52: 15 minutos | B52: 86 | C52: gr | D52: ensalada
B53: 200 | C53: gr | D53: papas al horno
B54: 15 gr | C54: gr | D54: chuney piña
C55: PRECIO VENTA | D55: % Ingredientes
C56: 32900 | D56: 0.38
A60: tener en cuenta
A62: FETTUCINNI CON MILANESA DE POLLO | B62: CANT. | C62: GRAMAJE O UNIDAD | D62: INGREDIENTES | E62: PREPARACIÓN
A63: TIEMPO DE PREPARACION | B63: 100 | C63: gr | D63: fettucinni
A64: 15 minutos | B64: 30 | C64: gr | D64: parmesano
B65: 80 | C65: ml | D65: salsa
B66: 180 | C66: gr | D66: milanesa de pollo
C67: PRECIO VENTA | D67: % Ingredientes
C68: 33900 | D68: 0.42
A72: tener en cuenta

Sheet PICADA MALAGANA
A4: RECETA ESTANDAR
A7: PREPARACION | B7: PICADA MALAGANA X 4
F10: FECHA:
A11: INGREDIENTES | D11: CANT. | E11: UNID. | F11: VALORES
F12: UNITARIO | G12: TOTAL | H12: TOTAL GRAMAJE | I12: COSTO POR INGREDIENTE | J12: TOTAL PARA EL SERVICIO
A13: Bondiola | D13: 140 | E13: gr | F13: =36.23 -> 36.23 | G13: =D13*F13 -> 5072.2 | H13: =D13*L13 -> 140 | I13: =F13*H13 -> 5072.2 | J13: COMENSALES | L13: 1
A14: Chicharron | D14: 250 | E14: gr | F14: 38.496 | G14: =D14*F14 -> 9624 | H14: =D14*L13 -> 250 | I14: =F14*H14 -> 9624 | J14: MATERIAS PRIMAS | L14: =SUM(I13:I23) -> 28524.65
A15: Pollo | D15: 250 | E15: gr | F15: 10.55 | G15: =D15*F15 -> 2637.5 | H15: =D15*L13 -> 250 | I15: =F15*H15 -> 2637.5 | J15: COSTO TOTAL | L15: =G31*L13 -> 133200
A16: Chorizo | D16: 2 | E16: unid | F16: 2680 | G16: =D16*F16 -> 5360 | H16: =D16*L13 -> 2 | I16: =F16*H16 -> 5360
A17: Papa amarilla | D17: 150 | E17: gr | F17: 3.5 | G17: =D17*F17 -> 525 | H17: 150 | I17: 525
A18: Papa francesa | D18: 300 | E18: gr | F18: 7.4 | G18: =D18*F18 -> 2220 | H18: =D18*L13 -> 300 | I18: =F18*H18 -> 2220
A19: Arepa | D19: 85 | E19: gr | F19: 10.95 | G19: =D19*F19 -> 930.75 | H19: =D19*L13 -> 85 | I19: =F19*H19 -> 930.75
A20: Tostados | D20: 80 | E20: gr | F20: 5.37 | G20: =D20*F20 -> 429.6 | H20: =D20*L13 -> 80 | I20: =F20*H20 -> 429.6
A21: Salsa chontaduro | D21: 30 | E21: gr | F21: 19 | G21: =D21*F21 -> 570 | H21: =D21*L13 -> 30 | I21: =F21*H21 -> 570
A22: Salsa alioli | D22: 30 | E22: gr | F22: 10.26 | G22: =D22*F22 -> 307.8 | H22: =D22*L13 -> 30 | I22: =F22*H22 -> 307.8
A23: Salsa de ajo | D23: 30 | E23: gr | F23: 28.26 | G23: =D23*F23 -> 847.8 | H23: =D23*L13 -> 30 | I23: =F23*H23 -> 847.8
A24: Enmpaques | G24: 2700 | H24: =D24*L13 -> 0 | I24: =F24*H24 -> 0
A25: COSTO TOTAL DE LOS INGREDIENTES | G25: =SUM(G13:G23) -> 28524.65
A26: MARGEN DE ERROR O VARIACION 10% | G26: =G25*0.1 -> 2852.465
A27: COSTO TOTAL DE LA PREPARACION | G27: =SUM(G25:G26) -> 31377.115
A28: EMPAQUES | G28: =G24 -> 2700
A29: COSTO PORCION | F29: 1 | G29: =G28+G27 -> 34077.115
A30: % COSTO MATERIA PRIMA ESTABLECIDA POR EL CENTRO | G30: =G29/G31 -> 0.2558342
A31: PRECIO POTENCIAL DE VENTA | G31: 133200
A32: impuesto al consumo 8% | G32: 6800
A33: PRECIO DE VENTA | G33: =G32+G31 -> 140000
A34: PRECIO REAL DE VENTA | G34: =G33 -> 140000
A35: % REAL DEL COSTO | G35: =(G29+G32)/G34 -> 0.29197939
A37: RECETA ESTANDAR
A40: PREPARACION | B40: PICADA MALAGANA X 2
F43: FECHA:
A44: INGREDIENTES | D44: CANT. | E44: UNID. | F44: VALORES | H44: TOTAL GRAMAJE | I44: COSTO POR INGREDIENTE | J44: TOTAL PARA EL SERVICIO
F45: UNITARIO | G45: TOTAL | H45: =D46*L45 -> 100 | I45: =F46*H45 -> 3623 | J45: COMENSALES | L45: 1
A46: Bondiola | D46: 100 | E46: gr | F46: =36.23 -> 36.23 | G46: =D46*F46 -> 3623 | H46: =D47*L45 -> 125 | I46: =F47*H46 -> 4812 | J46: MATERIAS PRIMAS | L46: =SUM(I45:I55) -> 16642.15
A47: Chicharron | D47: 125 | E47: gr | F47: 38.496 | G47: =D47*F47 -> 4812 | H47: =D48*L45 -> 125 | I47: =F48*H47 -> 1318.75 | J47: COSTO TOTAL | L47: =G64*L45 -> 78200
A48: Pollo | D48: 125 | E48: gr | F48: 10.55 | G48: =D48*F48 -> 1318.75 | H48: =D49*L45 -> 1 | I48: =F49*H48 -> 2680
A49: Chorizo | D49: 1 | E49: unid | F49: 2680 | G49: =D49*F49 -> 2680 | H49: 100 | I49: =F50*H49 -> 350
A50: Papa amarilla | D50: 100 | E50: gr | F50: 3.5 | G50: =D50*F50 -> 350 | H50: =D51*L45 -> 200 | I50: =F51*H50 -> 1480
A51: Papa francesa | D51: 200 | E51: gr | F51: 7.4 | G51: =D51*F51 -> 1480 | H51: =D52*L45 -> 40 | I51: =F52*H51 -> 438
A52: Arepa | D52: 40 | E52: gr | F52: 10.95 | G52: =D52*F52 -> 438 | H52: =D53*L45 -> 40 | I52: =F53*H52 -> 214.8
A53: Tostados | D53: 40 | E53: gr | F53: 5.37 | G53: =D53*F53 -> 214.8 | H53: =D54*L45 -> 30 | I53: =F54*H53 -> 570
A54: Salsa chontaduro | D54: 30 | E54: gr | F54: 19 | G54: =D54*F54 -> 570 | H54: =D55*L45 -> 30 | I54: =F55*H54 -> 307.8
A55: Salsa alioli | D55: 30 | E55: gr | F55: 10.26 | G55: =D55*F55 -> 307.8 | H55: =D56*L45 -> 30 | I55: =F56*H55 -> 847.8
A56: Salsa de ajo | D56: 30 | E56: gr | F56: 28.26 | G56: =D56*F56 -> 847.8 | H56: =D57*L45 -> 0 | I56: =F57*H56 -> 0
A57: Enmpaques | G57: 2700
A58: COSTO TOTAL DE LOS INGREDIENTES | G58: =SUM(G46:G56) -> 16642.15
A59: MARGEN DE ERROR O VARIACION 10% | G59: =G58*0.1 -> 1664.215
A60: COSTO TOTAL DE LA PREPARACION | G60: =SUM(G58:G59) -> 18306.365
A61: EMPAQUES | G61: =G57 -> 2700
A62: COSTO PORCION | F62: 1 | G62: =G61+G60 -> 21006.365
A63: % COSTO MATERIA PRIMA ESTABLECIDA POR EL CENTRO | G63: =G62/G64 -> 0.26862359
A64: PRECIO POTENCIAL DE VENTA | G64: 78200
A65: impuesto al consumo 8% | G65: 6800
A66: PRECIO DE VENTA | G66: =G65+G64 -> 85000
A67: PRECIO REAL DE VENTA | G67: =G66 -> 85000
A68: % REAL DEL COSTO | G68: =(G62+G65)/G67 -> 0.32713371

Sheet ESPECIALES 
A4: RECETA ESTANDAR
A7: PREPARACION | B7: FILETE DE SALMON CON VERDURAS Y PAPAS AL HORNO
F10: FECHA:
A11: INGREDIENTES | D11: CANT. | E11: UNID. | F11: VALORES
F12: UNITARIO | G12: TOTAL | H12: TOTAL GRAMAJE | I12: COSTO POR INGREDIENTE | J12: TOTAL PARA EL SERVICIO
A13: filete de salmon | D13: 200 | E13: gr | F13: 75.64 | G13: 15100 | H13: =D13*L13 -> 200 | I13: 15100 | J13: COMENSALES | L13: 1
A14: vegetales salteados | D14: 100 | E14: gr | F14: 21.49 | G14: 2164 | H14: =D14*L13 -> 100 | I14: 2164 | J14: MATERIAS PRIMAS | L14: =SUM(I13:I16) -> 21906
A15: papas al horno | D15: 200 | E15: gr | F15: 23.21 | G15: 4642 | H15: =D15*L13 -> 200 | I15: 4642 | J15: COSTO TOTAL | L15: =G22*L13 -> 65000
G16: =D16*F16 -> 0 | H16: =D16*L13 -> 0 | I16: =F16*H16 -> 0
A17: COSTO TOTAL DE LOS INGREDIENTES | G17: =SUM(G13:G16) -> 21906
A18: MARGEN DE ERROR O VARIACION 10% | G18: =G17*0.1 -> 2190.6
A19: COSTO TOTAL DE LA PREPARACION | G19: =SUM(G17:G18) -> 24096.6
A20: COSTO PORCION | F20: 1 | G20: =G19/F20 -> 24096.6
A21: % COSTO MATERIA PRIMA ESTABLECIDA POR EL CENTRO | G21: =G20/G22 -> 0.37071692
A22: PRECIO POTENCIAL DE VENTA | G22: 65000
A23: impuesto al consumo 8% | G23: =G22*0.08 -> 5200
A24: PRECIO DE VENTA | G24: =G23+G22 -> 70200
A25: PRECIO REAL DE VENTA | G25: =G24 -> 70200
A26: % REAL DEL COSTO | G26: =(G20+G23)/G25 -> 0.41733048

Sheet SUB RECETAS
A4: RECETA ESTANDAR
A7: PREPARACION | B7: VEGETALES SALTEADOS
F10: FECHA:
A11: INGREDIENTES | D11: CANT. | E11: UNID. | F11: VALORES
F12: UNITARIO | G12: TOTAL | H12: TOTAL GRAMAJE | I12: COSTO POR INGREDIENTE | J12: TOTAL PARA EL SERVICIO
A13: champiñon | D13: 40 | E13: gr | F13: 34.20 | G13: 1368 | H13: =D13*L13 -> 40 | I13: 1368 | J13: COMENSALES | L13: 1
A14: zanahoria | D14: 20 | E14: gr | F14: 4.10 | G14: 24 | H14: =D14*L13 -> 20 | I14: 24 | J14: MATERIAS PRIMAS | L14: =SUM(I13:I21) -> 2149
A15: tomate cherry | D15: 25 | E15: gr | F15: 14.30 | G15: 357 | H15: =D15*L13 -> 25 | I15: 357 | J15: COSTO TOTAL | L15: =G28*L13 -> 0
A16: cebolla roja | D16: 20 | E16: gr | F16: 5.98 | G16: 120 | H16: =D16*L13 -> 20 | I16: 120
A17: espinaca | D17: 10 | E17: gr | F17: 10.00 | G17: 100 | H17: =D17*L13 -> 10 | I17: 100
A18: ajo | D18: 2 | E18: gr | F18: 11.00 | G18: 22 | H18: =D18*L13 -> 2 | I18: 22
A19: sal | D19: 2 | E19: gr | F19: 2.60 | G19: 5 | H19: =D19*L13 -> 2 | I19: 5
A20: pimineta | D20: 1 | E20: gr | F20: 58.17 | G20: 58 | H20: =D20*L13 -> 1 | I20: 58
A21: soya | D21: 3 | E21: ml | F21: 31.60 | G21: 95 | H21: =D21*L13 -> 3 | I21: 95
G22: =D22*F22 -> 0 | H22: =D22*L13 -> 0 | I22: =F22*H22 -> 0
A23: COSTO TOTAL DE LOS INGREDIENTES | G23: =SUM(G13:G22) -> 2149
A24: MARGEN DE ERROR O VARIACION 10% | G24: =G23*0.1 -> 214.9
A25: COSTO TOTAL DE LA PREPARACION | G25: =SUM(G23:G24) -> 2363.9
A26: COSTO PORCION | F26: 1 | G26: =G25/F26 -> 2363.9
A27: % COSTO MATERIA PRIMA ESTABLECIDA POR EL CENTRO | G27: =G26/G28 -> #DIV/0!
A28: PRECIO POTENCIAL DE VENTA
A29: impuesto al consumo 8% | G29: =G28*0.08 -> 0
A30: PRECIO DE VENTA | G30: =G29+G28 -> 0
A31: PRECIO REAL DE VENTA | G31: =G30 -> 0
A32: % REAL DEL COSTO | G32: =(G26+G29)/G31 -> #DIV/0!
A34: RECETA ESTANDAR
A37: PREPARACION | B37: SUB CHULETON DE CERDO
F40: FECHA:
A41: INGREDIENTES | D41: CANT. | E41: UNID. | F41: VALORES
F42: UNITARIO | G42: TOTAL | H42: TOTAL GRAMAJE | I42: COSTO POR INGREDIENTE | J42: TOTAL PARA EL SERVICIO
A43: chuleton de cerdo | D43: 250 | E43: gr | F43: 14.16 | G43: 3540 | H43: =D43*L43 -> 250 | I43: 3540 | J43: COMENSALES | L43: 1
A44: sal | D44: 5 | E44: gr | F44: 2.60 | G44: 13 | H44: =D44*L43 -> 5 | I44: 13 | J44: MATERIAS PRIMAS | L44: =SUM(I43:I46) -> 3691
A45: pimienta | D45: 2 | E45: gr | F45: 58.17 | G45: 116 | H45: =D45*L43 -> 2 | I45: 116 | J45: COSTO TOTAL | L45: =G53*L43 -> 0
A46: pasta de ajo | D46: 2 | E46: gr | F46: 11.00 | G46: 22 | H46: =D46*L43 -> 2 | I46: 22
G47: =D47*F47 -> 0 | H47: =D47*L43 -> 0 | I47: =F47*H47 -> 0
A48: COSTO TOTAL DE LOS INGREDIENTES | G48: =SUM(G43:G47) -> 3691
A49: MARGEN DE ERROR O VARIACION 10% | G49: =G48*0.1 -> 369.1
A50: COSTO TOTAL DE LA PREPARACION | G50: =SUM(G48:G49) -> 4060.1
A51: COSTO PORCION | F51: 1 | G51: =G50/F51 -> 4060.1
A52: % COSTO MATERIA PRIMA ESTABLECIDA POR EL CENTRO | G52: =G51/G53 -> #DIV/0!
A53: PRECIO POTENCIAL DE VENTA
A54: impuesto al consumo 8% | G54: =G53*0.08 -> 0
A55: PRECIO DE VENTA | G55: =G54+G53 -> 0
A56: PRECIO REAL DE VENTA | G56: =G55 -> 0
A57: % REAL DEL COSTO | G57: =(G51+G54)/G56 -> #DIV/0!
A60: PREPARACION | B60: FILETE DE SALMON
F63: FECHA:
A64: INGREDIENTES | D64: CANT. | E64: UNID. | F64: VALORES
F65: UNITARIO | G65: TOTAL | H65: TOTAL GRAMAJE | I65: COSTO POR INGREDIENTE | J65: TOTAL PARA EL SERVICIO
A66: filete de salmon | D66: 200 | E66: gr | F66: 75.00 | G66: 15000 | H66: =D66*L66 -> 200 | I66: 15000 | J66: COMENSALES | L66: 1
A67: sal | D67: 2 | E67: gr | F67: 2.50 | G67: 5 | H67: =D67*L66 -> 2 | I67: 5 | J67: MATERIAS PRIMAS | L67: =SUM(I66:I70) -> 15005
A68: pimienta | D68: 1 | E68: gr | F68: 58.17 | G68: $ 58.17 | H68: =D68*L66 -> 1 | I68: $ 58.17 | J68: COSTO TOTAL | L68: =G76*L66 -> 0
A69: aceite de ajo y achiote | D69: 2 | E69: ml | F69: 33.22 | G69: $ 66.44 | H69: =D69*L66 -> 2 | I69: $ 66.44
G70: =D70*F70 -> 0 | H70: =D70*L66 -> 0 | I70: =F70*H70 -> 0
A71: COSTO TOTAL DE LOS INGREDIENTES | G71: =SUM(G66:G70) -> 15005
A72: MARGEN DE ERROR O VARIACION 10% | G72: =G71*0.1 -> 1500.5
A73: COSTO TOTAL DE LA PREPARACION | G73: =SUM(G71:G72) -> 16505.5
A74: COSTO PORCION | F74: 1 | G74: =G73/F74 -> 16505.5
A75: % COSTO MATERIA PRIMA ESTABLECIDA POR EL CENTRO | G75: =G74/G76 -> #DIV/0!
A76: PRECIO POTENCIAL DE VENTA
A77: impuesto al consumo 8% | G77: =G76*0.08 -> 0
A78: PRECIO DE VENTA | G78: =G77+G76 -> 0
A79: PRECIO REAL DE VENTA | G79: =G78 -> 0
A80: % REAL DEL COSTO | G80: =(G74+G77)/G79 -> #DIV/0!
A82: RECETA ESTANDAR
A85: PREPARACION | B85: MILANESA DE CERDO
F88: FECHA:
A89: INGREDIENTES | D89: CANT. | E89: UNID. | F89: VALORES
F90: UNITARIO | G90: TOTAL | H90: TOTAL GRAMAJE | I90: COSTO POR INGREDIENTE | J90: TOTAL PARA EL SERVICIO
A91: brazo de cerdo | D91: 200 | E91: gr | F91: 22.00 | G91: 4400 | H91: =D91*L91 -> 200 | I91: 4400 | J91: COMENSALES | L91: 1
A92: harina | D92: 30 | E92: gr | F92: 2.91 | G92: 87 | H92: =D92*L91 -> 30 | I92: 87 | J92: MATERIAS PRIMAS | L92: =SUM(I91:I97) -> 8785
A93: agua | D93: 50 | E93: gr | F93: 26.35 | G93: 1317 | H93: =D93*L91 -> 50 | I93: 1317 | J93: COSTO TOTAL | L93: =G103*L91 -> 0
A94: salsa negra | D94: 10 | E94: gr | F94: 31.60 | G94: 316 | H94: =D94*L91 -> 10 | I94: 316
A95: pasta de ajo | D95: 25 | E95: gr | F95: 11.00 | G95: 275 | H95: =D95*L91 -> 25 | I95: 275
A96: panko | D96: 100 | E96: gr | F96: 23.90 | G96: 2390 | H96: =D96*L91 -> 100 | I96: 2390
G97: =D97*F97 -> 0 | H97: =D97*L91 -> 0 | I97: =F97*H97 -> 0
A98: COSTO TOTAL DE LOS INGREDIENTES | G98: =SUM(G91:G97) -> 8785
A99: MARGEN DE ERROR O VARIACION 10% | G99: =G98*0.1 -> 878.5
A100: COSTO TOTAL DE LA PREPARACION | G100: =SUM(G98:G99) -> 9663.5
A101: COSTO PORCION | F101: 1 | G101: =G100/F101 -> 9663.5
A102: % COSTO MATERIA PRIMA ESTABLECIDA POR EL CENTRO | G102: =G101/G103 -> #DIV/0!
A103: PRECIO POTENCIAL DE VENTA | G103: 0
A104: impuesto al consumo 8% | G104: =G103*0.08 -> 0
A105: PRECIO DE VENTA | G105: =G104+G103 -> 0
A106: PRECIO REAL DE VENTA | G106: =G105 -> 0
A107: % REAL DEL COSTO | G107: =(G101+G104)/G106 -> #DIV/0!
A109: RECETA ESTANDAR
A112: PREPARACION | B112: ARROZ BLANCO
F115: FECHA:
A116: INGREDIENTES | D116: CANT. | E116: UNID. | F116: VALORES
F117: UNITARIO | G117: TOTAL | H117: TOTAL GRAMAJE | I117: COSTO POR INGREDIENTE | J117: TOTAL PARA EL SERVICIO
A118: arroz | D118: 100 | E118: gr | F118: 4.50 | G118: 450 | H118: =D118*L118 -> 100 | I118: 450 | J118: COMENSALES | L118: 1
A119: agua | D119: 200 | E119: gr | F119: 26.35 | G119: 5.27 | H119: =D119*L118 -> 200 | I119: 450 | J119: MATERIAS PRIMAS | L119: =SUM(I118:I122) -> 1098
A120: sal | D120: 15 | E120: gr | F120: 2.60 | G120: 39 | H120: =D120*L118 -> 15 | I120: 39 | J120: COSTO TOTAL | L120: =G128*L118 -> 0
A121: aceite | D121: 20 | E121: gr | F121: 7.95 | G121: 159 | H121: =D121*L118 -> 20 | I121: 159
G122: =D122*F122 -> 0 | H122: =D122*L118 -> 0 | I122: =F122*H122 -> 0
A123: COSTO TOTAL DE LOS INGREDIENTES | G123: =SUM(G118:G122) -> 653.27
A124: MARGEN DE ERROR O VARIACION 10% | G124: =G123*0.1 -> 65.327
A125: COSTO TOTAL DE LA PREPARACION | G125: =SUM(G123:G124) -> 718.597
A126: COSTO PORCION | F126: 1 | G126: =G125/F126 -> 718.597
...

Sheet Compras 22 mayo
B2: COMPRAS | C2: 45799 | E2: COMPRAS | F2: 45800
B3: LICORES PALMIRA | C3: 198800 | E3: QUICENO Y CIA | F3: 18360 | G3: EFECTIVO
B4: LA AMISTAD | C4: 910150 | E4: MEGA FRUVER | F4: 1600 | G4: EFECTIVO
B5: LOS MONOS | C5: 723952 | E5: COMERCIALIZADORA | F5: 3500 | G5: EFECTIVO
B6: CAÑAVERAL | C6: 422817 | E6: LOS MONOS | F6: 244530
B7: SOLO FRUTAS | C7: 324328 | E7: LA AMISTAD | F7: 350050
B8: LOS MONOS | C8: 289500 | E8: CLAVO Y CANELA | F8: 18000 | G8: EFECTIVO | H8: =F3+F4+F5+F8 -> 41460
B9: QUESOS LUIS | C9: 129000 | E9: COM MALTA | F9: 751360
B10: CERVALLE | C10: 121235 | E10: LICORES PALMIRA | F10: 90000
B11: D1 | C11: 21150 | E11: DISTRIDESCUENTOS | F11: 195000
C12: =SUM(C3:C10) -> 3119782 | F12: =SUM(F3:F11) -> 1672400
B14: Saldo tarjeta | C14: 6919379 | E14: Saldo tarjeta | F14: 3365492
